Workbook

Sheet Leeswijzer
A1: Case Fietsatelier Noor bv: gegevens voor de boekhoudapp 3e en 4e jaar
A2: Wat staat hierin? | B2: Alle gegevens van de case: bedrijven, artikelen, documenten (met lijnen), rekeninguittreksels en de sleutel (journaal). Facturen maak je zelf op basis van de tabbladen Documenten en Lijnen.
A3: Jaar 1 = 2026 (3e jaar) | B3: Eerste jaar na de opstart. Januari = voorbeelden uit de cursus. Kwartaal 1 = verplichte opdrachten (in blok). Kwartaal 2 = oefenen, kwartaal 3 = test jezelf, kwartaal 4 = remediëring (telkens alles door elkaar). Eind december: 2 facturen en de afsluiting door de boekhouder (niet voor leerlingen).
A4: Jaar 2 = 2027 (4e jaar) | B4: Consolidatieopdracht: iedereen doet alle kwartalen. Start vanuit een volledig afgewerkt jaar 1 (openingsbalans 1/1/2027 = eindbalans 2026 na afsluiting). Per kwartaal meer gemixt: K1 in blok per soort · K2 gemixt binnen aankoop en binnen verkoop · K3 aankoop en verkoop door elkaar · K4 alles door elkaar. Daarna de afsluiting. '(eventueel enkel tot kwartaal 3, en K4 houden voor remediëring)
A5: Jaar 3 = 2028 (3e graad, oefenen) | B5: Oefendossier in de boekhoudapp van kern 8 (noor.html): het 1e kwartaal 2028 met een afsluiting op 31 maart, zoals MetWear. Beginbalans = eindbalans 2027 na afsluiting. Noor heeft nu personeel (Jonas, arbeider; Lina, bediende deeltijds), een sociaal secretariaat (Loonwijs), een verzekeraar (Gerzo) en een opslagruimte (Immo Vaartkom). De stukken staan per les (5 à 6 per les): kortingen · kosten, verpakking, investeringen · creditnota's en over te dragen kosten · verkopen (2 lessen) · loonstaten · RSZ en personeelskosten · financiële verrichtingen · btw, eindejaar en resultaat. Tabbladen J3 …; gemaakt door hulpmiddelen/noor/ in de repo boekhouding_DeMet.
A6: Jaar 4 (3e graad, consolidatie) | B6: Nog te maken: alle stukken door elkaar, als eindopdracht (vanaf volgend schooljaar in de plaats van MetWear).
A7: Afspraken jaar 3 | B7: MAR van de 3e graad (js/mar.js) plus 700000 voor herstellingen. Over te dragen kosten: de factuur volledig als kost, bij de afsluiting het deel na 31/3 naar 490000 (OTK). Lonen: RSZ werknemer 13,07%, werkgever 25%; RSZ en voorheffing via factuur van Loonwijs (440000). Afschrijvingen: een kwart van de jaarafschrijving. Lening: deel dat binnen 12 maanden vervalt naar 423000. Belasting 20%, wettelijke reserve 5% van de winst na belasting.
A8: Volgorde jaar 2 | B8: K1 tot K3: aankoop, verkoop, btw-verrekening, financieel (de volgorde van de cursus). K4: chronologisch.
A9: Kwartaal | B9: Een boekhoudperiode in de case, niet de periode in het schooljaar.
A10: Volgorde | B10: Kolom "Volgorde in set" in Documenten en Uittreksels: in die volgorde zet je de documenten open in de app.
A11: Formules | B11: Bedragen op de lijnen, totalen per document, saldi op de uittreksels, proefbalans en voorraad zijn formules. Pas je een aantal of prijs aan op Lijnen, dan rekenen de totalen mee. Het journaal (sleutel) is NIET gekoppeld: laat de case dan opnieuw genereren met het script.
A12: Controles | B12: Kolom "Controle D-C" in Documenten moet overal 0 zijn. Proefbalans: totaal = 0. Voorraad: waarde inventaris = saldo 340000 na afsluiting.
A13: Rekeningen | B13: MAR 2e graad (tabblad en bestand mar 2e graad.js): een selectie uit het MAR van de 3e graad, 6 cijfers, plus 600000 Aankopen grondstoffen en 700000 Verkopen en dienstprestaties. Btw op creditnota’s: 411200 (uitgaande CN) en 451200 (inkomende CN).
... A18: Fictief | B18: Alle bedrijven, adressen, btw-nummers (BE 0999...) en rekeningnummers (BE00...) zijn fictief.
A20: Kleur per set
A21: CURSUS
A22: VERPLICHT
A23: OEFEN
A24: TJ
A25: REMEDIERING
A26: BOEKHOUDER
A27: K1
A28: K2
A29: K3
A30: K4
A31: AFSLUITING

Sheet Overzicht sets
A1: Jaar | B1: Set | C1: AK | D1: CN-AK | E1: VK | F1: CN-VK | G1: DO | H1: KAS | I1: MEMO | J1: Uittreksels | K1: Gevraagd (AK / CN-AK / VK / CN-VK / DO)
A2: 1 | B2: CURSUS | C2: =COUNTIFS('J1 Documenten'!$C:$C,$B2,'J1 Documenten'!$E:$E,"AK") | D2: =COUNTIFS('J1 Documenten'!$C:$C,$B2,'J1 Documenten'!$E:$E,"CN-AK") | E2: =COUNTIFS('J1 Documenten'!$C:$C,$B2,'J1 Documenten'!$E:$E,"VK") | F2: =COUNTIFS('J1 Documenten'!$C:$C,$B2,'J1 Documenten'!$E:$E,"CN-VK") | G2: =COUNTIFS('J1 Documenten'!$C:$C,$B2,'J1 Documenten'!$E:$E,"DO") | H2: =COUNTIFS('J1 Documenten'!$C:$C,$B2,'J1 Documenten'!$E:$E,"KAS") | I2: =COUNTIFS('J1 Documenten'!$C:$C,$B2,'J1 Documenten'!$E:$E,"MEMO") | J2: 3
A3: 1 | B3: VERPLICHT | C3: =COUNTIFS('J1 Documenten'!$C:$C,$B3,'J1 Documenten'!$E:$E,"AK") | D3: =COUNTIFS('J1 Documenten'!$C:$C,$B3,'J1 Documenten'!$E:$E,"CN-AK") | E3: =COUNTIFS('J1 Documenten'!$C:$C,$B3,'J1 Documenten'!$E:$E,"VK") | F3: =COUNTIFS('J1 Documenten'!$C:$C,$B3,'J1 Documenten'!$E:$E,"CN-VK") | G3: =COUNTIFS('J1 Documenten'!$C:$C,$B3,'J1 Documenten'!$E:$E,"DO") | H3: =COUNTIFS('J1 Documenten'!$C:$C,$B3,'J1 Documenten'!$E:$E,"KAS") | I3: =COUNTIFS('J1 Documenten'!$C:$C,$B3,'J1 Documenten'!$E:$E,"MEMO") | J3: 4 | K3: 5 / 3 / 5 / 3 / 3
A4: 1 | B4: OEFEN | C4: =COUNTIFS('J1 Documenten'!$C:$C,$B4,'J1 Documenten'!$E:$E,"AK") | D4: =COUNTIFS('J1 Documenten'!$C:$C,$B4,'J1 Documenten'!$E:$E,"CN-AK") | E4: =COUNTIFS('J1 Documenten'!$C:$C,$B4,'J1 Documenten'!$E:$E,"VK") | F4: =COUNTIFS('J1 Documenten'!$C:$C,$B4,'J1 Documenten'!$E:$E,"CN-VK") | G4: =COUNTIFS('J1 Documenten'!$C:$C,$B4,'J1 Documenten'!$E:$E,"DO") | H4: =COUNTIFS('J1 Documenten'!$C:$C,$B4,'J1 Documenten'!$E:$E,"KAS") | I4: =COUNTIFS('J1 Documenten'!$C:$C,$B4,'J1 Documenten'!$E:$E,"MEMO") | J4: 3 | K4: extra set samen: 10 / 5 / 10 / 5 / 2
A5: 1 | B5: TJ | C5: =COUNTIFS('J1 Documenten'!$C:$C,$B5,'J1 Documenten'!$E:$E,"AK") | D5: =COUNTIFS('J1 Documenten'!$C:$C,$B5,'J1 Documenten'!$E:$E,"CN-AK") | E5: =COUNTIFS('J1 Documenten'!$C:$C,$B5,'J1 Documenten'!$E:$E,"VK") | F5: =COUNTIFS('J1 Documenten'!$C:$C,$B5,'J1 Documenten'!$E:$E,"CN-VK") | G5: =COUNTIFS('J1 Documenten'!$C:$C,$B5,'J1 Documenten'!$E:$E,"DO") | H5: =COUNTIFS('J1 Documenten'!$C:$C,$B5,'J1 Documenten'!$E:$E,"KAS") | I5: =COUNTIFS('J1 Documenten'!$C:$C,$B5,'J1 Documenten'!$E:$E,"MEMO") | J5: 3 | K5: (verdeeld over oefenen, TJ en remediëring)
A6: 1 | B6: REMEDIERING | C6: =COUNTIFS('J1 Documenten'!$C:$C,$B6,'J1 Documenten'!$E:$E,"AK") | D6: =COUNTIFS('J1 Documenten'!$C:$C,$B6,'J1 Documenten'!$E:$E,"CN-AK") | E6: =COUNTIFS('J1 Documenten'!$C:$C,$B6,'J1 Documenten'!$E:$E,"VK") | F6: =COUNTIFS('J1 Documenten'!$C:$C,$B6,'J1 Documenten'!$E:$E,"CN-VK") | G6: =COUNTIFS('J1 Documenten'!$C:$C,$B6,'J1 Documenten'!$E:$E,"DO") | H6: =COUNTIFS('J1 Documenten'!$C:$C,$B6,'J1 Documenten'!$E:$E,"KAS") | I6: =COUNTIFS('J1 Documenten'!$C:$C,$B6,'J1 Documenten'!$E:$E,"MEMO") | J6: 4
A7: 1 | B7: BOEKHOUDER | C7: =COUNTIFS('J1 Documenten'!$C:$C,$B7,'J1 Documenten'!$E:$E,"AK") | D7: =COUNTIFS('J1 Documenten'!$C:$C,$B7,'J1 Documenten'!$E:$E,"CN-AK") | E7: =COUNTIFS('J1 Documenten'!$C:$C,$B7,'J1 Documenten'!$E:$E,"VK") | F7: =COUNTIFS('J1 Documenten'!$C:$C,$B7,'J1 Documenten'!$E:$E,"CN-VK") | G7: =COUNTIFS('J1 Documenten'!$C:$C,$B7,'J1 Documenten'!$E:$E,"DO") | H7: =COUNTIFS('J1 Documenten'!$C:$C,$B7,'J1 Documenten'!$E:$E,"KAS") | I7: =COUNTIFS('J1 Documenten'!$C:$C,$B7,'J1 Documenten'!$E:$E,"MEMO") | J7: 0
A9: 2 | B9: K1 | C9: =COUNTIFS('J2 Documenten'!$C:$C,$B9,'J2 Documenten'!$E:$E,"AK") | D9: =COUNTIFS('J2 Documenten'!$C:$C,$B9,'J2 Documenten'!$E:$E,"CN-AK") | E9: =COUNTIFS('J2 Documenten'!$C:$C,$B9,'J2 Documenten'!$E:$E,"VK") | F9: =COUNTIFS('J2 Documenten'!$C:$C,$B9,'J2 Documenten'!$E:$E,"CN-VK") | G9: =COUNTIFS('J2 Documenten'!$C:$C,$B9,'J2 Documenten'!$E:$E,"DO") | H9: =COUNTIFS('J2 Documenten'!$C:$C,$B9,'J2 Documenten'!$E:$E,"KAS") | I9: =COUNTIFS('J2 Documenten'!$C:$C,$B9,'J2 Documenten'!$E:$E,"MEMO") | J9: 8 | K9: in blok per soort
A10: 2 | B10: K2 | C10: =COUNTIFS('J2 Documenten'!$C:$C,$B10,'J2 Documenten'!$E:$E,"AK") | D10: =COUNTIFS('J2 Documenten'!$C:$C,$B10,'J2 Documenten'!$E:$E,"CN-AK") | E10: =COUNTIFS('J2 Documenten'!$C:$C,$B10,'J2 Documenten'!$E:$E,"VK") | F10: =COUNTIFS('J2 Documenten'!$C:$C,$B10,'J2 Documenten'!$E:$E,"CN-VK") | G10: =COUNTIFS('J2 Documenten'!$C:$C,$B10,'J2 Documenten'!$E:$E,"DO") | H10: =COUNTIFS('J2 Documenten'!$C:$C,$B10,'J2 Documenten'!$E:$E,"KAS") | I10: =COUNTIFS('J2 Documenten'!$C:$C,$B10,'J2 Documenten'!$E:$E,"MEMO") | J10: 5 | K10: gemixt binnen aankoop / verkoop
A11: 2 | B11: K3 | C11: =COUNTIFS('J2 Documenten'!$C:$C,$B11,'J2 Documenten'!$E:$E,"AK") | D11: =COUNTIFS('J2 Documenten'!$C:$C,$B11,'J2 Documenten'!$E:$E,"CN-AK") | E11: =COUNTIFS('J2 Documenten'!$C:$C,$B11,'J2 Documenten'!$E:$E,"VK") | F11: =COUNTIFS('J2 Documenten'!$C:$C,$B11,'J2 Documenten'!$E:$E,"CN-VK") | G11: =COUNTIFS('J2 Documenten'!$C:$C,$B11,'J2 Documenten'!$E:$E,"DO") | H11: =COUNTIFS('J2 Documenten'!$C:$C,$B11,'J2 Documenten'!$E:$E,"KAS") | I11: =COUNTIFS('J2 Documenten'!$C:$C,$B11,'J2 Documenten'!$E:$E,"MEMO") | J11: 5 | K11: aankoop en verkoop door elkaar
A12: 2 | B12: K4 | C12: =COUNTIFS('J2 Documenten'!$C:$C,$B12,'J2 Documenten'!$E:$E,"AK") | D12: =COUNTIFS('J2 Documenten'!$C:$C,$B12,'J2 Documenten'!$E:$E,"CN-AK") | E12: =COUNTIFS('J2 Documenten'!$C:$C,$B12,'J2 Documenten'!$E:$E,"VK") | F12: =COUNTIFS('J2 Documenten'!$C:$C,$B12,'J2 Documenten'!$E:$E,"CN-VK") | G12: =COUNTIFS('J2 Documenten'!$C:$C,$B12,'J2 Documenten'!$E:$E,"DO") | H12: =COUNTIFS('J2 Documenten'!$C:$C,$B12,'J2 Documenten'!$E:$E,"KAS") | I12: =COUNTIFS('J2 Documenten'!$C:$C,$B12,'J2 Documenten'!$E:$E,"MEMO") | J12: 5 | K12: alles door elkaar
A13: 2 | B13: AFSLUITING | C13: =COUNTIFS('J2 Documenten'!$C:$C,$B13,'J2 Documenten'!$E:$E,"AK") | D13: =COUNTIFS('J2 Documenten'!$C:$C,$B13,'J2 Documenten'!$E:$E,"CN-AK") | E13: =COUNTIFS('J2 Documenten'!$C:$C,$B13,'J2 Documenten'!$E:$E,"VK") | F13: =COUNTIFS('J2 Documenten'!$C:$C,$B13,'J2 Documenten'!$E:$E,"CN-VK") | G13: =COUNTIFS('J2 Documenten'!$C:$C,$B13,'J2 Documenten'!$E:$E,"DO") | H13: =COUNTIFS('J2 Documenten'!$C:$C,$B13,'J2 Documenten'!$E:$E,"KAS") | I13: =COUNTIFS('J2 Documenten'!$C:$C,$B13,'J2 Documenten'!$E:$E,"MEMO") | J13: 0
A14: 3 | B14: Aankopen 1 · kortingen | C14: 6 | D14: 0 | E14: 0 | F14: 0 | G14: 0 | H14: 0 | I14: 0 | J14: 0
A15: 3 | B15: Aankopen 2 · kosten, verpakking en investeringen | C15: 6 | D15: 0 | E15: 0 | F15: 0 | G15: 0 | H15: 0 | I15: 0 | J15: 0
A16: 3 | B16: Aankopen 3 · creditnota's en over te dragen kosten | C16: 2 | D16: 3 | E16: 0 | F16: 0 | G16: 0 | H16: 0 | I16: 0 | J16: 0
A17: 3 | B17: Verkopen 1 · handelskorting en kosten | C17: 0 | D17: 0 | E17: 6 | F17: 0 | G17: 0 | H17: 0 | I17: 0 | J17: 0
A18: 3 | B18: Verkopen 2 · verpakking, creditnota's, financiële korting | C18: 0 | D18: 0 | E18: 3 | F18: 2 | G18: 1 | H18: 0 | I18: 0 | J18: 0
A19: 3 | B19: Lonen 1 · loonstaten | C19: 0 | D19: 0 | E19: 0 | F19: 0 | G19: 0 | H19: 0 | I19: 0 | J19: 0 | K19: loonstaten: 6
A20: 3 | B20: Lonen 2 · RSZ, voorheffing en personeelskosten | C20: 6 | D20: 0 | E20: 0 | F20: 0 | G20: 0 | H20: 0 | I20: 0 | J20: 0
A21: 3 | B21: Financiële verrichtingen | C21: 0 | D21: 0 | E21: 0 | F21: 0 | G21: 0 | H21: 2 | I21: 0 | J21: 5
A22: 3 | B22: BTW-verwerking | C22: 0 | D22: 0 | E22: 0 | F22: 0 | G22: 0 | H22: 0 | I22: 1 | J22: 0
A23: 3 | B23: Eindejaarsverrichtingen | C23: 0 | D23: 0 | E23: 0 | F23: 0 | G23: 0 | H23: 0 | I23: 3 | J23: 0
A24: 3 | B24: Resultaatverwerking | C24: 0 | D24: 0 | E24: 0 | F24: 0 | G24: 0 | H24: 0 | I24: 2 | J24: 0

Sheet Bedrijven
A1: Code | B1: Naam | C1: Rol | D1: Adres | E1: Postcode en gemeente | F1: Btw-nummer | G1: IBAN | H1: Wat doet het bedrijf?
A2: NOOR | B2: Fietsatelier Noor bv | C2: eigen bedrijf | D2: Fietsstraat 12 | E2: 3000 Leuven | F2: BE 0999.000.101 | G2: BE00 0000 0000 0101 | H2: fietsenwinkel en -herstelling, zaakvoerder Noor Benali
A3: VELO | B3: Velomax bv | C3: leverancier | D3: Industrieweg 8 | E3: 9000 Gent | F3: BE 0999.000.201 | G3: BE00 0000 0000 0201 | H3: groothandel fietsen
A4: SPAAK | B4: Spaakwerk bv | C4: leverancier | D4: Zandstraat 22 | E4: 3500 Hasselt | F4: BE 0999.000.202 | G4: BE00 0000 0000 0202 | H4: groothandel onderdelen
A5: HELM | B5: HelmHuis bv | C5: leverancier | D5: Kortrijksesteenweg 101 | E5: 8500 Kortrijk | F5: BE 0999.000.203 | G5: BE00 0000 0000 0203 | H5: groothandel helmen en sloten
A6: STROOM | B6: Stroomkracht nv | C6: leverancier | D6: Energielaan 1 | E6: 1000 Brussel | F6: BE 0999.000.204 | G6: BE00 0000 0000 0204 | H6: energieleverancier
A7: NET | B7: Netlink bv | C7: leverancier | D7: Antwerpsesteenweg 5 | E7: 2800 Mechelen | F7: BE 0999.000.205 | G7: BE00 0000 0000 0205 | H7: internet en telefonie
A8: PEET | B8: Drukkerij Peeters bv | C8: leverancier | D8: Diestsestraat 77 | E8: 3000 Leuven | F8: BE 0999.000.206 | G8: BE00 0000 0000 0206 | H8: drukwerk en reclame
A9: NOWAK | B9: Boekhoudkantoor Nowak | C9: leverancier | D9: Tiensesteenweg 150 | E9: 3010 Kessel-Lo | F9: BE 0999.000.207 | G9: BE00 0000 0000 0207 | H9: boekhouder (Marta Nowak)
A10: DEPREZ | B10: Deprez Werkplaatsinrichting bv | C10: leverancier | D10: Ninoofsesteenweg 40 | E10: 1700 Dilbeek | F10: BE 0999.000.208 | G10: BE00 0000 0000 0208 | H10: werkbanken en montagestandaards
A11: KASSA | B11: Kassatech bv | C11: leverancier | D11: Researchpark 3 | E11: 3001 Heverlee | F11: BE 0999.000.209 | G11: BE00 0000 0000 0209 | H11: kassasystemen en computers
A12: MOREAU | B12: Garage Moreau bv | C12: leverancier | D12: Waversesteenweg 200 | E12: 3090 Overijse | F12: BE 0999.000.210 | G12: BE00 0000 0000 0210 | H12: bestelwagens
... A23: ZONNE | B23: Woonzorgcentrum Zonnehof vzw | C23: klant | D23: Kloosterweg 3 | E23: 3020 Herent | F23: BE 0999.000.311 | G23: BE00 0000 0000 0311 | H23: woonzorgcentrum
A24: BANK | B24: Banco Leuven | C24: bank | D24: Ladeuzeplein 1 | E24: 3000 Leuven | H24: bank van Noor, ook kredietgever
A25: LOONW | B25: Loonwijs vzw | C25: leverancier | D25: Brusselsesteenweg 61 | E25: 3000 Leuven | F25: BE 0999.000.211 | G25: BE00 0000 0000 0211 | H25: sociaal secretariaat (vanaf jaar 3)
A26: GERZO | B26: Gerzo Verzekeringen nv | C26: leverancier | D26: Martelarenplein 9 | E26: 3000 Leuven | F26: BE 0999.000.212 | G26: BE00 0000 0000 0212 | H26: verzekeraar (bestelwagen, arbeidsongevallen) (vanaf jaar 3)
A27: VAART | B27: Immo Vaartkom bv | C27: leverancier | D27: Vaartkom 30 | E27: 3000 Leuven | F27: BE 0999.000.213 | G27: BE00 0000 0000 0213 | H27: verhuurt de opslagruimte naast de winkel (vanaf jaar 3)
A28: PREV | B28: Preventa vzw | C28: leverancier | D28: Diestsevest 14 | E28: 3000 Leuven | F28: BE 0999.000.214 | G28: BE00 0000 0000 0214 | H28: externe dienst voor preventie en bescherming op het werk (vanaf jaar 3)

Sheet Artikelen
A1: Code | B1: Omschrijving | C1: Leverancier | D1: Aankoopprijs excl. btw | E1: Verkoopprijs excl. btw | F1: Btw | G1: Verkoopprijs incl. btw (particulier)
A2: STAD | B2: Stadsfiets City, 7 versnellingen | C2: Velomax bv | D2: 400 | E2: 600 | F2: 0.21 | G2: =E2*(1+F2)
A3: EBIKE | B3: E-bike Comfort, 500 Wh | C3: Velomax bv | D3: 1400 | E3: 2000 | F3: 0.21 | G3: =E3*(1+F3)
A4: BAK | B4: Bakfiets Cargo, 2 wielen | C4: Velomax bv | D4: 1800 | E4: 2600 | F4: 0.21 | G4: =E4*(1+F4)
A5: KIND | B5: Kinderfiets 20 inch | C5: Velomax bv | D5: 150 | E5: 250 | F5: 0.21 | G5: =E5*(1+F5)
A6: HELM | B6: Fietshelm Urban | C6: HelmHuis bv | D6: 30 | E6: 50 | F6: 0.21 | G6: =E6*(1+F6)
A7: SLOT | B7: Plooislot | C7: HelmHuis bv | D7: 20 | E7: 35 | F7: 0.21 | G7: =E7*(1+F7)
A8: BAND | B8: Buitenband 28 inch | C8: Spaakwerk bv | D8: 15 | E8: 25 | F8: 0.21 | G8: =E8*(1+F8)
A9: KET | B9: Fietsketting 8 speed | C9: Spaakwerk bv | D9: 10 | E9: 20 | F9: 0.21 | G9: =E9*(1+F9)
A10: LAMP | B10: Verlichtingsset LED | C10: Spaakwerk bv | D10: 25 | E10: 40 | F10: 0.21 | G10: =E10*(1+F10)
A12: Diensten
A13: HERST | B13: Herstelling (arbeid, per stuk) | E13: 50 | F13: 0.06 | G13: =E13*(1+F13)
A14: ONDH | B14: Onderhoudsbeurt (arbeid, per fiets) | E14: 60 | F14: 0.06 | G14: =E14*(1+F14)

Sheet MAR 2e graad
A1: Rekening | B1: Naam | C1: A/P/K/O | D1: Klasse | E1: Klasse omschrijving | F1: Rubriek | G1: Rubriek omschrijving | H1: Gebruikt in de case
A2: 100000 | B2: Geplaatst kapitaal | C2: P | D2: 1 | E2: Eigen vermogen | F2: 10 | G2: Kapitaal | H2: openingsbalans
A3: 140000 | B3: Overgedragen winst | C3: P | D3: 1 | E3: Eigen vermogen | F3: 14 | G3: Overgedragen resultaat | H3: jaar 1 + jaar 2
A4: 141000 | B4: Overgedragen verlies (-) | C4: P | D4: 1 | E4: Eigen vermogen | F4: 14 | G4: Overgedragen resultaat
A5: 173000 | B5: Schulden aan kredietinstellingen | C5: P | D5: 1 | E5: Eigen vermogen | F5: 17 | G5: Schulden op meer dan 1 jaar | H5: jaar 2
A6: 221000 | B6: Gebouwen | C6: A | D6: 2 | E6: Vaste activa | F6: 22 | G6: Terreinen & gebouwen
A7: 221009 | B7: Afschrijvingen op gebouwen (-) | C7: A | D7: 2 | E7: Vaste activa | F7: 22 | G7: Terreinen & gebouwen
A8: 230000 | B8: Installaties | C8: A | D8: 2 | E8: Vaste activa | F8: 23 | G8: Installaties, machines & uitrusting | H8: jaar 1
A9: 230009 | B9: Afschrijvingen op installaties (-) | C9: A | D9: 2 | E9: Vaste activa | F9: 23 | G9: Installaties, machines & uitrusting | H9: jaar 1 + jaar 2
A10: 232000 | B10: Uitrusting | C10: A | D10: 2 | E10: Vaste activa | F10: 23 | G10: Installaties, machines & uitrusting | H10: jaar 1
A11: 232009 | B11: Afschrijvingen op uitrusting (-) | C11: A | D11: 2 | E11: Vaste activa | F11: 23 | G11: Installaties, machines & uitrusting | H11: jaar 1 + jaar 2
A12: 240000 | B12: Meubilair | C12: A | D12: 2 | E12: Vaste activa | F12: 24 | G12: Meubilair & rollend materieel
A13: 240009 | B13: Afschrijvingen op meubilair (-) | C13: A | D13: 2 | E13: Vaste activa | F13: 24 | G13: Meubilair & rollend materieel
A14: 240200 | B14: Computers | C14: A | D14: 2 | E14: Vaste activa | F14: 24 | G14: Meubilair & rollend materieel | H14: jaar 1
A15: 240209 | B15: Afschrijvingen op computers (-) | C15: A | D15: 2 | E15: Vaste activa | F15: 24 | G15: Meubilair & rollend materieel | H15: jaar 1 + jaar 2
A16: 241000 | B16: Rollend materieel | C16: A | D16: 2 | E16: Vaste activa | F16: 24 | G16: Meubilair & rollend materieel | H16: jaar 2
A17: 241009 | B17: Afschrijvingen op rollend materieel (-) | C17: A | D17: 2 | E17: Vaste activa | F17: 24 | G17: Meubilair & rollend materieel | H17: jaar 1 + jaar 2
A18: 340000 | B18: Voorraad handelsgoederen | C18: A | D18: 3 | E18: Voorraden | F18: 34 | G18: Voorraden | H18: jaar 1 + jaar 2
A19: 400000 | B19: Handelsdebiteuren | C19: A | D19: 4 | E19: Vorderingen en schulden op ten hoogste 1 jaar | F19: 40 | G19: Handelsvorderingen | H19: jaar 1 + jaar 2
A20: 411000 | B20: Terug te vorderen btw-saldo | C20: A | D20: 4 | E20: Vorderingen en schulden op ten hoogste 1 jaar | F20: 41 | G20: Overige vorderingen | H20: jaar 2
A21: 411100 | B21: Aftrekbare btw | C21: A | D21: 4 | E21: Vorderingen en schulden op ten hoogste 1 jaar | F21: 41 | G21: Overige vorderingen | H21: jaar 1 + jaar 2
A22: 411200 | B22: Aftrekbare btw op uitgaande creditnota’s | C22: A | D22: 4 | E22: Vorderingen en schulden op ten hoogste 1 jaar | F22: 41 | G22: Overige vorderingen | H22: jaar 1 + jaar 2
A23: 418000 | B23: Terug te vorderen verpakking | C23: A | D23: 4 | E23: Vorderingen en schulden op ten hoogste 1 jaar | F23: 41 | G23: Overige vorderingen | H23: jaar 2
A24: 423000 | B24: Binnen het jaar vervallende schulden aan kredietinstellingen | C24: P | D24: 4 | E24: Vorderingen en schulden op ten hoogste 1 jaar | F24: 42 | G24: Schulden op maar dan 1 jaar die binnen het jaar vervallen
A25: 440000 | B25: Leveranciers | C25: P | D25: 4 | E25: Vorderingen en schulden op ten hoogste 1 jaar | F25: 44 | G25: Handelsschulden | H25: jaar 1 + jaar 2
A26: 451000 | B26: Te betalen btw-saldo | C26: P | D26: 4 | E26: Vorderingen en schulden op ten hoogste 1 jaar | F26: 45 | G26: Schulden mbt belastingen, ... | H26: jaar 1 + jaar 2
A27: 451100 | B27: Verschuldigde btw | C27: P | D27: 4 | E27: Vorderingen en schulden op ten hoogste 1 jaar | F27: 45 | G27: Schulden mbt belastingen, ... | H27: jaar 1 + jaar 2
A28: 451200 | B28: Verschuldigde btw op inkomende creditnota’s | C28: P | D28: 4 | E28: Vorderingen en schulden op ten hoogste 1 jaar | F28: 45 | G28: Schulden mbt belastingen, ... | H28: jaar 1 + jaar 2
A29: 488000 | B29: Terug te betalen verpakking | C29: P | D29: 4 | E29: Vorderingen en schulden op ten hoogste 1 jaar | F29: 48 | G29: Diverse schulden | H29: jaar 2
A30: 550000 | B30: Bankrekening | C30: A | D30: 5 | E30: Liquide middelen | F30: 55 | G30: Bank | H30: jaar 1 + jaar 2
A31: 570000 | B31: Kas | C31: A | D31: 5 | E31: Liquide middelen | F31: 57 | G31: Kas | H31: jaar 1 + jaar 2
A32: 580000 | B32: Interne overboekingen | C32: A | D32: 5 | E32: Liquide middelen | F32: 58 | G32: Interne overboekingen | H32: jaar 2
A33: 600000 | B33: Aankopen grondstoffen | C33: K | D33: 6 | E33: Kosten | F33: 60 | G33: Handelsgoederen, grond- en hulpstoffen
A34: 604000 | B34: Aankopen handelsgoederen | C34: K | D34: 6 | E34: Kosten | F34: 60 | G34: Handelsgoederen, grond- en hulpstoffen | H34: jaar 1 + jaar 2
A35: 604010 | B35: Retours op aankopen (-) | C35: K | D35: 6 | E35: Kosten | F35: 60 | G35: Handelsgoederen, grond- en hulpstoffen | H35: jaar 1 + jaar 2
A36: 604020 | B36: Handelskorting op aankopen (-) | C36: K | D36: 6 | E36: Kosten | F36: 60 | G36: Handelsgoederen, grond- en hulpstoffen | H36: jaar 2
A37: 604030 | B37: Aankoopkosten | C37: K | D37: 6 | E37: Kosten | F37: 60 | G37: Handelsgoederen, grond- en hulpstoffen | H37: jaar 2
A38: 609400 | B38: Voorraadwijzigingen handelsgoederen | C38: K | D38: 6 | E38: Kosten | F38: 60 | G38: Handelsgoederen, grond- en hulpstoffen | H38: jaar 1 + jaar 2
A39: 611000 | B39: Huur en huurlasten | C39: K | D39: 6 | E39: Kosten | F39: 61 | G39: Diensten en diverse goederen
A40: 611800 | B40: Onderhoud en herstellingen rollend materieel | C40: K | D40: 6 | E40: Kosten | F40: 61 | G40: Diensten en diverse goederen
A41: 612000 | B41: Kantoorbenodigdheden en drukwerk | C41: K | D41: 6 | E41: Kosten | F41: 61 | G41: Diensten en diverse goederen
A42: 612700 | B42: Verbruik elektriciteit | C42: K | D42: 6 | E42: Kosten | F42: 61 | G42: Diensten en diverse goederen | H42: jaar 1 + jaar 2
A43: 613200 | B43: Erelonen boekhouders | C43: K | D43: 6 | E43: Kosten | F43: 61 | G43: Diensten en diverse goederen | H43: jaar 1
A44: 616200 | B44: Telefoon, gsm | C44: K | D44: 6 | E44: Kosten | F44: 61 | G44: Diensten en diverse goederen
A45: 616300 | B45: Internetkosten | C45: K | D45: 6 | E45: Kosten | F45: 61 | G45: Diensten en diverse goederen | H45: jaar 1 + jaar 2
A46: 616520 | B46: Publiciteitskosten | C46: K | D46: 6 | E46: Kosten | F46: 61 | G46: Diensten en diverse goederen | H46: jaar 1
A47: 630200 | B47: Afschrijvingen op materiële vaste activa | C47: K | D47: 6 | E47: Kosten | F47: 63 | G47: Afschrijvingen | H47: jaar 1 + jaar 2
A48: 630300 | B48: Afschrijvingen op meubilair en rollend materieel | C48: K | D48: 6 | E48: Kosten | F48: 63 | G48: Afschrijvingen | H48: jaar 1 + jaar 2
A49: 650000 | B49: Rente, commissies en kosten verbonden aan schulden | C49: K | D49: 6 | E49: Kosten | F49: 65 | G49: Financiële kosten | H49: jaar 2
A50: 657000 | B50: Betalingskortingen aan klanten | C50: K | D50: 6 | E50: Kosten | F50: 65 | G50: Financiële kosten | H50: jaar 2
A51: 693000 | B51: Over te dragen winst | C51: K | D51: 6 | E51: Kosten | F51: 69 | G51: Resultaatverwerking | H51: jaar 1 + jaar 2
A52: 700000 | B52: Verkopen en dienstprestaties | C52: O | D52: 7 | E52: Opbrengsten | F52: 70 | G52: Omzet | H52: jaar 1 + jaar 2
A53: 704000 | B53: Verkopen handelsgoederen | C53: O | D53: 7 | E53: Opbrengsten | F53: 70 | G53: Omzet | H53: jaar 1 + jaar 2
A54: 704010 | B54: Retours op verkopen (-) | C54: O | D54: 7 | E54: Opbrengsten | F54: 70 | G54: Omzet | H54: jaar 1 + jaar 2
A55: 704020 | B55: Handelskorting op verkopen (-) | C55: O | D55: 7 | E55: Opbrengsten | F55: 70 | G55: Omzet | H55: jaar 2
A56: 746000 | B56: Doorgerekende kosten | C56: O | D56: 7 | E56: Opbrengsten | F56: 74 | G56: Andere bedrijfsopbrengsten | H56: jaar 2
A57: 757000 | B57: Betalingskortingen van leveranciers | C57: O | D57: 7 | E57: Opbrengsten | F57: 75 | G57: Financiële opbrengsten | H57: jaar 2
A58: 793000 | B58: Over te dragen verlies | C58: O | D58: 7 | E58: Opbrengsten | F58: 79 | G58: Resultaatverwerking
B60: Oranje = nieuw t.o.v. het MAR van de 3e graad (mar 3e graad.js)

Sheet J1 Lijnen
A1: ID | B1: Documentnr | C1: Soort doc | D1: Lijn | E1: Soort lijn | F1: Artikel | G1: Omschrijving | H1: Aantal | I1: Eenheidsprijs | J1: Bedrag excl. btw | K1: Btw % | L1: Btw
A2: C01 | B2: 2026-118 | C2: AK | D2: 1 | E2: artikel | F2: STAD | G2: Stadsfiets City, 7 versnellingen | H2: 10 | I2: 400 | J2: =H2*I2 | K2: 0.21 | L2: =J2*K2
A3: C02 | B3: SK-26-0457 | C3: AK | D3: 1 | E3: dienst | G3: Elektriciteit januari 2026 (voorschot) | H3: 1 | I3: 200 | J3: =H3*I3 | K3: 0.21 | L3: =J3*K3
A4: C03 | B4: DW-2026-012 | C4: AK | D4: 1 | E4: vast actief | G4: Werkbank met bankschroef en gereedschapswand | H4: 1 | I4: 1500 | J4: =H4*I4 | K4: 0.21 | L4: =J4*K4
A5: C04 | B5: 2026-001 | C5: VK | D5: 1 | E5: artikel | F5: STAD | G5: Stadsfiets City, 7 versnellingen | H5: 10 | I5: 600 | J5: =H5*I5 | K5: 0.21 | L5: =J5*K5
A6: C05 | B6: 2026-002 | C6: VK | D6: 1 | E6: artikel | F6: STAD | G6: Stadsfiets City, 7 versnellingen | H6: 4 | I6: 600 | J6: =H6*I6 | K6: 0.21 | L6: =J6*K6
A7: C06 | B7: CN-2026-001 | C7: CN-VK | D7: 1 | E7: artikel | F7: STAD | G7: Stadsfiets City, 7 versnellingen | H7: 1 | I7: 600 | J7: =H7*I7 | K7: 0.21 | L7: =J7*K7
A8: C07 | B8: CN-2026-007 | C8: CN-AK | D8: 1 | E8: artikel | F8: STAD | G8: Stadsfiets City, 7 versnellingen | H8: 1 | I8: 400 | J8: =H8*I8 | K8: 0.21 | L8: =J8*K8
A9: C08 | B9: DO-2026-01 | C9: DO | D9: 1 | E9: artikel | F9: STAD | G9: Stadsfiets City, 7 versnellingen | H9: 1 | I9: 600 | J9: =H9*I9 | K9: 0.21 | L9: =J9*K9
A10: C08 | B10: DO-2026-01 | C10: DO | D10: 2 | E10: artikel | F10: HELM | G10: Fietshelm Urban | H10: 6 | I10: 50 | J10: =H10*I10 | K10: 0.21 | L10: =J10*K10
A11: C08 | B11: DO-2026-01 | C11: DO | D11: 3 | E11: artikel | F11: BAND | G11: Buitenband 28 inch | H11: 4 | I11: 25 | J11: =H11*I11 | K11: 0.21 | L11: =J11*K11
A12: C08 | B12: DO-2026-01 | C12: DO | D12: 4 | E12: dienst | G12: Herstelling fiets (arbeid) | H12: 4 | I12: 50 | J12: =H12*I12 | K12: 0.06 | L12: =J12*K12
A13: A1 | B13: 2026-205 | C13: AK | D13: 1 | E13: artikel | F13: STAD | G13: Stadsfiets City, 7 versnellingen | H13: 12 | I13: 400 | J13: =H13*I13 | K13: 0.21 | L13: =J13*K13
A14: A1 | B14: 2026-205 | C14: AK | D14: 2 | E14: artikel | F14: EBIKE | G14: E-bike Comfort, 500 Wh | H14: 5 | I14: 1400 | J14: =H14*I14 | K14: 0.21 | L14: =J14*K14
A15: A1 | B15: 2026-205 | C15: AK | D15: 3 | E15: artikel | F15: BAK | G15: Bakfiets Cargo, 2 wielen | H15: 2 | I15: 1800 | J15: =H15*I15 | K15: 0.21 | L15: =J15*K15
A16: A2 | B16: SW-1032 | C16: AK | D16: 1 | E16: artikel | F16: BAND | G16: Buitenband 28 inch | H16: 20 | I16: 15 | J16: =H16*I16 | K16: 0.21 | L16: =J16*K16
A17: A2 | B17: SW-1032 | C17: AK | D17: 2 | E17: artikel | F17: KET | G17: Fietsketting 8 speed | H17: 10 | I17: 10 | J17: =H17*I17 | K17: 0.21 | L17: =J17*K17
A18: A3 | B18: HH-26-077 | C18: AK | D18: 1 | E18: artikel | F18: HELM | G18: Fietshelm Urban | H18: 20 | I18: 30 | J18: =H18*I18 | K18: 0.21 | L18: =J18*K18
A19: A3 | B19: HH-26-077 | C19: AK | D19: 2 | E19: artikel | F19: SLOT | G19: Plooislot | H19: 20 | I19: 20 | J19: =H19*I19 | K19: 0.21 | L19: =J19*K19
A20: A4 | B20: DP-2026-031 | C20: AK | D20: 1 | E20: dienst | G20: 2.000 flyers en 20 affiches opening voorjaar | H20: 1 | I20: 500 | J20: =H20*I20 | K20: 0.21 | L20: =J20*K20
A21: A5 | B21: KT-0458 | C21: AK | D21: 1 | E21: vast actief | G21: Kassasysteem met touchscreen, bonprinter en kassalade | H21: 1 | I21: 1200 | J21: =H21*I21 | K21: 0.21 | L21: =J21*K21
A22: CA1 | B22: CN-2026-015 | C22: CN-AK | D22: 1 | E22: artikel | F22: EBIKE | G22: E-bike Comfort, 500 Wh | H22: 1 | I22: 1400 | J22: =H22*I22 | K22: 0.21 | L22: =J22*K22
A23: CA2 | B23: HH-CN-26-004 | C23: CN-AK | D23: 1 | E23: artikel | F23: SLOT | G23: Plooislot | H23: 10 | I23: 20 | J23: =H23*I23 | K23: 0.21 | L23: =J23*K23
A24: CA3 | B24: SW-CN-118 | C24: CN-AK | D24: 1 | E24: artikel | F24: KET | G24: Fietsketting 8 speed | H24: 10 | I24: 10 | J24: =H24*I24 | K24: 0.21 | L24: =J24*K24
A25: V1 | B25: 2026-003 | C25: VK | D25: 1 | E25: artikel | F25: STAD | G25: Stadsfiets City, 7 versnellingen | H25: 8 | I25: 600 | J25: =H25*I25 | K25: 0.21 | L25: =J25*K25
A26: V2 | B26: 2026-004 | C26: VK | D26: 1 | E26: artikel | F26: BAK | G26: Bakfiets Cargo, 2 wielen | H26: 2 | I26: 2600 | J26: =H26*I26 | K26: 0.21 | L26: =J26*K26
A27: V3 | B27: 2026-005 | C27: VK | D27: 1 | E27: artikel | F27: EBIKE | G27: E-bike Comfort, 500 Wh | H27: 3 | I27: 2000 | J27: =H27*I27 | K27: 0.21 | L27: =J27*K27
A28: V4 | B28: 2026-006 | C28: VK | D28: 1 | E28: dienst | G28: Onderhoudsbeurt fiets (arbeid) | H28: 10 | I28: 60 | J28: =H28*I28 | K28: 0.06 | L28: =J28*K28
A29: V5 | B29: 2026-007 | C29: VK | D29: 1 | E29: artikel | F29: STAD | G29: Stadsfiets City, 7 versnellingen | H29: 2 | I29: 600 | J29: =H29*I29 | K29: 0.21 | L29: =J29*K29
A30: V5 | B30: 2026-007 | C30: VK | D30: 2 | E30: artikel | F30: HELM | G30: Fietshelm Urban | H30: 4 | I30: 50 | J30: =H30*I30 | K30: 0.21 | L30: =J30*K30
A31: CV1 | B31: CN-2026-002 | C31: CN-VK | D31: 1 | E31: artikel | F31: STAD | G31: Stadsfiets City, 7 versnellingen | H31: 1 | I31: 600 | J31: =H31*I31 | K31: 0.21 | L31: =J31*K31
A32: CV2 | B32: CN-2026-003 | C32: CN-VK | D32: 1 | E32: artikel | F32: HELM | G32: Fietshelm Urban | H32: 2 | I32: 50 | J32: =H32*I32 | K32: 0.21 | L32: =J32*K32
A33: CV3 | B33: CN-2026-004 | C33: CN-VK | D33: 1 | E33: artikel | F33: EBIKE | G33: E-bike Comfort, 500 Wh | H33: 1 | I33: 2000 | J33: =H33*I33 | K33: 0.21 | L33: =J33*K33
A34: D1 | B34: DO-2026-02 | C34: DO | D34: 1 | E34: artikel | F34: STAD | G34: Stadsfiets City, 7 versnellingen | H34: 2 | I34: 600 | J34: =H34*I34 | K34: 0.21 | L34: =J34*K34
A35: D1 | B35: DO-2026-02 | C35: DO | D35: 2 | E35: artikel | F35: HELM | G35: Fietshelm Urban | H35: 6 | I35: 50 | J35: =H35*I35 | K35: 0.21 | L35: =J35*K35
A36: D1 | B36: DO-2026-02 | C36: DO | D36: 3 | E36: dienst | G36: Herstelling fiets (arbeid) | H36: 6 | I36: 50 | J36: =H36*I36 | K36: 0.06 | L36: =J36*K36
A37: D2 | B37: DO-2026-03 | C37: DO | D37: 1 | E37: artikel | F37: EBIKE | G37: E-bike Comfort, 500 Wh | H37: 1 | I37: 2000 | J37: =H37*I37 | K37: 0.21 | L37: =J37*K37
A38: D2 | B38: DO-2026-03 | C38: DO | D38: 2 | E38: dienst | G38: Herstelling fiets (arbeid) | H38: 8 | I38: 50 | J38: =H38*I38 | K38: 0.06 | L38: =J38*K38
A39: D3 | B39: DO-2026-04 | C39: DO | D39: 1 | E39: artikel | F39: BAND | G39: Buitenband 28 inch | H39: 20 | I39: 25 | J39: =H39*I39 | K39: 0.21 | L39: =J39*K39
A40: D3 | B40: DO-2026-04 | C40: DO | D40: 2 | E40: artikel | F40: HELM | G40: Fietshelm Urban | H40: 8 | I40: 50 | J40: =H40*I40 | K40: 0.21 | L40: =J40*K40
A41: D3 | B41: DO-2026-04 | C41: DO | D41: 3 | E41: dienst | G41: Herstelling fiets (arbeid) | H41: 5 | I41: 50 | J41: =H41*I41 | K41: 0.06 | L41: =J41*K41
A42: Q2A1 | B42: 2026-411 | C42: AK | D42: 1 | E42: artikel | F42: STAD | G42: Stadsfiets City, 7 versnellingen | H42: 10 | I42: 400 | J42: =H42*I42 | K42: 0.21 | L42: =J42*K42
A43: Q2A1 | B43: 2026-411 | C43: AK | D43: 2 | E43: artikel | F43: EBIKE | G43: E-bike Comfort, 500 Wh | H43: 4 | I43: 1400 | J43: =H43*I43 | K43: 0.21 | L43: =J43*K43
A44: Q2A1 | B44: 2026-411 | C44: AK | D44: 3 | E44: artikel | F44: KIND | G44: Kinderfiets 20 inch | H44: 4 | I44: 150 | J44: =H44*I44 | K44: 0.21 | L44: =J44*K44
A45: Q2A2 | B45: SK-26-1290 | C45: AK | D45: 1 | E45: dienst | G45: Elektriciteit februari-maart 2026 | H45: 1 | I45: 400 | J45: =H45*I45 | K45: 0.21 | L45: =J45*K45
A46: Q2V1 | B46: 2026-008 | C46: VK | D46: 1 | E46: artikel | F46: STAD | G46: Stadsfiets City, 7 versnellingen | H46: 6 | I46: 600 | J46: =H46*I46 | K46: 0.21 | L46: =J46*K46
A47: Q2V1 | B47: 2026-008 | C47: VK | D47: 2 | E47: artikel | F47: HELM | G47: Fietshelm Urban | H47: 8 | I47: 50 | J47: =H47*I47 | K47: 0.21 | L47: =J47*K47
A48: Q2V1 | B48: 2026-008 | C48: VK | D48: 3 | E48: artikel | F48: SLOT | G48: Plooislot | H48: 20 | I48: 35 | J48: =H48*I48 | K48: 0.21 | L48: =J48*K48
A49: Q2CA1 | B49: CN-2026-029 | C49: CN-AK | D49: 1 | E49: artikel | F49: KIND | G49: Kinderfiets 20 inch | H49: 2 | I49: 150 | J49: =H49*I49 | K49: 0.21 | L49: =J49*K49
A50: Q2CV1 | B50: CN-2026-005 | C50: CN-VK | D50: 1 | E50: artikel | F50: HELM | G50: Fietshelm Urban | H50: 2 | I50: 50 | J50: =H50*I50 | K50: 0.21 | L50: =J50*K50
A51: Q2A3 | B51: DW-2026-087 | C51: AK | D51: 1 | E51: vast actief | G51: Montagestandaard voor fietsen, professioneel | H51: 1 | I51: 500 | J51: =H51*I51 | K51: 0.21 | L51: =J51*K51
A52: Q2V2 | B52: 2026-009 | C52: VK | D52: 1 | E52: artikel | F52: EBIKE | G52: E-bike Comfort, 500 Wh | H52: 2 | I52: 2000 | J52: =H52*I52 | K52: 0.21 | L52: =J52*K52
A53: Q2V2 | B53: 2026-009 | C53: VK | D53: 2 | E53: artikel | F53: HELM | G53: Fietshelm Urban | H53: 2 | I53: 50 | J53: =H53*I53 | K53: 0.21 | L53: =J53*K53
A54: Q2A4 | B54: SW-1290 | C54: AK | D54: 1 | E54: artikel | F54: LAMP | G54: Verlichtingsset LED | H54: 20 | I54: 25 | J54: =H54*I54 | K54: 0.21 | L54: =J54*K54
A55: Q2A4 | B55: SW-1290 | C55: AK | D55: 2 | E55: artikel | F55: BAND | G55: Buitenband 28 inch | H55: 20 | I55: 15 | J55: =H55*I55 | K55: 0.21 | L55: =J55*K55
A56: Q2A4 | B56: SW-1290 | C56: AK | D56: 3 | E56: artikel | F56: KET | G56: Fietsketting 8 speed | H56: 10 | I56: 10 | J56: =H56*I56 | K56: 0.21 | L56: =J56*K56
A57: Q2V3 | B57: 2026-010 | C57: VK | D57: 1 | E57: dienst | G57: Onderhoudsbeurt fiets (arbeid) | H57: 15 | I57: 60 | J57: =H57*I57 | K57: 0.06 | L57: =J57*K57
A58: Q2CA2 | B58: SW-CN-171 | C58: CN-AK | D58: 1 | E58: artikel | F58: LAMP | G58: Verlichtingsset LED | H58: 4 | I58: 25 | J58: =H58*I58 | K58: 0.21 | L58: =J58*K58
A59: Q2V4 | B59: 2026-011 | C59: VK | D59: 1 | E59: artikel | F59: STAD | G59: Stadsfiets City, 7 versnellingen | H59: 2 | I59: 600 | J59: =H59*I59 | K59: 0.21 | L59: =J59*K59
A60: Q2V4 | B60: 2026-011 | C60: VK | D60: 2 | E60: artikel | F60: KET | G60: Fietsketting 8 speed | H60: 5 | I60: 20 | J60: =H60*I60 | K60: 0.21 | L60: =J60*K60
A61: Q2CV2 | B61: CN-2026-006 | C61: CN-VK | D61: 1 | E61: artikel | F61: EBIKE | G61: E-bike Comfort, 500 Wh | H61: 1 | I61: 2000 | J61: =H61*I61 | K61: 0.21 | L61: =J61*K61
A62: Q2D1 | B62: DO-2026-05 | C62: DO | D62: 1 | E62: artikel | F62: STAD | G62: Stadsfiets City, 7 versnellingen | H62: 2 | I62: 600 | J62: =H62*I62 | K62: 0.21 | L62: =J62*K62
A63: Q2D1 | B63: DO-2026-05 | C63: DO | D63: 2 | E63: artikel | F63: LAMP | G63: Verlichtingsset LED | H63: 10 | I63: 40 | J63: =H63*I63 | K63: 0.21 | L63: =J63*K63
A64: Q2D1 | B64: DO-2026-05 | C64: DO | D64: 3 | E64: dienst | G64: Herstelling fiets (arbeid) | H64: 10 | I64: 50 | J64: =H64*I64 | K64: 0.06 | L64: =J64*K64
A65: Q3A1 | B65: 2026-702 | C65: AK | D65: 1 | E65: artikel | F65: STAD | G65: Stadsfiets City, 7 versnellingen | H65: 8 | I65: 400 | J65: =H65*I65 | K65: 0.21 | L65: =J65*K65
A66: Q3A1 | B66: 2026-702 | C66: AK | D66: 2 | E66: artikel | F66: BAK | G66: Bakfiets Cargo, 2 wielen | H66: 2 | I66: 1800 | J66: =H66*I66 | K66: 0.21 | L66: =J66*K66
A67: Q3A1 | B67: 2026-702 | C67: AK | D67: 3 | E67: artikel | F67: EBIKE | G67: E-bike Comfort, 500 Wh | H67: 2 | I67: 1400 | J67: =H67*I67 | K67: 0.21 | L67: =J67*K67
A68: Q3A3 | B68: HH-26-311 | C68: AK | D68: 1 | E68: artikel | F68: HELM | G68: Fietshelm Urban | H68: 20 | I68: 30 | J68: =H68*I68 | K68: 0.21 | L68: =J68*K68
A69: Q3A3 | B69: HH-26-311 | C69: AK | D69: 2 | E69: artikel | F69: SLOT | G69: Plooislot | H69: 20 | I69: 20 | J69: =H69*I69 | K69: 0.21 | L69: =J69*K69
A70: Q3CA1 | B70: CN-2026-044 | C70: CN-AK | D70: 1 | E70: artikel | F70: STAD | G70: Stadsfiets City, 7 versnellingen | H70: 1 | I70: 400 | J70: =H70*I70 | K70: 0.21 | L70: =J70*K70
A71: Q3A2 | B71: BN-2026-061 | C71: AK | D71: 1 | E71: dienst | G71: Erelonen boekhouding eerste semester 2026 | H71: 1 | I71: 800 | J71: =H71*I71 | K71: 0.21 | L71: =J71*K71
A72: Q3V1 | B72: 2026-012 | C72: VK | D72: 1 | E72: artikel | F72: STAD | G72: Stadsfiets City, 7 versnellingen | H72: 4 | I72: 600 | J72: =H72*I72 | K72: 0.21 | L72: =J72*K72
A73: Q3V1 | B73: 2026-012 | C73: VK | D73: 2 | E73: artikel | F73: HELM | G73: Fietshelm Urban | H73: 4 | I73: 50 | J73: =H73*I73 | K73: 0.21 | L73: =J73*K73
A74: Q3CV1 | B74: CN-2026-007 | C74: CN-VK | D74: 1 | E74: artikel | F74: STAD | G74: Stadsfiets City, 7 versnellingen | H74: 1 | I74: 600 | J74: =H74*I74 | K74: 0.21 | L74: =J74*K74
A75: Q3V2 | B75: 2026-013 | C75: VK | D75: 1 | E75: artikel | F75: BAK | G75: Bakfiets Cargo, 2 wielen | H75: 1 | I75: 2600 | J75: =H75*I75 | K75: 0.21 | L75: =J75*K75
A76: Q3V2 | B76: 2026-013 | C76: VK | D76: 2 | E76: artikel | F76: EBIKE | G76: E-bike Comfort, 500 Wh | H76: 2 | I76: 2000 | J76: =H76*I76 | K76: 0.21 | L76: =J76*K76
A77: Q3CA2 | B77: HH-CN-26-019 | C77: CN-AK | D77: 1 | E77: artikel | F77: HELM | G77: Fietshelm Urban | H77: 10 | I77: 30 | J77: =H77*I77 | K77: 0.21 | L77: =J77*K77
A78: Q3V3 | B78: 2026-014 | C78: VK | D78: 1 | E78: dienst | G78: Herstelling fiets (arbeid) | H78: 20 | I78: 50 | J78: =H78*I78 | K78: 0.06 | L78: =J78*K78
A79: Q4A1 | B79: 2026-1003 | C79: AK | D79: 1 | E79: artikel | F79: STAD | G79: Stadsfiets City, 7 versnellingen | H79: 6 | I79: 400 | J79: =H79*I79 | K79: 0.21 | L79: =J79*K79
A80: Q4A1 | B80: 2026-1003 | C80: AK | D80: 2 | E80: artikel | F80: EBIKE | G80: E-bike Comfort, 500 Wh | H80: 3 | I80: 1400 | J80: =H80*I80 | K80: 0.21 | L80: =J80*K80
A81: Q4A2 | B81: KT-0981 | C81: AK | D81: 1 | E81: vast actief | G81: Laptop voor administratie en webshop | H81: 1 | I81: 900 | J81: =H81*I81 | K81: 0.21 | L81: =J81*K81
A82: Q4V1 | B82: 2026-015 | C82: VK | D82: 1 | E82: artikel | F82: STAD | G82: Stadsfiets City, 7 versnellingen | H82: 6 | I82: 600 | J82: =H82*I82 | K82: 0.21 | L82: =J82*K82
A83: Q4V1 | B83: 2026-015 | C83: VK | D83: 2 | E83: artikel | F83: SLOT | G83: Plooislot | H83: 20 | I83: 35 | J83: =H83*I83 | K83: 0.21 | L83: =J83*K83
A84: Q4CA1 | B84: CN-2026-061 | C84: CN-AK | D84: 1 | E84: artikel | F84: EBIKE | G84: E-bike Comfort, 500 Wh | H84: 1 | I84: 1400 | J84: =H84*I84 | K84: 0.21 | L84: =J84*K84
A85: Q4CV1 | B85: CN-2026-008 | C85: CN-VK | D85: 1 | E85: artikel | F85: STAD | G85: Stadsfiets City, 7 versnellingen | H85: 1 | I85: 600 | J85: =H85*I85 | K85: 0.21 | L85: =J85*K85
A86: Q4V2 | B86: 2026-016 | C86: VK | D86: 1 | E86: artikel | F86: EBIKE | G86: E-bike Comfort, 500 Wh | H86: 2 | I86: 2000 | J86: =H86*I86 | K86: 0.21 | L86: =J86*K86
A87: Q4A3 | B87: NL-26-11-2207 | C87: AK | D87: 1 | E87: dienst | G87: Internet en telefonie oktober-december 2026 | H87: 1 | I87: 300 | J87: =H87*I87 | K87: 0.21 | L87: =J87*K87
A88: Q4V3 | B88: 2026-017 | C88: VK | D88: 1 | E88: dienst | G88: Onderhoudsbeurt fiets (arbeid) | H88: 20 | I88: 60 | J88: =H88*I88 | K88: 0.06 | L88: =J88*K88
A89: Q4CV2 | B89: CN-2026-009 | C89: CN-VK | D89: 1 | E89: artikel | F89: EBIKE | G89: E-bike Comfort, 500 Wh | H89: 1 | I89: 2000 | J89: =H89*I89 | K89: 0.21 | L89: =J89*K89
A90: Q4D1 | B90: DO-2026-06 | C90: DO | D90: 1 | E90: artikel | F90: EBIKE | G90: E-bike Comfort, 500 Wh | H90: 1 | I90: 2000 | J90: =H90*I90 | K90: 0.21 | L90: =J90*K90
A91: Q4D1 | B91: DO-2026-06 | C91: DO | D91: 2 | E91: artikel | F91: HELM | G91: Fietshelm Urban | H91: 6 | I91: 50 | J91: =H91*I91 | K91: 0.21 | L91: =J91*K91
A92: Q4D1 | B92: DO-2026-06 | C92: DO | D92: 3 | E92: artikel | F92: BAND | G92: Buitenband 28 inch | H92: 8 | I92: 25 | J92: =H92*I92 | K92: 0.21 | L92: =J92*K92
A93: Q4D1 | B93: DO-2026-06 | C93: DO | D93: 4 | E93: dienst | G93: Herstelling fiets (arbeid) | H93: 12 | I93: 50 | J93: =H93*I93 | K93: 0.06 | L93: =J93*K93
A94: B1 | B94: 2026-1288 | C94: AK | D94: 1 | E94: artikel | F94: STAD | G94: Stadsfiets City, 7 versnellingen | H94: 6 | I94: 400 | J94: =H94*I94 | K94: 0.21 | L94: =J94*K94
A95: B1 | B95: 2026-1288 | C95: AK | D95: 2 | E95: artikel | F95: BAK | G95: Bakfiets Cargo, 2 wielen | H95: 2 | I95: 1800 | J95: =H95*I95 | K95: 0.21 | L95: =J95*K95
A96: B2 | B96: 2026-018 | C96: VK | D96: 1 | E96: artikel | F96: STAD | G96: Stadsfiets City, 7 versnellingen | H96: 4 | I96: 600 | J96: =H96*I96 | K96: 0.21 | L96: =J96*K96
A97: B2 | B97: 2026-018 | C97: VK | D97: 2 | E97: artikel | F97: BAK | G97: Bakfiets Cargo, 2 wielen | H97: 2 | I97: 2600 | J97: =H97*I97 | K97: 0.21 | L97: =J97*K97

Sheet J1 Documenten
A1: Volgorde in set | B1: ID | C1: Set | D1: Kwartaal | E1: Soort | F1: Subsoort | G1: Datum | H1: Vervaldag | I1: Documentnr | J1: Van | K1: Aan | L1: Verwijst naar | M1: Reden / omschrijving | N1: MvH 21% | O1: Btw 21% | P1: MvH 6% | Q1: Btw 6% | R1: Waarborg | S1: Fin. korting (niet afgetrokken) | T1: Totaal (te betalen) | U1: Te betalen binnen kortingstermijn | V1: Contant (kas) | W1: Bancontact | X1: Betaald via uittreksel | Y1: Controle D-C | Z1: Opmerking
A2: 1 | B2: C01 | C2: CURSUS | D2: K1 | E2: AK | F2: handelsgoederen | G2: 46027 | H2: =G2+30 | I2: 2026-118 | J2: Velomax bv | K2: Fietsatelier Noor bv | N2: =SUMIFS('J1 Lijnen'!$J:$J,'J1 Lijnen'!$A:$A,$B2,'J1 Lijnen'!$K:$K,0.21,'J1 Lijnen'!$E:$E,"<>verpakking") | O2: =SUMIFS('J1 Lijnen'!$L:$L,'J1 Lijnen'!$A:$A,$B2,'J1 Lijnen'!$K:$K,0.21) | P2: =SUMIFS('J1 Lijnen'!$J:$J,'J1 Lijnen'!$A:$A,$B2,'J1 Lijnen'!$K:$K,0.06) | Q2: =SUMIFS('J1 Lijnen'!$L:$L,'J1 Lijnen'!$A:$A,$B2,'J1 Lijnen'!$K:$K,0.06) | R2: =SUMIFS('J1 Lijnen'!$J:$J,'J1 Lijnen'!$A:$A,$B2,'J1 Lijnen'!$E:$E,"verpakking") | S2: =-SUMIFS('J1 Lijnen'!$J:$J,'J1 Lijnen'!$A:$A,$B2,'J1 Lijnen'!$E:$E,"financiële korting") | T2: =SUM(N2:S2) | X2: U2026-01 | Y2: =SUMIFS('J1 Journaal'!$K:$K,'J1 Journaal'!$E:$E,$B2)-SUMIFS('J1 Journaal'!$L:$L,'J1 Journaal'!$E:$E,$B2)
A3: 2 | B3: C02 | C3: CURSUS | D3: K1 | E3: AK | F3: diensten | G3: 46029 | H3: =G3+30 | I3: SK-26-0457 | J3: Stroomkracht nv | K3: Fietsatelier Noor bv | N3: =SUMIFS('J1 Lijnen'!$J:$J,'J1 Lijnen'!$A:$A,$B3,'J1 Lijnen'!$K:$K,0.21,'J1 Lijnen'!$E:$E,"<>verpakking") | O3: =SUMIFS('J1 Lijnen'!$L:$L,'J1 Lijnen'!$A:$A,$B3,'J1 Lijnen'!$K:$K,0.21) | P3: =SUMIFS('J1 Lijnen'!$J:$J,'J1 Lijnen'!$A:$A,$B3,'J1 Lijnen'!$K:$K,0.06) | Q3: =SUMIFS('J1 Lijnen'!$L:$L,'J1 Lijnen'!$A:$A,$B3,'J1 Lijnen'!$K:$K,0.06) | R3: =SUMIFS('J1 Lijnen'!$J:$J,'J1 Lijnen'!$A:$A,$B3,'J1 Lijnen'!$E:$E,"verpakking") | S3: =-SUMIFS('J1 Lijnen'!$J:$J,'J1 Lijnen'!$A:$A,$B3,'J1 Lijnen'!$E:$E,"financiële korting") | T3: =SUM(N3:S3) | X3: U2026-01 | Y3: =SUMIFS('J1 Journaal'!$K:$K,'J1 Journaal'!$E:$E,$B3)-SUMIFS('J1 Journaal'!$L:$L,'J1 Journaal'!$E:$E,$B3)
A4: 3 | B4: C03 | C4: CURSUS | D4: K1 | E4: AK | F4: vaste activa | G4: 46031 | H4: =G4+30 | I4: DW-2026-012 | J4: Deprez Werkplaatsinrichting bv | K4: Fietsatelier Noor bv | N4: =SUMIFS('J1 Lijnen'!$J:$J,'J1 Lijnen'!$A:$A,$B4,'J1 Lijnen'!$K:$K,0.21,'J1 Lijnen'!$E:$E,"<>verpakking") | O4: =SUMIFS('J1 Lijnen'!$L:$L,'J1 Lijnen'!$A:$A,$B4,'J1 Lijnen'!$K:$K,0.21) | P4: =SUMIFS('J1 Lijnen'!$J:$J,'J1 Lijnen'!$A:$A,$B4,'J1 Lijnen'!$K:$K,0.06) | Q4: =SUMIFS('J1 Lijnen'!$L:$L,'J1 Lijnen'!$A:$A,$B4,'J1 Lijnen'!$K:$K,0.06) | R4: =SUMIFS('J1 Lijnen'!$J:$J,'J1 Lijnen'!$A:$A,$B4,'J1 Lijnen'!$E:$E,"verpakking") | S4: =-SUMIFS('J1 Lijnen'!$J:$J,'J1 Lijnen'!$A:$A,$B4,'J1 Lijnen'!$E:$E,"financiële korting") | T4: =SUM(N4:S4) | X4: U2026-01 | Y4: =SUMIFS('J1 Journaal'!$K:$K,'J1 Journaal'!$E:$E,$B4)-SUMIFS('J1 Journaal'!$L:$L,'J1 Journaal'!$E:$E,$B4)
A5: 4 | B5: C04 | C5: CURSUS | D5: K1 | E5: VK | F5: handelsgoederen | G5: 46036 | H5: =G5+30 | I5: 2026-001 | J5: Fietsatelier Noor bv | K5: Snelpost bv | N5: =SUMIFS('J1 Lijnen'!$J:$J,'J1 Lijnen'!$A:$A,$B5,'J1 Lijnen'!$K:$K,0.21,'J1 Lijnen'!$E:$E,"<>verpakking") | O5: =SUMIFS('J1 Lijnen'!$L:$L,'J1 Lijnen'!$A:$A,$B5,'J1 Lijnen'!$K:$K,0.21) | P5: =SUMIFS('J1 Lijnen'!$J:$J,'J1 Lijnen'!$A:$A,$B5,'J1 Lijnen'!$K:$K,0.06) | Q5: =SUMIFS('J1 Lijnen'!$L:$L,'J1 Lijnen'!$A:$A,$B5,'J1 Lijnen'!$K:$K,0.06) | R5: =SUMIFS('J1 Lijnen'!$J:$J,'J1 Lijnen'!$A:$A,$B5,'J1 Lijnen'!$E:$E,"verpakking") | S5: =-SUMIFS('J1 Lijnen'!$J:$J,'J1 Lijnen'!$A:$A,$B5,'J1 Lijnen'!$E:$E,"financiële korting") | T5: =SUM(N5:S5) | X5: U2026-02 | Y5: =SUMIFS('J1 Journaal'!$K:$K,'J1 Journaal'!$E:$E,$B5)-SUMIFS('J1 Journaal'!$L:$L,'J1 Journaal'!$E:$E,$B5)
A6: 5 | B6: C05 | C6: CURSUS | D6: K1 | E6: VK | F6: handelsgoederen | G6: 46041 | H6: =G6+30 | I6: 2026-002 | J6: Fietsatelier Noor bv | K6: Hotel De Linde bv | N6: =SUMIFS('J1 Lijnen'!$J:$J,'J1 Lijnen'!$A:$A,$B6,'J1 Lijnen'!$K:$K,0.21,'J1 Lijnen'!$E:$E,"<>verpakking") | O6: =SUMIFS('J1 Lijnen'!$L:$L,'J1 Lijnen'!$A:$A,$B6,'J1 Lijnen'!$K:$K,0.21) | P6: =SUMIFS('J1 Lijnen'!$J:$J,'J1 Lijnen'!$A:$A,$B6,'J1 Lijnen'!$K:$K,0.06) | Q6: =SUMIFS('J1 Lijnen'!$L:$L,'J1 Lijnen'!$A:$A,$B6,'J1 Lijnen'!$K:$K,0.06) | R6: =SUMIFS('J1 Lijnen'!$J:$J,'J1 Lijnen'!$A:$A,$B6,'J1 Lijnen'!$E:$E,"verpakking") | S6: =-SUMIFS('J1 Lijnen'!$J:$J,'J1 Lijnen'!$A:$A,$B6,'J1 Lijnen'!$E:$E,"financiële korting") | T6: =SUM(N6:S6) | X6: U2026-03 | Y6: =SUMIFS('J1 Journaal'!$K:$K,'J1 Journaal'!$E:$E,$B6)-SUMIFS('J1 Journaal'!$L:$L,'J1 Journaal'!$E:$E,$B6)
A7: 7 | B7: C06 | C7: CURSUS | D7: K1 | E7: CN-VK | F7: retour | G7: 46043 | I7: CN-2026-001 | J7: Fietsatelier Noor bv | K7: Hotel De Linde bv | L7: 2026-002 | M7: 1 fiets teruggenomen: kras op het frame | N7: =SUMIFS('J1 Lijnen'!$J:$J,'J1 Lijnen'!$A:$A,$B7,'J1 Lijnen'!$K:$K,0.21,'J1 Lijnen'!$E:$E,"<>verpakking") | O7: =SUMIFS('J1 Lijnen'!$L:$L,'J1 Lijnen'!$A:$A,$B7,'J1 Lijnen'!$K:$K,0.21) | P7: =SUMIFS('J1 Lijnen'!$J:$J,'J1 Lijnen'!$A:$A,$B7,'J1 Lijnen'!$K:$K,0.06) | Q7: =SUMIFS('J1 Lijnen'!$L:$L,'J1 Lijnen'!$A:$A,$B7,'J1 Lijnen'!$K:$K,0.06) | R7: =SUMIFS('J1 Lijnen'!$J:$J,'J1 Lijnen'!$A:$A,$B7,'J1 Lijnen'!$E:$E,"verpakking") | S7: =-SUMIFS('J1 Lijnen'!$J:$J,'J1 Lijnen'!$A:$A,$B7,'J1 Lijnen'!$E:$E,"financiële korting") | T7: =SUM(N7:S7) | X7: U2026-03 | Y7: =SUMIFS('J1 Journaal'!$K:$K,'J1 Journaal'!$E:$E,$B7)-SUMIFS('J1 Journaal'!$L:$L,'J1 Journaal'!$E:$E,$B7)
A8: 8 | B8: C07 | C8: CURSUS | D8: K1 | E8: CN-AK | F8: retour | G8: 46044 | I8: CN-2026-007 | J8: Velomax bv | K8: Fietsatelier Noor bv | L8: 2026-118 | M8: 1 fiets beschadigd geleverd, teruggestuurd | N8: =SUMIFS('J1 Lijnen'!$J:$J,'J1 Lijnen'!$A:$A,$B8,'J1 Lijnen'!$K:$K,0.21,'J1 Lijnen'!$E:$E,"<>verpakking") | O8: =SUMIFS('J1 Lijnen'!$L:$L,'J1 Lijnen'!$A:$A,$B8,'J1 Lijnen'!$K:$K,0.21) | P8: =SUMIFS('J1 Lijnen'!$J:$J,'J1 Lijnen'!$A:$A,$B8,'J1 Lijnen'!$K:$K,0.06) | Q8: =SUMIFS('J1 Lijnen'!$L:$L,'J1 Lijnen'!$A:$A,$B8,'J1 Lijnen'!$K:$K,0.06) | R8: =SUMIFS('J1 Lijnen'!$J:$J,'J1 Lijnen'!$A:$A,$B8,'J1 Lijnen'!$E:$E,"verpakking") | S8: =-SUMIFS('J1 Lijnen'!$J:$J,'J1 Lijnen'!$A:$A,$B8,'J1 Lijnen'!$E:$E,"financiële korting") | T8: =SUM(N8:S8) | X8: U2026-03 | Y8: =SUMIFS('J1 Journaal'!$K:$K,'J1 Journaal'!$E:$E,$B8)-SUMIFS('J1 Journaal'!$L:$L,'J1 Journaal'!$E:$E,$B8)
A9: 9 | B9: C08 | C9: CURSUS | D9: K1 | E9: DO | F9: dagontvangst | G9: 46046 | I9: DO-2026-01 | J9: Fietsatelier Noor bv | K9: particulieren (kasticket) | M9: Dagontvangsten winkel (verkopen aan particulieren) | N9: =SUMIFS('J1 Lijnen'!$J:$J,'J1 Lijnen'!$A:$A,$B9,'J1 Lijnen'!$K:$K,0.21,'J1 Lijnen'!$E:$E,"<>verpakking") | O9: =SUMIFS('J1 Lijnen'!$L:$L,'J1 Lijnen'!$A:$A,$B9,'J1 Lijnen'!$K:$K,0.21) | P9: =SUMIFS('J1 Lijnen'!$J:$J,'J1 Lijnen'!$A:$A,$B9,'J1 Lijnen'!$K:$K,0.06) | Q9: =SUMIFS('J1 Lijnen'!$L:$L,'J1 Lijnen'!$A:$A,$B9,'J1 Lijnen'!$K:$K,0.06) | R9: =SUMIFS('J1 Lijnen'!$J:$J,'J1 Lijnen'!$A:$A,$B9,'J1 Lijnen'!$E:$E,"verpakking") | S9: =-SUMIFS('J1 Lijnen'!$J:$J,'J1 Lijnen'!$A:$A,$B9,'J1 Lijnen'!$E:$E,"financiële korting") | T9: =SUM(N9:S9) | V9: =T9-W9 | W9: 1000 | X9: C08K, U2026-03 | Y9: =SUMIFS('J1 Journaal'!$K:$K,'J1 Journaal'!$E:$E,$B9)-SUMIFS('J1 Journaal'!$L:$L,'J1 Journaal'!$E:$E,$B9)
A10: 10 | B10: C08K | C10: CURSUS | D10: K1 | E10: KAS | F10: ontvangst | G10: 46046 | I10: Kasboek DO-2026-01 | J10: Fietsatelier Noor bv | K10: Fietsatelier Noor bv | L10: DO-2026-01 | M10: Contant deel van dagontvangst DO-2026-01 (laat de vordering op de klanten dalen) | T10: 422 | V10: 422 | Y10: =SUMIFS('J1 Journaal'!$K:$K,'J1 Journaal'!$E:$E,$B10)-SUMIFS('J1 Journaal'!$L:$L,'J1 Journaal'!$E:$E,$B10)
A11: 1 | B11: A1 | C11: VERPLICHT | D11: K1 | E11: AK | F11: handelsgoederen | G11: 46055 | H11: =G11+30 | I11: 2026-205 | J11: Velomax bv | K11: Fietsatelier Noor bv | N11: =SUMIFS('J1 Lijnen'!$J:$J,'J1 Lijnen'!$A:$A,$B11,'J1 Lijnen'!$K:$K,0.21,'J1 Lijnen'!$E:$E,"<>verpakking") | O11: =SUMIFS('J1 Lijnen'!$L:$L,'J1 Lijnen'!$A:$A,$B11,'J1 Lijnen'!$K:$K,0.21) | P11: =SUMIFS('J1 Lijnen'!$J:$J,'J1 Lijnen'!$A:$A,$B11,'J1 Lijnen'!$K:$K,0.06) | Q11: =SUMIFS('J1 Lijnen'!$L:$L,'J1 Lijnen'!$A:$A,$B11,'J1 Lijnen'!$K:$K,0.06) | R11: =SUMIFS('J1 Lijnen'!$J:$J,'J1 Lijnen'!$A:$A,$B11,'J1 Lijnen'!$E:$E,"verpakking") | S11: =-SUMIFS('J1 Lijnen'!$J:$J,'J1 Lijnen'!$A:$A,$B11,'J1 Lijnen'!$E:$E,"financiële korting") | T11: =SUM(N11:S11) | X11: U2026-06 | Y11: =SUMIFS('J1 Journaal'!$K:$K,'J1 Journaal'!$E:$E,$B11)-SUMIFS('J1 Journaal'!$L:$L,'J1 Journaal'!$E:$E,$B11)
A12: 2 | B12: A2 | C12: VERPLICHT | D12: K1 | E12: AK | F12: handelsgoederen | G12: 46057 | H12: =G12+30 | I12: SW-1032 | J12: Spaakwerk bv | K12: Fietsatelier Noor bv | N12: =SUMIFS('J1 Lijnen'!$J:$J,'J1 Lijnen'!$A:$A,$B12,'J1 Lijnen'!$K:$K,0.21,'J1 Lijnen'!$E:$E,"<>verpakking") | O12: =SUMIFS('J1 Lijnen'!$L:$L,'J1 Lijnen'!$A:$A,$B12,'J1 Lijnen'!$K:$K,0.21) | P12: =SUMIFS('J1 Lijnen'!$J:$J,'J1 Lijnen'!$A:$A,$B12,'J1 Lijnen'!$K:$K,0.06) | Q12: =SUMIFS('J1 Lijnen'!$L:$L,'J1 Lijnen'!$A:$A,$B12,'J1 Lijnen'!$K:$K,0.06) | R12: =SUMIFS('J1 Lijnen'!$J:$J,'J1 Lijnen'!$A:$A,$B12,'J1 Lijnen'!$E:$E,"verpakking") | S12: =-SUMIFS('J1 Lijnen'!$J:$J,'J1 Lijnen'!$A:$A,$B12,'J1 Lijnen'!$E:$E,"financiële korting") | T12: =SUM(N12:S12) | X12: U2026-05 | Y12: =SUMIFS('J1 Journaal'!$K:$K,'J1 Journaal'!$E:$E,$B12)-SUMIFS('J1 Journaal'!$L:$L,'J1 Journaal'!$E:$E,$B12)
A13: 3 | B13: A3 | C13: VERPLICHT | D13: K1 | E13: AK | F13: handelsgoederen | G13: 46059 | H13: =G13+30 | I13: HH-26-077 | J13: HelmHuis bv | K13: Fietsatelier Noor bv | N13: =SUMIFS('J1 Lijnen'!$J:$J,'J1 Lijnen'!$A:$A,$B13,'J1 Lijnen'!$K:$K,0.21,'J1 Lijnen'!$E:$E,"<>verpakking") | O13: =SUMIFS('J1 Lijnen'!$L:$L,'J1 Lijnen'!$A:$A,$B13,'J1 Lijnen'!$K:$K,0.21) | P13: =SUMIFS('J1 Lijnen'!$J:$J,'J1 Lijnen'!$A:$A,$B13,'J1 Lijnen'!$K:$K,0.06) | Q13: =SUMIFS('J1 Lijnen'!$L:$L,'J1 Lijnen'!$A:$A,$B13,'J1 Lijnen'!$K:$K,0.06) | R13: =SUMIFS('J1 Lijnen'!$J:$J,'J1 Lijnen'!$A:$A,$B13,'J1 Lijnen'!$E:$E,"verpakking") | S13: =-SUMIFS('J1 Lijnen'!$J:$J,'J1 Lijnen'!$A:$A,$B13,'J1 Lijnen'!$E:$E,"financiële korting") | T13: =SUM(N13:S13) | X13: U2026-05 | Y13: =SUMIFS('J1 Journaal'!$K:$K,'J1 Journaal'!$E:$E,$B13)-SUMIFS('J1 Journaal'!$L:$L,'J1 Journaal'!$E:$E,$B13)
A14: 4 | B14: A4 | C14: VERPLICHT | D14: K1 | E14: AK | F14: diensten | G14: 46062 | H14: =G14+30 | I14: DP-2026-031 | J14: Drukkerij Peeters bv | K14: Fietsatelier Noor bv | N14: =SUMIFS('J1 Lijnen'!$J:$J,'J1 Lijnen'!$A:$A,$B14,'J1 Lijnen'!$K:$K,0.21,'J1 Lijnen'!$E:$E,"<>verpakking") | O14: =SUMIFS('J1 Lijnen'!$L:$L,'J1 Lijnen'!$A:$A,$B14,'J1 Lijnen'!$K:$K,0.21) | P14: =SUMIFS('J1 Lijnen'!$J:$J,'J1 Lijnen'!$A:$A,$B14,'J1 Lijnen'!$K:$K,0.06) | Q14: =SUMIFS('J1 Lijnen'!$L:$L,'J1 Lijnen'!$A:$A,$B14,'J1 Lijnen'!$K:$K,0.06) | R14: =SUMIFS('J1 Lijnen'!$J:$J,'J1 Lijnen'!$A:$A,$B14,'J1 Lijnen'!$E:$E,"verpakking") | S14: =-SUMIFS('J1 Lijnen'!$J:$J,'J1 Lijnen'!$A:$A,$B14,'J1 Lijnen'!$E:$E,"financiële korting") | T14: =SUM(N14:S14) | X14: U2026-06 | Y14: =SUMIFS('J1 Journaal'!$K:$K,'J1 Journaal'!$E:$E,$B14)-SUMIFS('J1 Journaal'!$L:$L,'J1 Journaal'!$E:$E,$B14)
A15: 5 | B15: A5 | C15: VERPLICHT | D15: K1 | E15: AK | F15: vaste activa | G15: 46064 | H15: =G15+30 | I15: KT-0458 | J15: Kassatech bv | K15: Fietsatelier Noor bv | N15: =SUMIFS('J1 Lijnen'!$J:$J,'J1 Lijnen'!$A:$A,$B15,'J1 Lijnen'!$K:$K,0.21,'J1 Lijnen'!$E:$E,"<>verpakking") | O15: =SUMIFS('J1 Lijnen'!$L:$L,'J1 Lijnen'!$A:$A,$B15,'J1 Lijnen'!$K:$K,0.21) | P15: =SUMIFS('J1 Lijnen'!$J:$J,'J1 Lijnen'!$A:$A,$B15,'J1 Lijnen'!$K:$K,0.06) | Q15: =SUMIFS('J1 Lijnen'!$L:$L,'J1 Lijnen'!$A:$A,$B15,'J1 Lijnen'!$K:$K,0.06) | R15: =SUMIFS('J1 Lijnen'!$J:$J,'J1 Lijnen'!$A:$A,$B15,'J1 Lijnen'!$E:$E,"verpakking") | S15: =-SUMIFS('J1 Lijnen'!$J:$J,'J1 Lijnen'!$A:$A,$B15,'J1 Lijnen'!$E:$E,"financiële korting") | T15: =SUM(N15:S15) | X15: U2026-06 | Y15: =SUMIFS('J1 Journaal'!$K:$K,'J1 Journaal'!$E:$E,$B15)-SUMIFS('J1 Journaal'!$L:$L,'J1 Journaal'!$E:$E,$B15)
A16: 6 | B16: CA1 | C16: VERPLICHT | D16: K1 | E16: CN-AK | F16: retour | G16: 46066 | I16: CN-2026-015 | J16: Velomax bv | K16: Fietsatelier Noor bv | L16: 2026-205 | M16: 1 e-bike in verkeerde framemaat geleverd, teruggestuurd | N16: =SUMIFS('J1 Lijnen'!$J:$J,'J1 Lijnen'!$A:$A,$B16,'J1 Lijnen'!$K:$K,0.21,'J1 Lijnen'!$E:$E,"<>verpakking") | O16: =SUMIFS('J1 Lijnen'!$L:$L,'J1 Lijnen'!$A:$A,$B16,'J1 Lijnen'!$K:$K,0.21) | P16: =SUMIFS('J1 Lijnen'!$J:$J,'J1 Lijnen'!$A:$A,$B16,'J1 Lijnen'!$K:$K,0.06) | Q16: =SUMIFS('J1 Lijnen'!$L:$L,'J1 Lijnen'!$A:$A,$B16,'J1 Lijnen'!$K:$K,0.06) | R16: =SUMIFS('J1 Lijnen'!$J:$J,'J1 Lijnen'!$A:$A,$B16,'J1 Lijnen'!$E:$E,"verpakking") | S16: =-SUMIFS('J1 Lijnen'!$J:$J,'J1 Lijnen'!$A:$A,$B16,'J1 Lijnen'!$E:$E,"financiële korting") | T16: =SUM(N16:S16) | X16: U2026-06 | Y16: =SUMIFS('J1 Journaal'!$K:$K,'J1 Journaal'!$E:$E,$B16)-SUMIFS('J1 Journaal'!$L:$L,'J1 Journaal'!$E:$E,$B16)
A17: 7 | B17: CA2 | C17: VERPLICHT | D17: K1 | E17: CN-AK | F17: retour | G17: 46069 | I17: HH-CN-26-004 | J17: HelmHuis bv | K17: Fietsatelier Noor bv | L17: HH-26-077 | M17: 10 sloten beschadigd geleverd, teruggestuurd | N17: =SUMIFS('J1 Lijnen'!$J:$J,'J1 Lijnen'!$A:$A,$B17,'J1 Lijnen'!$K:$K,0.21,'J1 Lijnen'!$E:$E,"<>verpakking") | O17: =SUMIFS('J1 Lijnen'!$L:$L,'J1 Lijnen'!$A:$A,$B17,'J1 Lijnen'!$K:$K,0.21) | P17: =SUMIFS('J1 Lijnen'!$J:$J,'J1 Lijnen'!$A:$A,$B17,'J1 Lijnen'!$K:$K,0.06) | Q17: =SUMIFS('J1 Lijnen'!$L:$L,'J1 Lijnen'!$A:$A,$B17,'J1 Lijnen'!$K:$K,0.06) | R17: =SUMIFS('J1 Lijnen'!$J:$J,'J1 Lijnen'!$A:$A,$B17,'J1 Lijnen'!$E:$E,"verpakking") | S17: =-SUMIFS('J1 Lijnen'!$J:$J,'J1 Lijnen'!$A:$A,$B17,'J1 Lijnen'!$E:$E,"financiële korting") | T17: =SUM(N17:S17) | X17: U2026-05 | Y17: =SUMIFS('J1 Journaal'!$K:$K,'J1 Journaal'!$E:$E,$B17)-SUMIFS('J1 Journaal'!$L:$L,'J1 Journaal'!$E:$E,$B17)
A18: 8 | B18: CA3 | C18: VERPLICHT | D18: K1 | E18: CN-AK | F18: retour | G18: 46078 | I18: SW-CN-118 | J18: Spaakwerk bv | K18: Fietsatelier Noor bv | L18: SW-1032 | M18: 10 kettingen van het verkeerde type, teruggestuurd (factuur was al betaald) | N18: =SUMIFS('J1 Lijnen'!$J:$J,'J1 Lijnen'!$A:$A,$B18,'J1 Lijnen'!$K:$K,0.21,'J1 Lijnen'!$E:$E,"<>verpakking") | O18: =SUMIFS('J1 Lijnen'!$L:$L,'J1 Lijnen'!$A:$A,$B18,'J1 Lijnen'!$K:$K,0.21) | P18: =SUMIFS('J1 Lijnen'!$J:$J,'J1 Lijnen'!$A:$A,$B18,'J1 Lijnen'!$K:$K,0.06) | Q18: =SUMIFS('J1 Lijnen'!$L:$L,'J1 Lijnen'!$A:$A,$B18,'J1 Lijnen'!$K:$K,0.06) | R18: =SUMIFS('J1 Lijnen'!$J:$J,'J1 Lijnen'!$A:$A,$B18,'J1 Lijnen'!$E:$E,"verpakking") | S18: =-SUMIFS('J1 Lijnen'!$J:$J,'J1 Lijnen'!$A:$A,$B18,'J1 Lijnen'!$E:$E,"financiële korting") | T18: =SUM(N18:S18) | X18: U2026-07 | Y18: =SUMIFS('J1 Journaal'!$K:$K,'J1 Journaal'!$E:$E,$B18)-SUMIFS('J1 Journaal'!$L:$L,'J1 Journaal'!$E:$E,$B18)
A19: 9 | B19: V1 | C19: VERPLICHT | D19: K1 | E19: VK | F19: handelsgoederen | G19: 46056 | H19: =G19+30 | I19: 2026-003 | J19: Fietsatelier Noor bv | K19: Velocity Deelfietsen bv | N19: =SUMIFS('J1 Lijnen'!$J:$J,'J1 Lijnen'!$A:$A,$B19,'J1 Lijnen'!$K:$K,0.21,'J1 Lijnen'!$E:$E,"<>verpakking") | O19: =SUMIFS('J1 Lijnen'!$L:$L,'J1 Lijnen'!$A:$A,$B19,'J1 Lijnen'!$K:$K,0.21) | P19: =SUMIFS('J1 Lijnen'!$J:$J,'J1 Lijnen'!$A:$A,$B19,'J1 Lijnen'!$K:$K,0.06) | Q19: =SUMIFS('J1 Lijnen'!$L:$L,'J1 Lijnen'!$A:$A,$B19,'J1 Lijnen'!$K:$K,0.06) | R19: =SUMIFS('J1 Lijnen'!$J:$J,'J1 Lijnen'!$A:$A,$B19,'J1 Lijnen'!$E:$E,"verpakking") | S19: =-SUMIFS('J1 Lijnen'!$J:$J,'J1 Lijnen'!$A:$A,$B19,'J1 Lijnen'!$E:$E,"financiële korting") | T19: =SUM(N19:S19) | X19: U2026-06 | Y19: =SUMIFS('J1 Journaal'!$K:$K,'J1 Journaal'!$E:$E,$B19)-SUMIFS('J1 Journaal'!$L:$L,'J1 Journaal'!$E:$E,$B19)
A20: 10 | B20: V2 | C20: VERPLICHT | D20: K1 | E20: VK | F20: handelsgoederen | G20: 46063 | H20: =G20+30 | I20: 2026-004 | J20: Fietsatelier Noor bv | K20: Bouwbedrijf Janssens & Zonen bv | N20: =SUMIFS('J1 Lijnen'!$J:$J,'J1 Lijnen'!$A:$A,$B20,'J1 Lijnen'!$K:$K,0.21,'J1 Lijnen'!$E:$E,"<>verpakking") | O20: =SUMIFS('J1 Lijnen'!$L:$L,'J1 Lijnen'!$A:$A,$B20,'J1 Lijnen'!$K:$K,0.21) | P20: =SUMIFS('J1 Lijnen'!$J:$J,'J1 Lijnen'!$A:$A,$B20,'J1 Lijnen'!$K:$K,0.06) | Q20: =SUMIFS('J1 Lijnen'!$L:$L,'J1 Lijnen'!$A:$A,$B20,'J1 Lijnen'!$K:$K,0.06) | R20: =SUMIFS('J1 Lijnen'!$J:$J,'J1 Lijnen'!$A:$A,$B20,'J1 Lijnen'!$E:$E,"verpakking") | S20: =-SUMIFS('J1 Lijnen'!$J:$J,'J1 Lijnen'!$A:$A,$B20,'J1 Lijnen'!$E:$E,"financiële korting") | T20: =SUM(N20:S20) | X20: U2026-05 | Y20: =SUMIFS('J1 Journaal'!$K:$K,'J1 Journaal'!$E:$E,$B20)-SUMIFS('J1 Journaal'!$L:$L,'J1 Journaal'!$E:$E,$B20)
A21: 11 | B21: V3 | C21: VERPLICHT | D21: K1 | E21: VK | F21: handelsgoederen | G21: 46065 | H21: =G21+30 | I21: 2026-005 | J21: Fietsatelier Noor bv | K21: Architectenbureau Dubois srl | N21: =SUMIFS('J1 Lijnen'!$J:$J,'J1 Lijnen'!$A:$A,$B21,'J1 Lijnen'!$K:$K,0.21,'J1 Lijnen'!$E:$E,"<>verpakking") | O21: =SUMIFS('J1 Lijnen'!$L:$L,'J1 Lijnen'!$A:$A,$B21,'J1 Lijnen'!$K:$K,0.21) | P21: =SUMIFS('J1 Lijnen'!$J:$J,'J1 Lijnen'!$A:$A,$B21,'J1 Lijnen'!$K:$K,0.06) | Q21: =SUMIFS('J1 Lijnen'!$L:$L,'J1 Lijnen'!$A:$A,$B21,'J1 Lijnen'!$K:$K,0.06) | R21: =SUMIFS('J1 Lijnen'!$J:$J,'J1 Lijnen'!$A:$A,$B21,'J1 Lijnen'!$E:$E,"verpakking") | S21: =-SUMIFS('J1 Lijnen'!$J:$J,'J1 Lijnen'!$A:$A,$B21,'J1 Lijnen'!$E:$E,"financiële korting") | T21: =SUM(N21:S21) | X21: U2026-06 | Y21: =SUMIFS('J1 Journaal'!$K:$K,'J1 Journaal'!$E:$E,$B21)-SUMIFS('J1 Journaal'!$L:$L,'J1 Journaal'!$E:$E,$B21)
A22: 12 | B22: V4 | C22: VERPLICHT | D22: K1 | E22: VK | F22: herstellingen | G22: 46070 | H22: =G22+30 | I22: 2026-006 | J22: Fietsatelier Noor bv | K22: Snelpost bv | N22: =SUMIFS('J1 Lijnen'!$J:$J,'J1 Lijnen'!$A:$A,$B22,'J1 Lijnen'!$K:$K,0.21,'J1 Lijnen'!$E:$E,"<>verpakking") | O22: =SUMIFS('J1 Lijnen'!$L:$L,'J1 Lijnen'!$A:$A,$B22,'J1 Lijnen'!$K:$K,0.21) | P22: =SUMIFS('J1 Lijnen'!$J:$J,'J1 Lijnen'!$A:$A,$B22,'J1 Lijnen'!$K:$K,0.06) | Q22: =SUMIFS('J1 Lijnen'!$L:$L,'J1 Lijnen'!$A:$A,$B22,'J1 Lijnen'!$K:$K,0.06) | R22: =SUMIFS('J1 Lijnen'!$J:$J,'J1 Lijnen'!$A:$A,$B22,'J1 Lijnen'!$E:$E,"verpakking") | S22: =-SUMIFS('J1 Lijnen'!$J:$J,'J1 Lijnen'!$A:$A,$B22,'J1 Lijnen'!$E:$E,"financiële korting") | T22: =SUM(N22:S22) | X22: U2026-07 | Y22: =SUMIFS('J1 Journaal'!$K:$K,'J1 Journaal'!$E:$E,$B22)-SUMIFS('J1 Journaal'!$L:$L,'J1 Journaal'!$E:$E,$B22)
A23: 13 | B23: V5 | C23: VERPLICHT | D23: K1 | E23: VK | F23: handelsgoederen | G23: 46072 | H23: =G23+30 | I23: 2026-007 | J23: Fietsatelier Noor bv | K23: Koffiebar Da Silva | N23: =SUMIFS('J1 Lijnen'!$J:$J,'J1 Lijnen'!$A:$A,$B23,'J1 Lijnen'!$K:$K,0.21,'J1 Lijnen'!$E:$E,"<>verpakking") | O23: =SUMIFS('J1 Lijnen'!$L:$L,'J1 Lijnen'!$A:$A,$B23,'J1 Lijnen'!$K:$K,0.21) | P23: =SUMIFS('J1 Lijnen'!$J:$J,'J1 Lijnen'!$A:$A,$B23,'J1 Lijnen'!$K:$K,0.06) | Q23: =SUMIFS('J1 Lijnen'!$L:$L,'J1 Lijnen'!$A:$A,$B23,'J1 Lijnen'!$K:$K,0.06) | R23: =SUMIFS('J1 Lijnen'!$J:$J,'J1 Lijnen'!$A:$A,$B23,'J1 Lijnen'!$E:$E,"verpakking") | S23: =-SUMIFS('J1 Lijnen'!$J:$J,'J1 Lijnen'!$A:$A,$B23,'J1 Lijnen'!$E:$E,"financiële korting") | T23: =SUM(N23:S23) | X23: U2026-07 | Y23: =SUMIFS('J1 Journaal'!$K:$K,'J1 Journaal'!$E:$E,$B23)-SUMIFS('J1 Journaal'!$L:$L,'J1 Journaal'!$E:$E,$B23)
A24: 14 | B24: CV1 | C24: VERPLICHT | D24: K1 | E24: CN-VK | F24: retour | G24: 46073 | I24: CN-2026-002 | J24: Fietsatelier Noor bv | K24: Velocity Deelfietsen bv | L24: 2026-003 | M24: 1 fiets met defecte versnelling teruggenomen | N24: =SUMIFS('J1 Lijnen'!$J:$J,'J1 Lijnen'!$A:$A,$B24,'J1 Lijnen'!$K:$K,0.21,'J1 Lijnen'!$E:$E,"<>verpakking") | O24: =SUMIFS('J1 Lijnen'!$L:$L,'J1 Lijnen'!$A:$A,$B24,'J1 Lijnen'!$K:$K,0.21) | P24: =SUMIFS('J1 Lijnen'!$J:$J,'J1 Lijnen'!$A:$A,$B24,'J1 Lijnen'!$K:$K,0.06) | Q24: =SUMIFS('J1 Lijnen'!$L:$L,'J1 Lijnen'!$A:$A,$B24,'J1 Lijnen'!$K:$K,0.06) | R24: =SUMIFS('J1 Lijnen'!$J:$J,'J1 Lijnen'!$A:$A,$B24,'J1 Lijnen'!$E:$E,"verpakking") | S24: =-SUMIFS('J1 Lijnen'!$J:$J,'J1 Lijnen'!$A:$A,$B24,'J1 Lijnen'!$E:$E,"financiële korting") | T24: =SUM(N24:S24) | X24: U2026-06 | Y24: =SUMIFS('J1 Journaal'!$K:$K,'J1 Journaal'!$E:$E,$B24)-SUMIFS('J1 Journaal'!$L:$L,'J1 Journaal'!$E:$E,$B24)
A25: 15 | B25: CV2 | C25: VERPLICHT | D25: K1 | E25: CN-VK | F25: retour | G25: 46076 | I25: CN-2026-003 | J25: Fietsatelier Noor bv | K25: Koffiebar Da Silva | L25: 2026-007 | M25: 2 helmen in de verkeerde maat teruggebracht | N25: =SUMIFS('J1 Lijnen'!$J:$J,'J1 Lijnen'!$A:$A,$B25,'J1 Lijnen'!$K:$K,0.21,'J1 Lijnen'!$E:$E,"<>verpakking") | O25: =SUMIFS('J1 Lijnen'!$L:$L,'J1 Lijnen'!$A:$A,$B25,'J1 Lijnen'!$K:$K,0.21) | P25: =SUMIFS('J1 Lijnen'!$J:$J,'J1 Lijnen'!$A:$A,$B25,'J1 Lijnen'!$K:$K,0.06) | Q25: =SUMIFS('J1 Lijnen'!$L:$L,'J1 Lijnen'!$A:$A,$B25,'J1 Lijnen'!$K:$K,0.06) | R25: =SUMIFS('J1 Lijnen'!$J:$J,'J1 Lijnen'!$A:$A,$B25,'J1 Lijnen'!$E:$E,"verpakking") | S25: =-SUMIFS('J1 Lijnen'!$J:$J,'J1 Lijnen'!$A:$A,$B25,'J1 Lijnen'!$E:$E,"financiële korting") | T25: =SUM(N25:S25) | X25: U2026-07 | Y25: =SUMIFS('J1 Journaal'!$K:$K,'J1 Journaal'!$E:$E,$B25)-SUMIFS('J1 Journaal'!$L:$L,'J1 Journaal'!$E:$E,$B25)
A26: 16 | B26: CV3 | C26: VERPLICHT | D26: K1 | E26: CN-VK | F26: retour | G26: 46083 | I26: CN-2026-004 | J26: Fietsatelier Noor bv | K26: Architectenbureau Dubois srl | L26: 2026-005 | M26: 1 e-bike met defecte batterij teruggenomen (factuur was al betaald) | N26: =SUMIFS('J1 Lijnen'!$J:$J,'J1 Lijnen'!$A:$A,$B26,'J1 Lijnen'!$K:$K,0.21,'J1 Lijnen'!$E:$E,"<>verpakking") | O26: =SUMIFS('J1 Lijnen'!$L:$L,'J1 Lijnen'!$A:$A,$B26,'J1 Lijnen'!$K:$K,0.21) | P26: =SUMIFS('J1 Lijnen'!$J:$J,'J1 Lijnen'!$A:$A,$B26,'J1 Lijnen'!$K:$K,0.06) | Q26: =SUMIFS('J1 Lijnen'!$L:$L,'J1 Lijnen'!$A:$A,$B26,'J1 Lijnen'!$K:$K,0.06) | R26: =SUMIFS('J1 Lijnen'!$J:$J,'J1 Lijnen'!$A:$A,$B26,'J1 Lijnen'!$E:$E,"verpakking") | S26: =-SUMIFS('J1 Lijnen'!$J:$J,'J1 Lijnen'!$A:$A,$B26,'J1 Lijnen'!$E:$E,"financiële korting") | T26: =SUM(N26:S26) | X26: U2026-07 | Y26: =SUMIFS('J1 Journaal'!$K:$K,'J1 Journaal'!$E:$E,$B26)-SUMIFS('J1 Journaal'!$L:$L,'J1 Journaal'!$E:$E,$B26)
A27: 17 | B27: D1 | C27: VERPLICHT | D27: K1 | E27: DO | F27: dagontvangst | G27: 46060 | I27: DO-2026-02 | J27: Fietsatelier Noor bv | K27: particulieren (kasticket) | M27: Dagontvangsten winkel (verkopen aan particulieren) | N27: =SUMIFS('J1 Lijnen'!$J:$J,'J1 Lijnen'!$A:$A,$B27,'J1 Lijnen'!$K:$K,0.21,'J1 Lijnen'!$E:$E,"<>verpakking") | O27: =SUMIFS('J1 Lijnen'!$L:$L,'J1 Lijnen'!$A:$A,$B27,'J1 Lijnen'!$K:$K,0.21) | P27: =SUMIFS('J1 Lijnen'!$J:$J,'J1 Lijnen'!$A:$A,$B27,'J1 Lijnen'!$K:$K,0.06) | Q27: =SUMIFS('J1 Lijnen'!$L:$L,'J1 Lijnen'!$A:$A,$B27,'J1 Lijnen'!$K:$K,0.06) | R27: =SUMIFS('J1 Lijnen'!$J:$J,'J1 Lijnen'!$A:$A,$B27,'J1 Lijnen'!$E:$E,"verpakking") | S27: =-SUMIFS('J1 Lijnen'!$J:$J,'J1 Lijnen'!$A:$A,$B27,'J1 Lijnen'!$E:$E,"financiële korting") | T27: =SUM(N27:S27) | V27: =T27-W27 | W27: 1500 | X27: D1K, U2026-04 | Y27: =SUMIFS('J1 Journaal'!$K:$K,'J1 Journaal'!$E:$E,$B27)-SUMIFS('J1 Journaal'!$L:$L,'J1 Journaal'!$E:$E,$B27)
A28: 18 | B28: D1K | C28: VERPLICHT | D28: K1 | E28: KAS | F28: ontvangst | G28: 46060 | I28: Kasboek DO-2026-02 | J28: Fietsatelier Noor bv | K28: Fietsatelier Noor bv | L28: DO-2026-02 | M28: Contant deel van dagontvangst DO-2026-02 (laat de vordering op de klanten dalen) | T28: 633 | V28: 633 | Y28: =SUMIFS('J1 Journaal'!$K:$K,'J1 Journaal'!$E:$E,$B28)-SUMIFS('J1 Journaal'!$L:$L,'J1 Journaal'!$E:$E,$B28)
A29: 19 | B29: D2 | C29: VERPLICHT | D29: K1 | E29: DO | F29: dagontvangst | G29: 46067 | I29: DO-2026-03 | J29: Fietsatelier Noor bv | K29: particulieren (kasticket) | M29: Dagontvangsten winkel (verkopen aan particulieren) | N29: =SUMIFS('J1 Lijnen'!$J:$J,'J1 Lijnen'!$A:$A,$B29,'J1 Lijnen'!$K:$K,0.21,'J1 Lijnen'!$E:$E,"<>verpakking") | O29: =SUMIFS('J1 Lijnen'!$L:$L,'J1 Lijnen'!$A:$A,$B29,'J1 Lijnen'!$K:$K,0.21) | P29: =SUMIFS('J1 Lijnen'!$J:$J,'J1 Lijnen'!$A:$A,$B29,'J1 Lijnen'!$K:$K,0.06) | Q29: =SUMIFS('J1 Lijnen'!$L:$L,'J1 Lijnen'!$A:$A,$B29,'J1 Lijnen'!$K:$K,0.06) | R29: =SUMIFS('J1 Lijnen'!$J:$J,'J1 Lijnen'!$A:$A,$B29,'J1 Lijnen'!$E:$E,"verpakking") | S29: =-SUMIFS('J1 Lijnen'!$J:$J,'J1 Lijnen'!$A:$A,$B29,'J1 Lijnen'!$E:$E,"financiële korting") | T29: =SUM(N29:S29) | V29: =T29-W29 | W29: 2500 | X29: D2K, U2026-05 | Y29: =SUMIFS('J1 Journaal'!$K:$K,'J1 Journaal'!$E:$E,$B29)-SUMIFS('J1 Journaal'!$L:$L,'J1 Journaal'!$E:$E,$B29)
A30: 20 | B30: D2K | C30: VERPLICHT | D30: K1 | E30: KAS | F30: ontvangst | G30: 46067 | I30: Kasboek DO-2026-03 | J30: Fietsatelier Noor bv | K30: Fietsatelier Noor bv | L30: DO-2026-03 | M30: Contant deel van dagontvangst DO-2026-03 (laat de vordering op de klanten dalen) | T30: 344 | V30: 344 | Y30: =SUMIFS('J1 Journaal'!$K:$K,'J1 Journaal'!$E:$E,$B30)-SUMIFS('J1 Journaal'!$L:$L,'J1 Journaal'!$E:$E,$B30)
A31: 21 | B31: D3 | C31: VERPLICHT | D31: K1 | E31: DO | F31: dagontvangst | G31: 46074 | I31: DO-2026-04 | J31: Fietsatelier Noor bv | K31: particulieren (kasticket) | M31: Dagontvangsten winkel (verkopen aan particulieren) | N31: =SUMIFS('J1 Lijnen'!$J:$J,'J1 Lijnen'!$A:$A,$B31,'J1 Lijnen'!$K:$K,0.21,'J1 Lijnen'!$E:$E,"<>verpakking") | O31: =SUMIFS('J1 Lijnen'!$L:$L,'J1 Lijnen'!$A:$A,$B31,'J1 Lijnen'!$K:$K,0.21) | P31: =SUMIFS('J1 Lijnen'!$J:$J,'J1 Lijnen'!$A:$A,$B31,'J1 Lijnen'!$K:$K,0.06) | Q31: =SUMIFS('J1 Lijnen'!$L:$L,'J1 Lijnen'!$A:$A,$B31,'J1 Lijnen'!$K:$K,0.06) | R31: =SUMIFS('J1 Lijnen'!$J:$J,'J1 Lijnen'!$A:$A,$B31,'J1 Lijnen'!$E:$E,"verpakking") | S31: =-SUMIFS('J1 Lijnen'!$J:$J,'J1 Lijnen'!$A:$A,$B31,'J1 Lijnen'!$E:$E,"financiële korting") | T31: =SUM(N31:S31) | V31: =T31-W31 | W31: 1000 | X31: D3K, U2026-06 | Y31: =SUMIFS('J1 Journaal'!$K:$K,'J1 Journaal'!$E:$E,$B31)-SUMIFS('J1 Journaal'!$L:$L,'J1 Journaal'!$E:$E,$B31)
A32: 22 | B32: D3K | C32: VERPLICHT | D32: K1 | E32: KAS | F32: ontvangst | G32: 46074 | I32: Kasboek DO-2026-04 | J32: Fietsatelier Noor bv | K32: Fietsatelier Noor bv | L32: DO-2026-04 | M32: Contant deel van dagontvangst DO-2026-04 (laat de vordering op de klanten dalen) | T32: 354 | V32: 354 | Y32: =SUMIFS('J1 Journaal'!$K:$K,'J1 Journaal'!$E:$E,$B32)-SUMIFS('J1 Journaal'!$L:$L,'J1 Journaal'!$E:$E,$B32)
A33: 1 | B33: Q2A1 | C33: OEFEN | D33: K2 | E33: AK | F33: handelsgoederen | G33: 46114 | H33: =G33+30 | I33: 2026-411 | J33: Velomax bv | K33: Fietsatelier Noor bv | N33: =SUMIFS('J1 Lijnen'!$J:$J,'J1 Lijnen'!$A:$A,$B33,'J1 Lijnen'!$K:$K,0.21,'J1 Lijnen'!$E:$E,"<>verpakking") | O33: =SUMIFS('J1 Lijnen'!$L:$L,'J1 Lijnen'!$A:$A,$B33,'J1 Lijnen'!$K:$K,0.21) | P33: =SUMIFS('J1 Lijnen'!$J:$J,'J1 Lijnen'!$A:$A,$B33,'J1 Lijnen'!$K:$K,0.06) | Q33: =SUMIFS('J1 Lijnen'!$L:$L,'J1 Lijnen'!$A:$A,$B33,'J1 Lijnen'!$K:$K,0.06) | R33: =SUMIFS('J1 Lijnen'!$J:$J,'J1 Lijnen'!$A:$A,$B33,'J1 Lijnen'!$E:$E,"verpakking") | S33: =-SUMIFS('J1 Lijnen'!$J:$J,'J1 Lijnen'!$A:$A,$B33,'J1 Lijnen'!$E:$E,"financiële korting") | T33: =SUM(N33:S33) | X33: U2026-08 | Y33: =SUMIFS('J1 Journaal'!$K:$K,'J1 Journaal'!$E:$E,$B33)-SUMIFS('J1 Journaal'!$L:$L,'J1 Journaal'!$E:$E,$B33)
A34: 2 | B34: Q2A2 | C34: OEFEN | D34: K2 | E34: AK | F34: diensten | G34: 46120 | H34: =G34+30 | I34: SK-26-1290 | J34: Stroomkracht nv | K34: Fietsatelier Noor bv | N34: =SUMIFS('J1 Lijnen'!$J:$J,'J1 Lijnen'!$A:$A,$B34,'J1 Lijnen'!$K:$K,0.21,'J1 Lijnen'!$E:$E,"<>verpakking") | O34: =SUMIFS('J1 Lijnen'!$L:$L,'J1 Lijnen'!$A:$A,$B34,'J1 Lijnen'!$K:$K,0.21) | P34: =SUMIFS('J1 Lijnen'!$J:$J,'J1 Lijnen'!$A:$A,$B34,'J1 Lijnen'!$K:$K,0.06) | Q34: =SUMIFS('J1 Lijnen'!$L:$L,'J1 Lijnen'!$A:$A,$B34,'J1 Lijnen'!$K:$K,0.06) | R34: =SUMIFS('J1 Lijnen'!$J:$J,'J1 Lijnen'!$A:$A,$B34,'J1 Lijnen'!$E:$E,"verpakking") | S34: =-SUMIFS('J1 Lijnen'!$J:$J,'J1 Lijnen'!$A:$A,$B34,'J1 Lijnen'!$E:$E,"financiële korting") | T34: =SUM(N34:S34) | X34: U2026-08 | Y34: =SUMIFS('J1 Journaal'!$K:$K,'J1 Journaal'!$E:$E,$B34)-SUMIFS('J1 Journaal'!$L:$L,'J1 Journaal'!$E:$E,$B34)
A35: 3 | B35: Q2V1 | C35: OEFEN | D35: K2 | E35: VK | F35: handelsgoederen | G35: 46122 | H35: =G35+30 | I35: 2026-008 | J35: Fietsatelier Noor bv | K35: Camping De Vlinder bv | N35: =SUMIFS('J1 Lijnen'!$J:$J,'J1 Lijnen'!$A:$A,$B35,'J1 Lijnen'!$K:$K,0.21,'J1 Lijnen'!$E:$E,"<>verpakking") | O35: =SUMIFS('J1 Lijnen'!$L:$L,'J1 Lijnen'!$A:$A,$B35,'J1 Lijnen'!$K:$K,0.21) | P35: =SUMIFS('J1 Lijnen'!$J:$J,'J1 Lijnen'!$A:$A,$B35,'J1 Lijnen'!$K:$K,0.06) | Q35: =SUMIFS('J1 Lijnen'!$L:$L,'J1 Lijnen'!$A:$A,$B35,'J1 Lijnen'!$K:$K,0.06) | R35: =SUMIFS('J1 Lijnen'!$J:$J,'J1 Lijnen'!$A:$A,$B35,'J1 Lijnen'!$E:$E,"verpakking") | S35: =-SUMIFS('J1 Lijnen'!$J:$J,'J1 Lijnen'!$A:$A,$B35,'J1 Lijnen'!$E:$E,"financiële korting") | T35: =SUM(N35:S35) | X35: U2026-08 | Y35: =SUMIFS('J1 Journaal'!$K:$K,'J1 Journaal'!$E:$E,$B35)-SUMIFS('J1 Journaal'!$L:$L,'J1 Journaal'!$E:$E,$B35)
A36: 4 | B36: Q2CA1 | C36: OEFEN | D36: K2 | E36: CN-AK | F36: retour | G36: 46124 | I36: CN-2026-029 | J36: Velomax bv | K36: Fietsatelier Noor bv | L36: 2026-411 | M36: 2 kinderfietsen in de verkeerde kleur, teruggestuurd | N36: =SUMIFS('J1 Lijnen'!$J:$J,'J1 Lijnen'!$A:$A,$B36,'J1 Lijnen'!$K:$K,0.21,'J1 Lijnen'!$E:$E,"<>verpakking") | O36: =SUMIFS('J1 Lijnen'!$L:$L,'J1 Lijnen'!$A:$A,$B36,'J1 Lijnen'!$K:$K,0.21) | P36: =SUMIFS('J1 Lijnen'!$J:$J,'J1 Lijnen'!$A:$A,$B36,'J1 Lijnen'!$K:$K,0.06) | Q36: =SUMIFS('J1 Lijnen'!$L:$L,'J1 Lijnen'!$A:$A,$B36,'J1 Lijnen'!$K:$K,0.06) | R36: =SUMIFS('J1 Lijnen'!$J:$J,'J1 Lijnen'!$A:$A,$B36,'J1 Lijnen'!$E:$E,"verpakking") | S36: =-SUMIFS('J1 Lijnen'!$J:$J,'J1 Lijnen'!$A:$A,$B36,'J1 Lijnen'!$E:$E,"financiële korting") | T36: =SUM(N36:S36) | X36: U2026-08 | Y36: =SUMIFS('J1 Journaal'!$K:$K,'J1 Journaal'!$E:$E,$B36)-SUMIFS('J1 Journaal'!$L:$L,'J1 Journaal'!$E:$E,$B36)
A37: 5 | B37: Q2CV1 | C37: OEFEN | D37: K2 | E37: CN-VK | F37: retour | G37: 46127 | I37: CN-2026-005 | J37: Fietsatelier Noor bv | K37: Camping De Vlinder bv | L37: 2026-008 | M37: 2 helmen te veel geleverd, teruggebracht | N37: =SUMIFS('J1 Lijnen'!$J:$J,'J1 Lijnen'!$A:$A,$B37,'J1 Lijnen'!$K:$K,0.21,'J1 Lijnen'!$E:$E,"<>verpakking") | O37: =SUMIFS('J1 Lijnen'!$L:$L,'J1 Lijnen'!$A:$A,$B37,'J1 Lijnen'!$K:$K,0.21) | P37: =SUMIFS('J1 Lijnen'!$J:$J,'J1 Lijnen'!$A:$A,$B37,'J1 Lijnen'!$K:$K,0.06) | Q37: =SUMIFS('J1 Lijnen'!$L:$L,'J1 Lijnen'!$A:$A,$B37,'J1 Lijnen'!$K:$K,0.06) | R37: =SUMIFS('J1 Lijnen'!$J:$J,'J1 Lijnen'!$A:$A,$B37,'J1 Lijnen'!$E:$E,"verpakking") | S37: =-SUMIFS('J1 Lijnen'!$J:$J,'J1 Lijnen'!$A:$A,$B37,'J1 Lijnen'!$E:$E,"financiële korting") | T37: =SUM(N37:S37) | X37: U2026-08 | Y37: =SUMIFS('J1 Journaal'!$K:$K,'J1 Journaal'!$E:$E,$B37)-SUMIFS('J1 Journaal'!$L:$L,'J1 Journaal'!$E:$E,$B37)
A38: 6 | B38: Q2A3 | C38: OEFEN | D38: K2 | E38: AK | F38: vaste activa | G38: 46129 | H38: =G38+30 | I38: DW-2026-087 | J38: Deprez Werkplaatsinrichting bv | K38: Fietsatelier Noor bv | N38: =SUMIFS('J1 Lijnen'!$J:$J,'J1 Lijnen'!$A:$A,$B38,'J1 Lijnen'!$K:$K,0.21,'J1 Lijnen'!$E:$E,"<>verpakking") | O38: =SUMIFS('J1 Lijnen'!$L:$L,'J1 Lijnen'!$A:$A,$B38,'J1 Lijnen'!$K:$K,0.21) | P38: =SUMIFS('J1 Lijnen'!$J:$J,'J1 Lijnen'!$A:$A,$B38,'J1 Lijnen'!$K:$K,0.06) | Q38: =SUMIFS('J1 Lijnen'!$L:$L,'J1 Lijnen'!$A:$A,$B38,'J1 Lijnen'!$K:$K,0.06) | R38: =SUMIFS('J1 Lijnen'!$J:$J,'J1 Lijnen'!$A:$A,$B38,'J1 Lijnen'!$E:$E,"verpakking") | S38: =-SUMIFS('J1 Lijnen'!$J:$J,'J1 Lijnen'!$A:$A,$B38,'J1 Lijnen'!$E:$E,"financiële korting") | T38: =SUM(N38:S38) | X38: U2026-09 | Y38: =SUMIFS('J1 Journaal'!$K:$K,'J1 Journaal'!$E:$E,$B38)-SUMIFS('J1 Journaal'!$L:$L,'J1 Journaal'!$E:$E,$B38)
A39: 7 | B39: Q2V2 | C39: OEFEN | D39: K2 | E39: VK | F39: handelsgoederen | G39: 46134 | H39: =G39+30 | I39: 2026-009 | J39: Fietsatelier Noor bv | K39: Bytewise bv | N39: =SUMIFS('J1 Lijnen'!$J:$J,'J1 Lijnen'!$A:$A,$B39,'J1 Lijnen'!$K:$K,0.21,'J1 Lijnen'!$E:$E,"<>verpakking") | O39: =SUMIFS('J1 Lijnen'!$L:$L,'J1 Lijnen'!$A:$A,$B39,'J1 Lijnen'!$K:$K,0.21) | P39: =SUMIFS('J1 Lijnen'!$J:$J,'J1 Lijnen'!$A:$A,$B39,'J1 Lijnen'!$K:$K,0.06) | Q39: =SUMIFS('J1 Lijnen'!$L:$L,'J1 Lijnen'!$A:$A,$B39,'J1 Lijnen'!$K:$K,0.06) | R39: =SUMIFS('J1 Lijnen'!$J:$J,'J1 Lijnen'!$A:$A,$B39,'J1 Lijnen'!$E:$E,"verpakking") | S39: =-SUMIFS('J1 Lijnen'!$J:$J,'J1 Lijnen'!$A:$A,$B39,'J1 Lijnen'!$E:$E,"financiële korting") | T39: =SUM(N39:S39) | X39: U2026-09 | Y39: =SUMIFS('J1 Journaal'!$K:$K,'J1 Journaal'!$E:$E,$B39)-SUMIFS('J1 Journaal'!$L:$L,'J1 Journaal'!$E:$E,$B39)
A40: 9 | B40: Q2A4 | C40: OEFEN | D40: K2 | E40: AK | F40: handelsgoederen | G40: 46148 | H40: =G40+30 | I40: SW-1290 | J40: Spaakwerk bv | K40: Fietsatelier Noor bv | N40: =SUMIFS('J1 Lijnen'!$J:$J,'J1 Lijnen'!$A:$A,$B40,'J1 Lijnen'!$K:$K,0.21,'J1 Lijnen'!$E:$E,"<>verpakking") | O40: =SUMIFS('J1 Lijnen'!$L:$L,'J1 Lijnen'!$A:$A,$B40,'J1 Lijnen'!$K:$K,0.21) | P40: =SUMIFS('J1 Lijnen'!$J:$J,'J1 Lijnen'!$A:$A,$B40,'J1 Lijnen'!$K:$K,0.06) | Q40: =SUMIFS('J1 Lijnen'!$L:$L,'J1 Lijnen'!$A:$A,$B40,'J1 Lijnen'!$K:$K,0.06) | R40: =SUMIFS('J1 Lijnen'!$J:$J,'J1 Lijnen'!$A:$A,$B40,'J1 Lijnen'!$E:$E,"verpakking") | S40: =-SUMIFS('J1 Lijnen'!$J:$J,'J1 Lijnen'!$A:$A,$B40,'J1 Lijnen'!$E:$E,"financiële korting") | T40: =SUM(N40:S40) | X40: U2026-09 | Y40: =SUMIFS('J1 Journaal'!$K:$K,'J1 Journaal'!$E:$E,$B40)-SUMIFS('J1 Journaal'!$L:$L,'J1 Journaal'!$E:$E,$B40)
A41: 10 | B41: Q2V3 | C41: OEFEN | D41: K2 | E41: VK | F41: herstellingen | G41: 46155 | H41: =G41+30 | I41: 2026-010 | J41: Fietsatelier Noor bv | K41: Snelpost bv | N41: =SUMIFS('J1 Lijnen'!$J:$J,'J1 Lijnen'!$A:$A,$B41,'J1 Lijnen'!$K:$K,0.21,'J1 Lijnen'!$E:$E,"<>verpakking") | O41: =SUMIFS('J1 Lijnen'!$L:$L,'J1 Lijnen'!$A:$A,$B41,'J1 Lijnen'!$K:$K,0.21) | P41: =SUMIFS('J1 Lijnen'!$J:$J,'J1 Lijnen'!$A:$A,$B41,'J1 Lijnen'!$K:$K,0.06) | Q41: =SUMIFS('J1 Lijnen'!$L:$L,'J1 Lijnen'!$A:$A,$B41,'J1 Lijnen'!$K:$K,0.06) | R41: =SUMIFS('J1 Lijnen'!$J:$J,'J1 Lijnen'!$A:$A,$B41,'J1 Lijnen'!$E:$E,"verpakking") | S41: =-SUMIFS('J1 Lijnen'!$J:$J,'J1 Lijnen'!$A:$A,$B41,'J1 Lijnen'!$E:$E,"financiële korting") | T41: =SUM(N41:S41) | X41: U2026-10 | Y41: =SUMIFS('J1 Journaal'!$K:$K,'J1 Journaal'!$E:$E,$B41)-SUMIFS('J1 Journaal'!$L:$L,'J1 Journaal'!$E:$E,$B41)
A42: 12 | B42: Q2CA2 | C42: OEFEN | D42: K2 | E42: CN-AK | F42: retour | G42: 46162 | I42: SW-CN-171 | J42: Spaakwerk bv | K42: Fietsatelier Noor bv | L42: SW-1290 | M42: 4 verlichtingssets defect, teruggestuurd (factuur was al betaald) | N42: =SUMIFS('J1 Lijnen'!$J:$J,'J1 Lijnen'!$A:$A,$B42,'J1 Lijnen'!$K:$K,0.21,'J1 Lijnen'!$E:$E,"<>verpakking") | O42: =SUMIFS('J1 Lijnen'!$L:$L,'J1 Lijnen'!$A:$A,$B42,'J1 Lijnen'!$K:$K,0.21) | P42: =SUMIFS('J1 Lijnen'!$J:$J,'J1 Lijnen'!$A:$A,$B42,'J1 Lijnen'!$K:$K,0.06) | Q42: =SUMIFS('J1 Lijnen'!$L:$L,'J1 Lijnen'!$A:$A,$B42,'J1 Lijnen'!$K:$K,0.06) | R42: =SUMIFS('J1 Lijnen'!$J:$J,'J1 Lijnen'!$A:$A,$B42,'J1 Lijnen'!$E:$E,"verpakking") | S42: =-SUMIFS('J1 Lijnen'!$J:$J,'J1 Lijnen'!$A:$A,$B42,'J1 Lijnen'!$E:$E,"financiële korting") | T42: =SUM(N42:S42) | X42: U2026-10 | Y42: =SUMIFS('J1 Journaal'!$K:$K,'J1 Journaal'!$E:$E,$B42)-SUMIFS('J1 Journaal'!$L:$L,'J1 Journaal'!$E:$E,$B42)
A43: 13 | B43: Q2V4 | C43: OEFEN | D43: K2 | E43: VK | F43: handelsgoederen | G43: 46169 | H43: =G43+30 | I43: 2026-011 | J43: Fietsatelier Noor bv | K43: Studio Kowalski bv | N43: =SUMIFS('J1 Lijnen'!$J:$J,'J1 Lijnen'!$A:$A,$B43,'J1 Lijnen'!$K:$K,0.21,'J1 Lijnen'!$E:$E,"<>verpakking") | O43: =SUMIFS('J1 Lijnen'!$L:$L,'J1 Lijnen'!$A:$A,$B43,'J1 Lijnen'!$K:$K,0.21) | P43: =SUMIFS('J1 Lijnen'!$J:$J,'J1 Lijnen'!$A:$A,$B43,'J1 Lijnen'!$K:$K,0.06) | Q43: =SUMIFS('J1 Lijnen'!$L:$L,'J1 Lijnen'!$A:$A,$B43,'J1 Lijnen'!$K:$K,0.06) | R43: =SUMIFS('J1 Lijnen'!$J:$J,'J1 Lijnen'!$A:$A,$B43,'J1 Lijnen'!$E:$E,"verpakking") | S43: =-SUMIFS('J1 Lijnen'!$J:$J,'J1 Lijnen'!$A:$A,$B43,'J1 Lijnen'!$E:$E,"financiële korting") | T43: =SUM(N43:S43) | X43: U2026-10 | Y43: =SUMIFS('J1 Journaal'!$K:$K,'J1 Journaal'!$E:$E,$B43)-SUMIFS('J1 Journaal'!$L:$L,'J1 Journaal'!$E:$E,$B43)
A44: 14 | B44: Q2CV2 | C44: OEFEN | D44: K2 | E44: CN-VK | F44: retour | G44: 46175 | I44: CN-2026-006 | J44: Fietsatelier Noor bv | K44: Bytewise bv | L44: 2026-009 | M44: 1 e-bike teruggenomen: motor maakt lawaai (factuur was al betaald) | N44: =SUMIFS('J1 Lijnen'!$J:$J,'J1 Lijnen'!$A:$A,$B44,'J1 Lijnen'!$K:$K,0.21,'J1 Lijnen'!$E:$E,"<>verpakking") | O44: =SUMIFS('J1 Lijnen'!$L:$L,'J1 Lijnen'!$A:$A,$B44,'J1 Lijnen'!$K:$K,0.21) | P44: =SUMIFS('J1 Lijnen'!$J:$J,'J1 Lijnen'!$A:$A,$B44,'J1 Lijnen'!$K:$K,0.06) | Q44: =SUMIFS('J1 Lijnen'!$L:$L,'J1 Lijnen'!$A:$A,$B44,'J1 Lijnen'!$K:$K,0.06) | R44: =SUMIFS('J1 Lijnen'!$J:$J,'J1 Lijnen'!$A:$A,$B44,'J1 Lijnen'!$E:$E,"verpakking") | S44: =-SUMIFS('J1 Lijnen'!$J:$J,'J1 Lijnen'!$A:$A,$B44,'J1 Lijnen'!$E:$E,"financiële korting") | T44: =SUM(N44:S44) | X44: U2026-10 | Y44: =SUMIFS('J1 Journaal'!$K:$K,'J1 Journaal'!$E:$E,$B44)-SUMIFS('J1 Journaal'!$L:$L,'J1 Journaal'!$E:$E,$B44)
A45: 15 | B45: Q2D1 | C45: OEFEN | D45: K2 | E45: DO | F45: dagontvangst | G45: 46179 | I45: DO-2026-05 | J45: Fietsatelier Noor bv | K45: particulieren (kasticket) | M45: Dagontvangsten winkel (verkopen aan particulieren) | N45: =SUMIFS('J1 Lijnen'!$J:$J,'J1 Lijnen'!$A:$A,$B45,'J1 Lijnen'!$K:$K,0.21,'J1 Lijnen'!$E:$E,"<>verpakking") | O45: =SUMIFS('J1 Lijnen'!$L:$L,'J1 Lijnen'!$A:$A,$B45,'J1 Lijnen'!$K:$K,0.21) | P45: =SUMIFS('J1 Lijnen'!$J:$J,'J1 Lijnen'!$A:$A,$B45,'J1 Lijnen'!$K:$K,0.06) | Q45: =SUMIFS('J1 Lijnen'!$L:$L,'J1 Lijnen'!$A:$A,$B45,'J1 Lijnen'!$K:$K,0.06) | R45: =SUMIFS('J1 Lijnen'!$J:$J,'J1 Lijnen'!$A:$A,$B45,'J1 Lijnen'!$E:$E,"verpakking") | S45: =-SUMIFS('J1 Lijnen'!$J:$J,'J1 Lijnen'!$A:$A,$B45,'J1 Lijnen'!$E:$E,"financiële korting") | T45: =SUM(N45:S45) | V45: =T45-W45 | W45: 2000 | X45: Q2D1K, U2026-10 | Y45: =SUMIFS('J1 Journaal'!$K:$K,'J1 Journaal'!$E:$E,$B45)-SUMIFS('J1 Journaal'!$L:$L,'J1 Journaal'!$E:$E,$B45)
A46: 16 | B46: Q2D1K | C46: OEFEN | D46: K2 | E46: KAS | F46: ontvangst | G46: 46179 | I46: Kasboek DO-2026-05 | J46: Fietsatelier Noor bv | K46: Fietsatelier Noor bv | L46: DO-2026-05 | M46: Contant deel van dagontvangst DO-2026-05 (laat de vordering op de klanten dalen) | T46: 466 | V46: 466 | Y46: =SUMIFS('J1 Journaal'!$K:$K,'J1 Journaal'!$E:$E,$B46)-SUMIFS('J1 Journaal'!$L:$L,'J1 Journaal'!$E:$E,$B46)
A47: 1 | B47: Q3A1 | C47: TJ | D47: K3 | E47: AK | F47: handelsgoederen | G47: 46204 | H47: =G47+30 | I47: 2026-702 | J47: Velomax bv | K47: Fietsatelier Noor bv | N47: =SUMIFS('J1 Lijnen'!$J:$J,'J1 Lijnen'!$A:$A,$B47,'J1 Lijnen'!$K:$K,0.21,'J1 Lijnen'!$E:$E,"<>verpakking") | O47: =SUMIFS('J1 Lijnen'!$L:$L,'J1 Lijnen'!$A:$A,$B47,'J1 Lijnen'!$K:$K,0.21) | P47: =SUMIFS('J1 Lijnen'!$J:$J,'J1 Lijnen'!$A:$A,$B47,'J1 Lijnen'!$K:$K,0.06) | Q47: =SUMIFS('J1 Lijnen'!$L:$L,'J1 Lijnen'!$A:$A,$B47,'J1 Lijnen'!$K:$K,0.06) | R47: =SUMIFS('J1 Lijnen'!$J:$J,'J1 Lijnen'!$A:$A,$B47,'J1 Lijnen'!$E:$E,"verpakking") | S47: =-SUMIFS('J1 Lijnen'!$J:$J,'J1 Lijnen'!$A:$A,$B47,'J1 Lijnen'!$E:$E,"financiële korting") | T47: =SUM(N47:S47) | X47: U2026-11 | Y47: =SUMIFS('J1 Journaal'!$K:$K,'J1 Journaal'!$E:$E,$B47)-SUMIFS('J1 Journaal'!$L:$L,'J1 Journaal'!$E:$E,$B47)
A48: 2 | B48: Q3A3 | C48: TJ | D48: K3 | E48: AK | F48: handelsgoederen | G48: 46206 | H48: =G48+30 | I48: HH-26-311 | J48: HelmHuis bv | K48: Fietsatelier Noor bv | N48: =SUMIFS('J1 Lijnen'!$J:$J,'J1 Lijnen'!$A:$A,$B48,'J1 Lijnen'!$K:$K,0.21,'J1 Lijnen'!$E:$E,"<>verpakking") | O48: =SUMIFS('J1 Lijnen'!$L:$L,'J1 Lijnen'!$A:$A,$B48,'J1 Lijnen'!$K:$K,0.21) | P48: =SUMIFS('J1 Lijnen'!$J:$J,'J1 Lijnen'!$A:$A,$B48,'J1 Lijnen'!$K:$K,0.06) | Q48: =SUMIFS('J1 Lijnen'!$L:$L,'J1 Lijnen'!$A:$A,$B48,'J1 Lijnen'!$K:$K,0.06) | R48: =SUMIFS('J1 Lijnen'!$J:$J,'J1 Lijnen'!$A:$A,$B48,'J1 Lijnen'!$E:$E,"verpakking") | S48: =-SUMIFS('J1 Lijnen'!$J:$J,'J1 Lijnen'!$A:$A,$B48,'J1 Lijnen'!$E:$E,"financiële korting") | T48: =SUM(N48:S48) | X48: U2026-12 | Y48: =SUMIFS('J1 Journaal'!$K:$K,'J1 Journaal'!$E:$E,$B48)-SUMIFS('J1 Journaal'!$L:$L,'J1 Journaal'!$E:$E,$B48)
A49: 3 | B49: Q3CA1 | C49: TJ | D49: K3 | E49: CN-AK | F49: retour | G49: 46211 | I49: CN-2026-044 | J49: Velomax bv | K49: Fietsatelier Noor bv | L49: 2026-702 | M49: 1 fiets met gebroken spaken geleverd, teruggestuurd | N49: =SUMIFS('J1 Lijnen'!$J:$J,'J1 Lijnen'!$A:$A,$B49,'J1 Lijnen'!$K:$K,0.21,'J1 Lijnen'!$E:$E,"<>verpakking") | O49: =SUMIFS('J1 Lijnen'!$L:$L,'J1 Lijnen'!$A:$A,$B49,'J1 Lijnen'!$K:$K,0.21) | P49: =SUMIFS('J1 Lijnen'!$J:$J,'J1 Lijnen'!$A:$A,$B49,'J1 Lijnen'!$K:$K,0.06) | Q49: =SUMIFS('J1 Lijnen'!$L:$L,'J1 Lijnen'!$A:$A,$B49,'J1 Lijnen'!$K:$K,0.06) | R49: =SUMIFS('J1 Lijnen'!$J:$J,'J1 Lijnen'!$A:$A,$B49,'J1 Lijnen'!$E:$E,"verpakking") | S49: =-SUMIFS('J1 Lijnen'!$J:$J,'J1 Lijnen'!$A:$A,$B49,'J1 Lijnen'!$E:$E,"financiële korting") | T49: =SUM(N49:S49) | X49: U2026-11 | Y49: =SUMIFS('J1 Journaal'!$K:$K,'J1 Journaal'!$E:$E,$B49)-SUMIFS('J1 Journaal'!$L:$L,'J1 Journaal'!$E:$E,$B49)
A50: 4 | B50: Q3A2 | C50: TJ | D50: K3 | E50: AK | F50: diensten | G50: 46213 | H50: =G50+30 | I50: BN-2026-061 | J50: Boekhoudkantoor Nowak | K50: Fietsatelier Noor bv | N50: =SUMIFS('J1 Lijnen'!$J:$J,'J1 Lijnen'!$A:$A,$B50,'J1 Lijnen'!$K:$K,0.21,'J1 Lijnen'!$E:$E,"<>verpakking") | O50: =SUMIFS('J1 Lijnen'!$L:$L,'J1 Lijnen'!$A:$A,$B50,'J1 Lijnen'!$K:$K,0.21) | P50: =SUMIFS('J1 Lijnen'!$J:$J,'J1 Lijnen'!$A:$A,$B50,'J1 Lijnen'!$K:$K,0.06) | Q50: =SUMIFS('J1 Lijnen'!$L:$L,'J1 Lijnen'!$A:$A,$B50,'J1 Lijnen'!$K:$K,0.06) | R50: =SUMIFS('J1 Lijnen'!$J:$J,'J1 Lijnen'!$A:$A,$B50,'J1 Lijnen'!$E:$E,"verpakking") | S50: =-SUMIFS('J1 Lijnen'!$J:$J,'J1 Lijnen'!$A:$A,$B50,'J1 Lijnen'!$E:$E,"financiële korting") | T50: =SUM(N50:S50) | X50: U2026-11 | Y50: =SUMIFS('J1 Journaal'!$K:$K,'J1 Journaal'!$E:$E,$B50)-SUMIFS('J1 Journaal'!$L:$L,'J1 Journaal'!$E:$E,$B50)
A51: 5 | B51: Q3V1 | C51: TJ | D51: K3 | E51: VK | F51: handelsgoederen | G51: 46217 | H51: =G51+30 | I51: 2026-012 | J51: Fietsatelier Noor bv | K51: Hotel De Linde bv | N51: =SUMIFS('J1 Lijnen'!$J:$J,'J1 Lijnen'!$A:$A,$B51,'J1 Lijnen'!$K:$K,0.21,'J1 Lijnen'!$E:$E,"<>verpakking") | O51: =SUMIFS('J1 Lijnen'!$L:$L,'J1 Lijnen'!$A:$A,$B51,'J1 Lijnen'!$K:$K,0.21) | P51: =SUMIFS('J1 Lijnen'!$J:$J,'J1 Lijnen'!$A:$A,$B51,'J1 Lijnen'!$K:$K,0.06) | Q51: =SUMIFS('J1 Lijnen'!$L:$L,'J1 Lijnen'!$A:$A,$B51,'J1 Lijnen'!$K:$K,0.06) | R51: =SUMIFS('J1 Lijnen'!$J:$J,'J1 Lijnen'!$A:$A,$B51,'J1 Lijnen'!$E:$E,"verpakking") | S51: =-SUMIFS('J1 Lijnen'!$J:$J,'J1 Lijnen'!$A:$A,$B51,'J1 Lijnen'!$E:$E,"financiële korting") | T51: =SUM(N51:S51) | X51: U2026-11 | Y51: =SUMIFS('J1 Journaal'!$K:$K,'J1 Journaal'!$E:$E,$B51)-SUMIFS('J1 Journaal'!$L:$L,'J1 Journaal'!$E:$E,$B51)
A52: 6 | B52: Q3CV1 | C52: TJ | D52: K3 | E52: CN-VK | F52: retour | G52: 46224 | I52: CN-2026-007 | J52: Fietsatelier Noor bv | K52: Hotel De Linde bv | L52: 2026-012 | M52: 1 fiets teruggenomen: lak beschadigd | N52: =SUMIFS('J1 Lijnen'!$J:$J,'J1 Lijnen'!$A:$A,$B52,'J1 Lijnen'!$K:$K,0.21,'J1 Lijnen'!$E:$E,"<>verpakking") | O52: =SUMIFS('J1 Lijnen'!$L:$L,'J1 Lijnen'!$A:$A,$B52,'J1 Lijnen'!$K:$K,0.21) | P52: =SUMIFS('J1 Lijnen'!$J:$J,'J1 Lijnen'!$A:$A,$B52,'J1 Lijnen'!$K:$K,0.06) | Q52: =SUMIFS('J1 Lijnen'!$L:$L,'J1 Lijnen'!$A:$A,$B52,'J1 Lijnen'!$K:$K,0.06) | R52: =SUMIFS('J1 Lijnen'!$J:$J,'J1 Lijnen'!$A:$A,$B52,'J1 Lijnen'!$E:$E,"verpakking") | S52: =-SUMIFS('J1 Lijnen'!$J:$J,'J1 Lijnen'!$A:$A,$B52,'J1 Lijnen'!$E:$E,"financiële korting") | T52: =SUM(N52:S52) | X52: U2026-11 | Y52: =SUMIFS('J1 Journaal'!$K:$K,'J1 Journaal'!$E:$E,$B52)-SUMIFS('J1 Journaal'!$L:$L,'J1 Journaal'!$E:$E,$B52)
A53: 8 | B53: Q3V2 | C53: TJ | D53: K3 | E53: VK | F53: handelsgoederen | G53: 46238 | H53: =G53+30 | I53: 2026-013 | J53: Fietsatelier Noor bv | K53: Bouwbedrijf Janssens & Zonen bv | N53: =SUMIFS('J1 Lijnen'!$J:$J,'J1 Lijnen'!$A:$A,$B53,'J1 Lijnen'!$K:$K,0.21,'J1 Lijnen'!$E:$E,"<>verpakking") | O53: =SUMIFS('J1 Lijnen'!$L:$L,'J1 Lijnen'!$A:$A,$B53,'J1 Lijnen'!$K:$K,0.21) | P53: =SUMIFS('J1 Lijnen'!$J:$J,'J1 Lijnen'!$A:$A,$B53,'J1 Lijnen'!$K:$K,0.06) | Q53: =SUMIFS('J1 Lijnen'!$L:$L,'J1 Lijnen'!$A:$A,$B53,'J1 Lijnen'!$K:$K,0.06) | R53: =SUMIFS('J1 Lijnen'!$J:$J,'J1 Lijnen'!$A:$A,$B53,'J1 Lijnen'!$E:$E,"verpakking") | S53: =-SUMIFS('J1 Lijnen'!$J:$J,'J1 Lijnen'!$A:$A,$B53,'J1 Lijnen'!$E:$E,"financiële korting") | T53: =SUM(N53:S53) | X53: U2026-12 | Y53: =SUMIFS('J1 Journaal'!$K:$K,'J1 Journaal'!$E:$E,$B53)-SUMIFS('J1 Journaal'!$L:$L,'J1 Journaal'!$E:$E,$B53)
A54: 10 | B54: Q3CA2 | C54: TJ | D54: K3 | E54: CN-AK | F54: retour | G54: 46254 | I54: HH-CN-26-019 | J54: HelmHuis bv | K54: Fietsatelier Noor bv | L54: HH-26-311 | M54: 10 helmen zonder veiligheidslabel, teruggestuurd (factuur was al betaald) | N54: =SUMIFS('J1 Lijnen'!$J:$J,'J1 Lijnen'!$A:$A,$B54,'J1 Lijnen'!$K:$K,0.21,'J1 Lijnen'!$E:$E,"<>verpakking") | O54: =SUMIFS('J1 Lijnen'!$L:$L,'J1 Lijnen'!$A:$A,$B54,'J1 Lijnen'!$K:$K,0.21) | P54: =SUMIFS('J1 Lijnen'!$J:$J,'J1 Lijnen'!$A:$A,$B54,'J1 Lijnen'!$K:$K,0.06) | Q54: =SUMIFS('J1 Lijnen'!$L:$L,'J1 Lijnen'!$A:$A,$B54,'J1 Lijnen'!$K:$K,0.06) | R54: =SUMIFS('J1 Lijnen'!$J:$J,'J1 Lijnen'!$A:$A,$B54,'J1 Lijnen'!$E:$E,"verpakking") | S54: =-SUMIFS('J1 Lijnen'!$J:$J,'J1 Lijnen'!$A:$A,$B54,'J1 Lijnen'!$E:$E,"financiële korting") | T54: =SUM(N54:S54) | X54: U2026-13 | Y54: =SUMIFS('J1 Journaal'!$K:$K,'J1 Journaal'!$E:$E,$B54)-SUMIFS('J1 Journaal'!$L:$L,'J1 Journaal'!$E:$E,$B54)
A55: 11 | B55: Q3V3 | C55: TJ | D55: K3 | E55: VK | F55: herstellingen | G55: 46260 | H55: =G55+30 | I55: 2026-014 | J55: Fietsatelier Noor bv | K55: Velocity Deelfietsen bv | N55: =SUMIFS('J1 Lijnen'!$J:$J,'J1 Lijnen'!$A:$A,$B55,'J1 Lijnen'!$K:$K,0.21,'J1 Lijnen'!$E:$E,"<>verpakking") | O55: =SUMIFS('J1 Lijnen'!$L:$L,'J1 Lijnen'!$A:$A,$B55,'J1 Lijnen'!$K:$K,0.21) | P55: =SUMIFS('J1 Lijnen'!$J:$J,'J1 Lijnen'!$A:$A,$B55,'J1 Lijnen'!$K:$K,0.06) | Q55: =SUMIFS('J1 Lijnen'!$L:$L,'J1 Lijnen'!$A:$A,$B55,'J1 Lijnen'!$K:$K,0.06) | R55: =SUMIFS('J1 Lijnen'!$J:$J,'J1 Lijnen'!$A:$A,$B55,'J1 Lijnen'!$E:$E,"verpakking") | S55: =-SUMIFS('J1 Lijnen'!$J:$J,'J1 Lijnen'!$A:$A,$B55,'J1 Lijnen'!$E:$E,"financiële korting") | T55: =SUM(N55:S55) | X55: U2026-13 | Y55: =SUMIFS('J1 Journaal'!$K:$K,'J1 Journaal'!$E:$E,$B55)-SUMIFS('J1 Journaal'!$L:$L,'J1 Journaal'!$E:$E,$B55)
A56: 1 | B56: Q4A1 | C56: REMEDIERING | D56: K4 | E56: AK | F56: handelsgoederen | G56: 46296 | H56: =G56+30 | I56: 2026-1003 | J56: Velomax bv | K56: Fietsatelier Noor bv | N56: =SUMIFS('J1 Lijnen'!$J:$J,'J1 Lijnen'!$A:$A,$B56,'J1 Lijnen'!$K:$K,0.21,'J1 Lijnen'!$E:$E,"<>verpakking") | O56: =SUMIFS('J1 Lijnen'!$L:$L,'J1 Lijnen'!$A:$A,$B56,'J1 Lijnen'!$K:$K,0.21) | P56: =SUMIFS('J1 Lijnen'!$J:$J,'J1 Lijnen'!$A:$A,$B56,'J1 Lijnen'!$K:$K,0.06) | Q56: =SUMIFS('J1 Lijnen'!$L:$L,'J1 Lijnen'!$A:$A,$B56,'J1 Lijnen'!$K:$K,0.06) | R56: =SUMIFS('J1 Lijnen'!$J:$J,'J1 Lijnen'!$A:$A,$B56,'J1 Lijnen'!$E:$E,"verpakking") | S56: =-SUMIFS('J1 Lijnen'!$J:$J,'J1 Lijnen'!$A:$A,$B56,'J1 Lijnen'!$E:$E,"financiële korting") | T56: =SUM(N56:S56) | X56: U2026-14 | Y56: =SUMIFS('J1 Journaal'!$K:$K,'J1 Journaal'!$E:$E,$B56)-SUMIFS('J1 Journaal'!$L:$L,'J1 Journaal'!$E:$E,$B56)
A57: 2 | B57: Q4A2 | C57: REMEDIERING | D57: K4 | E57: AK | F57: vaste activa | G57: 46302 | H57: =G57+30 | I57: KT-0981 | J57: Kassatech bv | K57: Fietsatelier Noor bv | N57: =SUMIFS('J1 Lijnen'!$J:$J,'J1 Lijnen'!$A:$A,$B57,'J1 Lijnen'!$K:$K,0.21,'J1 Lijnen'!$E:$E,"<>verpakking") | O57: =SUMIFS('J1 Lijnen'!$L:$L,'J1 Lijnen'!$A:$A,$B57,'J1 Lijnen'!$K:$K,0.21) | P57: =SUMIFS('J1 Lijnen'!$J:$J,'J1 Lijnen'!$A:$A,$B57,'J1 Lijnen'!$K:$K,0.06) | Q57: =SUMIFS('J1 Lijnen'!$L:$L,'J1 Lijnen'!$A:$A,$B57,'J1 Lijnen'!$K:$K,0.06) | R57: =SUMIFS('J1 Lijnen'!$J:$J,'J1 Lijnen'!$A:$A,$B57,'J1 Lijnen'!$E:$E,"verpakking") | S57: =-SUMIFS('J1 Lijnen'!$J:$J,'J1 Lijnen'!$A:$A,$B57,'J1 Lijnen'!$E:$E,"financiële korting") | T57: =SUM(N57:S57) | X57: U2026-14 | Y57: =SUMIFS('J1 Journaal'!$K:$K,'J1 Journaal'!$E:$E,$B57)-SUMIFS('J1 Journaal'!$L:$L,'J1 Journaal'!$E:$E,$B57)
A58: 3 | B58: Q4V1 | C58: REMEDIERING | D58: K4 | E58: VK | F58: handelsgoederen | G58: 46304 | H58: =G58+30 | I58: 2026-015 | J58: Fietsatelier Noor bv | K58: Brouwerij Van Acker bv | N58: =SUMIFS('J1 Lijnen'!$J:$J,'J1 Lijnen'!$A:$A,$B58,'J1 Lijnen'!$K:$K,0.21,'J1 Lijnen'!$E:$E,"<>verpakking") | O58: =SUMIFS('J1 Lijnen'!$L:$L,'J1 Lijnen'!$A:$A,$B58,'J1 Lijnen'!$K:$K,0.21) | P58: =SUMIFS('J1 Lijnen'!$J:$J,'J1 Lijnen'!$A:$A,$B58,'J1 Lijnen'!$K:$K,0.06) | Q58: =SUMIFS('J1 Lijnen'!$L:$L,'J1 Lijnen'!$A:$A,$B58,'J1 Lijnen'!$K:$K,0.06) | R58: =SUMIFS('J1 Lijnen'!$J:$J,'J1 Lijnen'!$A:$A,$B58,'J1 Lijnen'!$E:$E,"verpakking") | S58: =-SUMIFS('J1 Lijnen'!$J:$J,'J1 Lijnen'!$A:$A,$B58,'J1 Lijnen'!$E:$E,"financiële korting") | T58: =SUM(N58:S58) | X58: U2026-14 | Y58: =SUMIFS('J1 Journaal'!$K:$K,'J1 Journaal'!$E:$E,$B58)-SUMIFS('J1 Journaal'!$L:$L,'J1 Journaal'!$E:$E,$B58)
A59: 4 | B59: Q4CA1 | C59: REMEDIERING | D59: K4 | E59: CN-AK | F59: retour | G59: 46305 | I59: CN-2026-061 | J59: Velomax bv | K59: Fietsatelier Noor bv | L59: 2026-1003 | M59: 1 e-bike met defect display, teruggestuurd | N59: =SUMIFS('J1 Lijnen'!$J:$J,'J1 Lijnen'!$A:$A,$B59,'J1 Lijnen'!$K:$K,0.21,'J1 Lijnen'!$E:$E,"<>verpakking") | O59: =SUMIFS('J1 Lijnen'!$L:$L,'J1 Lijnen'!$A:$A,$B59,'J1 Lijnen'!$K:$K,0.21) | P59: =SUMIFS('J1 Lijnen'!$J:$J,'J1 Lijnen'!$A:$A,$B59,'J1 Lijnen'!$K:$K,0.06) | Q59: =SUMIFS('J1 Lijnen'!$L:$L,'J1 Lijnen'!$A:$A,$B59,'J1 Lijnen'!$K:$K,0.06) | R59: =SUMIFS('J1 Lijnen'!$J:$J,'J1 Lijnen'!$A:$A,$B59,'J1 Lijnen'!$E:$E,"verpakking") | S59: =-SUMIFS('J1 Lijnen'!$J:$J,'J1 Lijnen'!$A:$A,$B59,'J1 Lijnen'!$E:$E,"financiële korting") | T59: =SUM(N59:S59) | X59: U2026-14 | Y59: =SUMIFS('J1 Journaal'!$K:$K,'J1 Journaal'!$E:$E,$B59)-SUMIFS('J1 Journaal'!$L:$L,'J1 Journaal'!$E:$E,$B59)
A60: 5 | B60: Q4CV1 | C60: REMEDIERING | D60: K4 | E60: CN-VK | F60: retour | G60: 46309 | I60: CN-2026-008 | J60: Fietsatelier Noor bv | K60: Brouwerij Van Acker bv | L60: 2026-015 | M60: 1 fiets te veel geleverd, teruggebracht | N60: =SUMIFS('J1 Lijnen'!$J:$J,'J1 Lijnen'!$A:$A,$B60,'J1 Lijnen'!$K:$K,0.21,'J1 Lijnen'!$E:$E,"<>verpakking") | O60: =SUMIFS('J1 Lijnen'!$L:$L,'J1 Lijnen'!$A:$A,$B60,'J1 Lijnen'!$K:$K,0.21) | P60: =SUMIFS('J1 Lijnen'!$J:$J,'J1 Lijnen'!$A:$A,$B60,'J1 Lijnen'!$K:$K,0.06) | Q60: =SUMIFS('J1 Lijnen'!$L:$L,'J1 Lijnen'!$A:$A,$B60,'J1 Lijnen'!$K:$K,0.06) | R60: =SUMIFS('J1 Lijnen'!$J:$J,'J1 Lijnen'!$A:$A,$B60,'J1 Lijnen'!$E:$E,"verpakking") | S60: =-SUMIFS('J1 Lijnen'!$J:$J,'J1 Lijnen'!$A:$A,$B60,'J1 Lijnen'!$E:$E,"financiële korting") | T60: =SUM(N60:S60) | X60: U2026-14 | Y60: =SUMIFS('J1 Journaal'!$K:$K,'J1 Journaal'!$E:$E,$B60)-SUMIFS('J1 Journaal'!$L:$L,'J1 Journaal'!$E:$E,$B60)
A61: 7 | B61: Q4V2 | C61: REMEDIERING | D61: K4 | E61: VK | F61: handelsgoederen | G61: 46318 | H61: =G61+30 | I61: 2026-016 | J61: Fietsatelier Noor bv | K61: Architectenbureau Dubois srl | N61: =SUMIFS('J1 Lijnen'!$J:$J,'J1 Lijnen'!$A:$A,$B61,'J1 Lijnen'!$K:$K,0.21,'J1 Lijnen'!$E:$E,"<>verpakking") | O61: =SUMIFS('J1 Lijnen'!$L:$L,'J1 Lijnen'!$A:$A,$B61,'J1 Lijnen'!$K:$K,0.21) | P61: =SUMIFS('J1 Lijnen'!$J:$J,'J1 Lijnen'!$A:$A,$B61,'J1 Lijnen'!$K:$K,0.06) | Q61: =SUMIFS('J1 Lijnen'!$L:$L,'J1 Lijnen'!$A:$A,$B61,'J1 Lijnen'!$K:$K,0.06) | R61: =SUMIFS('J1 Lijnen'!$J:$J,'J1 Lijnen'!$A:$A,$B61,'J1 Lijnen'!$E:$E,"verpakking") | S61: =-SUMIFS('J1 Lijnen'!$J:$J,'J1 Lijnen'!$A:$A,$B61,'J1 Lijnen'!$E:$E,"financiële korting") | T61: =SUM(N61:S61) | X61: U2026-15 | Y61: =SUMIFS('J1 Journaal'!$K:$K,'J1 Journaal'!$E:$E,$B61)-SUMIFS('J1 Journaal'!$L:$L,'J1 Journaal'!$E:$E,$B61)
A62: 8 | B62: Q4A3 | C62: REMEDIERING | D62: K4 | E62: AK | F62: diensten | G62: 46329 | H62: =G62+30 | I62: NL-26-11-2207 | J62: Netlink bv | K62: Fietsatelier Noor bv | N62: =SUMIFS('J1 Lijnen'!$J:$J,'J1 Lijnen'!$A:$A,$B62,'J1 Lijnen'!$K:$K,0.21,'J1 Lijnen'!$E:$E,"<>verpakking") | O62: =SUMIFS('J1 Lijnen'!$L:$L,'J1 Lijnen'!$A:$A,$B62,'J1 Lijnen'!$K:$K,0.21) | P62: =SUMIFS('J1 Lijnen'!$J:$J,'J1 Lijnen'!$A:$A,$B62,'J1 Lijnen'!$K:$K,0.06) | Q62: =SUMIFS('J1 Lijnen'!$L:$L,'J1 Lijnen'!$A:$A,$B62,'J1 Lijnen'!$K:$K,0.06) | R62: =SUMIFS('J1 Lijnen'!$J:$J,'J1 Lijnen'!$A:$A,$B62,'J1 Lijnen'!$E:$E,"verpakking") | S62: =-SUMIFS('J1 Lijnen'!$J:$J,'J1 Lijnen'!$A:$A,$B62,'J1 Lijnen'!$E:$E,"financiële korting") | T62: =SUM(N62:S62) | X62: U2026-15 | Y62: =SUMIFS('J1 Journaal'!$K:$K,'J1 Journaal'!$E:$E,$B62)-SUMIFS('J1 Journaal'!$L:$L,'J1 Journaal'!$E:$E,$B62)
A63: 10 | B63: Q4V3 | C63: REMEDIERING | D63: K4 | E63: VK | F63: herstellingen | G63: 46344 | H63: =G63+30 | I63: 2026-017 | J63: Fietsatelier Noor bv | K63: Snelpost bv | N63: =SUMIFS('J1 Lijnen'!$J:$J,'J1 Lijnen'!$A:$A,$B63,'J1 Lijnen'!$K:$K,0.21,'J1 Lijnen'!$E:$E,"<>verpakking") | O63: =SUMIFS('J1 Lijnen'!$L:$L,'J1 Lijnen'!$A:$A,$B63,'J1 Lijnen'!$K:$K,0.21) | P63: =SUMIFS('J1 Lijnen'!$J:$J,'J1 Lijnen'!$A:$A,$B63,'J1 Lijnen'!$K:$K,0.06) | Q63: =SUMIFS('J1 Lijnen'!$L:$L,'J1 Lijnen'!$A:$A,$B63,'J1 Lijnen'!$K:$K,0.06) | R63: =SUMIFS('J1 Lijnen'!$J:$J,'J1 Lijnen'!$A:$A,$B63,'J1 Lijnen'!$E:$E,"verpakking") | S63: =-SUMIFS('J1 Lijnen'!$J:$J,'J1 Lijnen'!$A:$A,$B63,'J1 Lijnen'!$E:$E,"financiële korting") | T63: =SUM(N63:S63) | X63: U2026-16 | Y63: =SUMIFS('J1 Journaal'!$K:$K,'J1 Journaal'!$E:$E,$B63)-SUMIFS('J1 Journaal'!$L:$L,'J1 Journaal'!$E:$E,$B63)
A64: 11 | B64: Q4CV2 | C64: REMEDIERING | D64: K4 | E64: CN-VK | F64: retour | G64: 46346 | I64: CN-2026-009 | J64: Fietsatelier Noor bv | K64: Architectenbureau Dubois srl | L64: 2026-016 | M64: 1 e-bike teruggenomen: verkeerde framemaat (factuur was al betaald) | N64: =SUMIFS('J1 Lijnen'!$J:$J,'J1 Lijnen'!$A:$A,$B64,'J1 Lijnen'!$K:$K,0.21,'J1 Lijnen'!$E:$E,"<>verpakking") | O64: =SUMIFS('J1 Lijnen'!$L:$L,'J1 Lijnen'!$A:$A,$B64,'J1 Lijnen'!$K:$K,0.21) | P64: =SUMIFS('J1 Lijnen'!$J:$J,'J1 Lijnen'!$A:$A,$B64,'J1 Lijnen'!$K:$K,0.06) | Q64: =SUMIFS('J1 Lijnen'!$L:$L,'J1 Lijnen'!$A:$A,$B64,'J1 Lijnen'!$K:$K,0.06) | R64: =SUMIFS('J1 Lijnen'!$J:$J,'J1 Lijnen'!$A:$A,$B64,'J1 Lijnen'!$E:$E,"verpakking") | S64: =-SUMIFS('J1 Lijnen'!$J:$J,'J1 Lijnen'!$A:$A,$B64,'J1 Lijnen'!$E:$E,"financiële korting") | T64: =SUM(N64:S64) | X64: U2026-16 | Y64: =SUMIFS('J1 Journaal'!$K:$K,'J1 Journaal'!$E:$E,$B64)-SUMIFS('J1 Journaal'!$L:$L,'J1 Journaal'!$E:$E,$B64)
A65: 13 | B65: Q4D1 | C65: REMEDIERING | D65: K4 | E65: DO | F65: dagontvangst | G65: 46368 | I65: DO-2026-06 | J65: Fietsatelier Noor bv | K65: particulieren (kasticket) | M65: Dagontvangsten winkel (verkopen aan particulieren) | N65: =SUMIFS('J1 Lijnen'!$J:$J,'J1 Lijnen'!$A:$A,$B65,'J1 Lijnen'!$K:$K,0.21,'J1 Lijnen'!$E:$E,"<>verpakking") | O65: =SUMIFS('J1 Lijnen'!$L:$L,'J1 Lijnen'!$A:$A,$B65,'J1 Lijnen'!$K:$K,0.21) | P65: =SUMIFS('J1 Lijnen'!$J:$J,'J1 Lijnen'!$A:$A,$B65,'J1 Lijnen'!$K:$K,0.06) | Q65: =SUMIFS('J1 Lijnen'!$L:$L,'J1 Lijnen'!$A:$A,$B65,'J1 Lijnen'!$K:$K,0.06) | R65: =SUMIFS('J1 Lijnen'!$J:$J,'J1 Lijnen'!$A:$A,$B65,'J1 Lijnen'!$E:$E,"verpakking") | S65: =-SUMIFS('J1 Lijnen'!$J:$J,'J1 Lijnen'!$A:$A,$B65,'J1 Lijnen'!$E:$E,"financiële korting") | T65: =SUM(N65:S65) | V65: =T65-W65 | W65: 3000 | X65: Q4D1K, U2026-17 | Y65: =SUMIFS('J1 Journaal'!$K:$K,'J1 Journaal'!$E:$E,$B65)-SUMIFS('J1 Journaal'!$L:$L,'J1 Journaal'!$E:$E,$B65)
A66: 14 | B66: Q4D1K | C66: REMEDIERING | D66: K4 | E66: KAS | F66: ontvangst | G66: 46368 | I66: Kasboek DO-2026-06 | J66: Fietsatelier Noor bv | K66: Fietsatelier Noor bv | L66: DO-2026-06 | M66: Contant deel van dagontvangst DO-2026-06 (laat de vordering op de klanten dalen) | T66: 661 | V66: 661 | Y66: =SUMIFS('J1 Journaal'!$K:$K,'J1 Journaal'!$E:$E,$B66)-SUMIFS('J1 Journaal'!$L:$L,'J1 Journaal'!$E:$E,$B66)
A67: 1 | B67: B1 | C67: BOEKHOUDER | D67: K4 | E67: AK | F67: handelsgoederen | G67: 46384 | H67: =G67+30 | I67: 2026-1288 | J67: Velomax bv | K67: Fietsatelier Noor bv | N67: =SUMIFS('J1 Lijnen'!$J:$J,'J1 Lijnen'!$A:$A,$B67,'J1 Lijnen'!$K:$K,0.21,'J1 Lijnen'!$E:$E,"<>verpakking") | O67: =SUMIFS('J1 Lijnen'!$L:$L,'J1 Lijnen'!$A:$A,$B67,'J1 Lijnen'!$K:$K,0.21) | P67: =SUMIFS('J1 Lijnen'!$J:$J,'J1 Lijnen'!$A:$A,$B67,'J1 Lijnen'!$K:$K,0.06) | Q67: =SUMIFS('J1 Lijnen'!$L:$L,'J1 Lijnen'!$A:$A,$B67,'J1 Lijnen'!$K:$K,0.06) | R67: =SUMIFS('J1 Lijnen'!$J:$J,'J1 Lijnen'!$A:$A,$B67,'J1 Lijnen'!$E:$E,"verpakking") | S67: =-SUMIFS('J1 Lijnen'!$J:$J,'J1 Lijnen'!$A:$A,$B67,'J1 Lijnen'!$E:$E,"financiële korting") | T67: =SUM(N67:S67) | X67: U2027-01 | Y67: =SUMIFS('J1 Journaal'!$K:$K,'J1 Journaal'!$E:$E,$B67)-SUMIFS('J1 Journaal'!$L:$L,'J1 Journaal'!$E:$E,$B67) | Z67: blijft open op 31/12, betaald in jaar 2
A68: 2 | B68: B2 | C68: BOEKHOUDER | D68: K4 | E68: VK | F68: handelsgoederen | G68: 46385 | H68: =G68+30 | I68: 2026-018 | J68: Fietsatelier Noor bv | K68: Velocity Deelfietsen bv | N68: =SUMIFS('J1 Lijnen'!$J:$J,'J1 Lijnen'!$A:$A,$B68,'J1 Lijnen'!$K:$K,0.21,'J1 Lijnen'!$E:$E,"<>verpakking") | O68: =SUMIFS('J1 Lijnen'!$L:$L,'J1 Lijnen'!$A:$A,$B68,'J1 Lijnen'!$K:$K,0.21) | P68: =SUMIFS('J1 Lijnen'!$J:$J,'J1 Lijnen'!$A:$A,$B68,'J1 Lijnen'!$K:$K,0.06) | Q68: =SUMIFS('J1 Lijnen'!$L:$L,'J1 Lijnen'!$A:$A,$B68,'J1 Lijnen'!$K:$K,0.06) | R68: =SUMIFS('J1 Lijnen'!$J:$J,'J1 Lijnen'!$A:$A,$B68,'J1 Lijnen'!$E:$E,"verpakking") | S68: =-SUMIFS('J1 Lijnen'!$J:$J,'J1 Lijnen'!$A:$A,$B68,'J1 Lijnen'!$E:$E,"financiële korting") | T68: =SUM(N68:S68) | X68: U2027-01 | Y68: =SUMIFS('J1 Journaal'!$K:$K,'J1 Journaal'!$E:$E,$B68)-SUMIFS('J1 Journaal'!$L:$L,'J1 Journaal'!$E:$E,$B68) | Z68: blijft open op 31/12, ontvangen in jaar 2
A69: 3 | B69: AF1-1 | C69: BOEKHOUDER | D69: K4 | E69: MEMO | F69: btw-verrekening | G69: 46387 | I69: AF1-1 | M69: Btw-verrekening 2026 | Y69: =SUMIFS('J1 Journaal'!$K:$K,'J1 Journaal'!$E:$E,$B69)-SUMIFS('J1 Journaal'!$L:$L,'J1 Journaal'!$E:$E,$B69)
A70: 4 | B70: AF1-2 | C70: BOEKHOUDER | D70: K4 | E70: MEMO | F70: voorraadwijziging | G70: 46387 | I70: AF1-2 | M70: Voorraadwijziging 2026 (inventaris 31/12) | Y70: =SUMIFS('J1 Journaal'!$K:$K,'J1 Journaal'!$E:$E,$B70)-SUMIFS('J1 Journaal'!$L:$L,'J1 Journaal'!$E:$E,$B70)
A71: 5 | B71: AF1-3 | C71: BOEKHOUDER | D71: K4 | E71: MEMO | F71: afschrijvingen | G71: 46387 | I71: AF1-3 | M71: Afschrijvingen 2026 | Y71: =SUMIFS('J1 Journaal'!$K:$K,'J1 Journaal'!$E:$E,$B71)-SUMIFS('J1 Journaal'!$L:$L,'J1 Journaal'!$E:$E,$B71)
A72: 6 | B72: AF1-4 | C72: BOEKHOUDER | D72: K4 | E72: MEMO | F72: resultaat | G72: 46387 | I72: AF1-4 | M72: Resultaat 2026 naar overgedragen winst | Y72: =SUMIFS('J1 Journaal'!$K:$K,'J1 Journaal'!$E:$E,$B72)-SUMIFS('J1 Journaal'!$L:$L,'J1 Journaal'!$E:$E,$B72)

Sheet J1 Uittreksels
A1: Volgorde in set | B1: Uittreksel | C1: Set | D1: Kwartaal | E1: Datum | F1: Lijn | G1: Omschrijving op het uittreksel | H1: Verwijst naar (ID) | I1: Bedrag | J1: Saldo na lijn
G2: Saldo bank bij de start van het jaar | J2: 10500
A3: 6 | B3: 1 | C3: CURSUS | D3: K1 | E3: 46042 | F3: 1 | G3: Overschrijving naar Velomax bv, factuur 2026-118 | H3: C01 | I3: -4840 | J3: =J2+I3
A4: 6 | B4: 1 | C4: CURSUS | D4: K1 | E4: 46042 | F4: 2 | G4: Overschrijving naar Stroomkracht nv, factuur SK-26-0457 | H4: C02 | I4: -242 | J4: =J3+I4
A5: 6 | B5: 1 | C5: CURSUS | D5: K1 | E5: 46042 | F5: 3 | G5: Overschrijving naar Deprez Werkplaatsinrichting bv, factuur DW-2026-012 | H5: C03 | I5: -1815 | J5: =J4+I5
A6: 11 | B6: 2 | C6: CURSUS | D6: K1 | E6: 46050 | F6: 1 | G6: Overschrijving van Snelpost bv, factuur 2026-001 | H6: C04 | I6: 7260 | J6: =J5+I6
A7: 12 | B7: 3 | C7: CURSUS | D7: K1 | E7: 46052 | F7: 1 | G7: Overschrijving van Hotel De Linde bv, factuur 2026-002 - creditnota CN-2026-001 | H7: C05, C06 | I7: 2178 | J7: =J6+I7
A8: 12 | B8: 3 | C8: CURSUS | D8: K1 | E8: 46052 | F8: 2 | G8: Terugbetaling door Velomax bv, creditnota CN-2026-007 | H8: C07 | I8: 484 | J8: =J7+I8
A9: 12 | B9: 3 | C9: CURSUS | D9: K1 | E9: 46052 | F9: 3 | G9: Bancontact-ontvangsten 24/01/2026 | H9: C08 | I9: 1000 | J9: =J8+I9
A10: 23 | B10: 4 | C10: VERPLICHT | D10: K1 | E10: 46063 | F10: 1 | G10: Bancontact-ontvangsten 07/02/2026 | H10: D1 | I10: 1500 | J10: =J9+I10
A11: 24 | B11: 5 | C11: VERPLICHT | D11: K1 | E11: 46073 | F11: 1 | G11: Bancontact-ontvangsten 14/02/2026 | H11: D2 | I11: 2500 | J11: =J10+I11
A12: 24 | B12: 5 | C12: VERPLICHT | D12: K1 | E12: 46073 | F12: 2 | G12: Overschrijving van Bouwbedrijf Janssens & Zonen bv, factuur 2026-004 | H12: V2 | I12: 6292 | J12: =J11+I12
A13: 24 | B13: 5 | C13: VERPLICHT | D13: K1 | E13: 46073 | F13: 3 | G13: Overschrijving naar Spaakwerk bv, factuur SW-1032 | H13: A2 | I13: -484 | J13: =J12+I13
A14: 24 | B14: 5 | C14: VERPLICHT | D14: K1 | E14: 46073 | F14: 4 | G14: Overschrijving naar HelmHuis bv, factuur HH-26-077 - creditnota HH-CN-26-004 | H14: A3, CA2 | I14: -968 | J14: =J13+I14
... A50: 15 | B50: 17 | C50: REMEDIERING | D50: K4 | E50: 46372 | F50: 1 | G50: Bancontact-ontvangsten 12/12/2026 | H50: Q4D1 | I50: 3000 | J50: =J49+I50

Sheet J1 Journaal
A1: Volgnr | B1: Datum | C1: Set | D1: Kwartaal | E1: Document | F1: Documentnr / uittreksel | G1: Rekening | H1: Rekeningnaam | I1: A/P/K/O | J1: +/- | K1: Debet | L1: Credit | M1: Redenering | N1: Afsluiting
A2: 1 | B2: 46027 | C2: CURSUS | D2: K1 | E2: C01 | F2: 2026-118 | G2: 604000 | H2: =INDEX('MAR 2e graad'!$B$2:$B$58,MATCH(G2,'MAR 2e graad'!$A$2:$A$58,0)) | I2: =INDEX('MAR 2e graad'!$C$2:$C$58,MATCH(G2,'MAR 2e graad'!$A$2:$A$58,0)) | J2: =IF(OR(I2="A",I2="K"),IF(K2>0,"+","-"),IF(L2>0,"+","-")) | K2: 4000 | M2: de kosten voor handelsgoederen stijgen | N2: nee
A3: 2 | B3: 46027 | C3: CURSUS | D3: K1 | E3: C01 | F3: 2026-118 | G3: 411100 | H3: =INDEX('MAR 2e graad'!$B$2:$B$58,MATCH(G3,'MAR 2e graad'!$A$2:$A$58,0)) | I3: =INDEX('MAR 2e graad'!$C$2:$C$58,MATCH(G3,'MAR 2e graad'!$A$2:$A$58,0)) | J3: =IF(OR(I3="A",I3="K"),IF(K3>0,"+","-"),IF(L3>0,"+","-")) | K3: 840 | M3: de vordering op de overheid (aftrekbare btw) stijgt | N3: nee
A4: 3 | B4: 46027 | C4: CURSUS | D4: K1 | E4: C01 | F4: 2026-118 | G4: 440000 | H4: =INDEX('MAR 2e graad'!$B$2:$B$58,MATCH(G4,'MAR 2e graad'!$A$2:$A$58,0)) | I4: =INDEX('MAR 2e graad'!$C$2:$C$58,MATCH(G4,'MAR 2e graad'!$A$2:$A$58,0)) | J4: =IF(OR(I4="A",I4="K"),IF(K4>0,"+","-"),IF(L4>0,"+","-")) | L4: 4840 | M4: de schuld aan de leverancier stijgt | N4: nee
A5: 4 | B5: 46029 | C5: CURSUS | D5: K1 | E5: C02 | F5: SK-26-0457 | G5: 612700 | H5: =INDEX('MAR 2e graad'!$B$2:$B$58,MATCH(G5,'MAR 2e graad'!$A$2:$A$58,0)) | I5: =INDEX('MAR 2e graad'!$C$2:$C$58,MATCH(G5,'MAR 2e graad'!$A$2:$A$58,0)) | J5: =IF(OR(I5="A",I5="K"),IF(K5>0,"+","-"),IF(L5>0,"+","-")) | K5: 200 | M5: de kosten voor diensten en diverse goederen stijgen | N5: nee
A6: 5 | B6: 46029 | C6: CURSUS | D6: K1 | E6: C02 | F6: SK-26-0457 | G6: 411100 | H6: =INDEX('MAR 2e graad'!$B$2:$B$58,MATCH(G6,'MAR 2e graad'!$A$2:$A$58,0)) | I6: =INDEX('MAR 2e graad'!$C$2:$C$58,MATCH(G6,'MAR 2e graad'!$A$2:$A$58,0)) | J6: =IF(OR(I6="A",I6="K"),IF(K6>0,"+","-"),IF(L6>0,"+","-")) | K6: 42 | M6: de vordering op de overheid (aftrekbare btw) stijgt | N6: nee
A7: 6 | B7: 46029 | C7: CURSUS | D7: K1 | E7: C02 | F7: SK-26-0457 | G7: 440000 | H7: =INDEX('MAR 2e graad'!$B$2:$B$58,MATCH(G7,'MAR 2e graad'!$A$2:$A$58,0)) | I7: =INDEX('MAR 2e graad'!$C$2:$C$58,MATCH(G7,'MAR 2e graad'!$A$2:$A$58,0)) | J7: =IF(OR(I7="A",I7="K"),IF(K7>0,"+","-"),IF(L7>0,"+","-")) | L7: 242 | M7: de schuld aan de leverancier stijgt | N7: nee
A8: 7 | B8: 46031 | C8: CURSUS | D8: K1 | E8: C03 | F8: DW-2026-012 | G8: 230000 | H8: =INDEX('MAR 2e graad'!$B$2:$B$58,MATCH(G8,'MAR 2e graad'!$A$2:$A$58,0)) | I8: =INDEX('MAR 2e graad'!$C$2:$C$58,MATCH(G8,'MAR 2e graad'!$A$2:$A$58,0)) | J8: =IF(OR(I8="A",I8="K"),IF(K8>0,"+","-"),IF(L8>0,"+","-")) | K8: 1500 | M8: het vast actief stijgt | N8: nee
A9: 8 | B9: 46031 | C9: CURSUS | D9: K1 | E9: C03 | F9: DW-2026-012 | G9: 411100 | H9: =INDEX('MAR 2e graad'!$B$2:$B$58,MATCH(G9,'MAR 2e graad'!$A$2:$A$58,0)) | I9: =INDEX('MAR 2e graad'!$C$2:$C$58,MATCH(G9,'MAR 2e graad'!$A$2:$A$58,0)) | J9: =IF(OR(I9="A",I9="K"),IF(K9>0,"+","-"),IF(L9>0,"+","-")) | K9: 315 | M9: de vordering op de overheid (aftrekbare btw) stijgt | N9: nee
A10: 9 | B10: 46031 | C10: CURSUS | D10: K1 | E10: C03 | F10: DW-2026-012 | G10: 440000 | H10: =INDEX('MAR 2e graad'!$B$2:$B$58,MATCH(G10,'MAR 2e graad'!$A$2:$A$58,0)) | I10: =INDEX('MAR 2e graad'!$C$2:$C$58,MATCH(G10,'MAR 2e graad'!$A$2:$A$58,0)) | J10: =IF(OR(I10="A",I10="K"),IF(K10>0,"+","-"),IF(L10>0,"+","-")) | L10: 1815 | M10: de schuld aan de leverancier stijgt | N10: nee
A11: 10 | B11: 46036 | C11: CURSUS | D11: K1 | E11: C04 | F11: 2026-001 | G11: 400000 | H11: =INDEX('MAR 2e graad'!$B$2:$B$58,MATCH(G11,'MAR 2e graad'!$A$2:$A$58,0)) | I11: =INDEX('MAR 2e graad'!$C$2:$C$58,MATCH(G11,'MAR 2e graad'!$A$2:$A$58,0)) | J11: =IF(OR(I11="A",I11="K"),IF(K11>0,"+","-"),IF(L11>0,"+","-")) | K11: 7260 | M11: de vordering op de klant stijgt | N11: nee
A12: 11 | B12: 46036 | C12: CURSUS | D12: K1 | E12: C04 | F12: 2026-001 | G12: 704000 | H12: =INDEX('MAR 2e graad'!$B$2:$B$58,MATCH(G12,'MAR 2e graad'!$A$2:$A$58,0)) | I12: =INDEX('MAR 2e graad'!$C$2:$C$58,MATCH(G12,'MAR 2e graad'!$A$2:$A$58,0)) | J12: =IF(OR(I12="A",I12="K"),IF(K12>0,"+","-"),IF(L12>0,"+","-")) | L12: 6000 | M12: de omzet stijgt | N12: nee
A13: 12 | B13: 46036 | C13: CURSUS | D13: K1 | E13: C04 | F13: 2026-001 | G13: 451100 | H13: =INDEX('MAR 2e graad'!$B$2:$B$58,MATCH(G13,'MAR 2e graad'!$A$2:$A$58,0)) | I13: =INDEX('MAR 2e graad'!$C$2:$C$58,MATCH(G13,'MAR 2e graad'!$A$2:$A$58,0)) | J13: =IF(OR(I13="A",I13="K"),IF(K13>0,"+","-"),IF(L13>0,"+","-")) | L13: 1260 | M13: de schuld aan de overheid (verschuldigde btw) stijgt | N13: nee
A14: 13 | B14: 46041 | C14: CURSUS | D14: K1 | E14: C05 | F14: 2026-002 | G14: 400000 | H14: =INDEX('MAR 2e graad'!$B$2:$B$58,MATCH(G14,'MAR 2e graad'!$A$2:$A$58,0)) | I14: =INDEX('MAR 2e graad'!$C$2:$C$58,MATCH(G14,'MAR 2e graad'!$A$2:$A$58,0)) | J14: =IF(OR(I14="A",I14="K"),IF(K14>0,"+","-"),IF(L14>0,"+","-")) | K14: 2904 | M14: de vordering op de klant stijgt | N14: nee
A15: 14 | B15: 46041 | C15: CURSUS | D15: K1 | E15: C05 | F15: 2026-002 | G15: 704000 | H15: =INDEX('MAR 2e graad'!$B$2:$B$58,MATCH(G15,'MAR 2e graad'!$A$2:$A$58,0)) | I15: =INDEX('MAR 2e graad'!$C$2:$C$58,MATCH(G15,'MAR 2e graad'!$A$2:$A$58,0)) | J15: =IF(OR(I15="A",I15="K"),IF(K15>0,"+","-"),IF(L15>0,"+","-")) | L15: 2400 | M15: de omzet stijgt | N15: nee
A16: 15 | B16: 46041 | C16: CURSUS | D16: K1 | E16: C05 | F16: 2026-002 | G16: 451100 | H16: =INDEX('MAR 2e graad'!$B$2:$B$58,MATCH(G16,'MAR 2e graad'!$A$2:$A$58,0)) | I16: =INDEX('MAR 2e graad'!$C$2:$C$58,MATCH(G16,'MAR 2e graad'!$A$2:$A$58,0)) | J16: =IF(OR(I16="A",I16="K"),IF(K16>0,"+","-"),IF(L16>0,"+","-")) | L16: 504 | M16: de schuld aan de overheid (verschuldigde btw) stijgt | N16: nee
A17: 16 | B17: 46042 | C17: CURSUS | D17: K1 | E17: U2026-01/1 | F17: uittreksel U2026-01/1 | G17: 440000 | H17: =INDEX('MAR 2e graad'!$B$2:$B$58,MATCH(G17,'MAR 2e graad'!$A$2:$A$58,0)) | I17: =INDEX('MAR 2e graad'!$C$2:$C$58,MATCH(G17,'MAR 2e graad'!$A$2:$A$58,0)) | J17: =IF(OR(I17="A",I17="K"),IF(K17>0,"+","-"),IF(L17>0,"+","-")) | K17: 4840 | M17: de schuld aan de leverancier daalt | N17: nee
A18: 17 | B18: 46042 | C18: CURSUS | D18: K1 | E18: U2026-01/1 | F18: uittreksel U2026-01/1 | G18: 550000 | H18: =INDEX('MAR 2e graad'!$B$2:$B$58,MATCH(G18,'MAR 2e graad'!$A$2:$A$58,0)) | I18: =INDEX('MAR 2e graad'!$C$2:$C$58,MATCH(G18,'MAR 2e graad'!$A$2:$A$58,0)) | J18: =IF(OR(I18="A",I18="K"),IF(K18>0,"+","-"),IF(L18>0,"+","-")) | L18: 4840 | M18: de bank daalt | N18: nee
A19: 18 | B19: 46042 | C19: CURSUS | D19: K1 | E19: U2026-01/2 | F19: uittreksel U2026-01/2 | G19: 440000 | H19: =INDEX('MAR 2e graad'!$B$2:$B$58,MATCH(G19,'MAR 2e graad'!$A$2:$A$58,0)) | I19: =INDEX('MAR 2e graad'!$C$2:$C$58,MATCH(G19,'MAR 2e graad'!$A$2:$A$58,0)) | J19: =IF(OR(I19="A",I19="K"),IF(K19>0,"+","-"),IF(L19>0,"+","-")) | K19: 242 | M19: de schuld aan de leverancier daalt | N19: nee
A20: 19 | B20: 46042 | C20: CURSUS | D20: K1 | E20: U2026-01/2 | F20: uittreksel U2026-01/2 | G20: 550000 | H20: =INDEX('MAR 2e graad'!$B$2:$B$58,MATCH(G20,'MAR 2e graad'!$A$2:$A$58,0)) | I20: =INDEX('MAR 2e graad'!$C$2:$C$58,MATCH(G20,'MAR 2e graad'!$A$2:$A$58,0)) | J20: =IF(OR(I20="A",I20="K"),IF(K20>0,"+","-"),IF(L20>0,"+","-")) | L20: 242 | M20: de bank daalt | N20: nee
A21: 20 | B21: 46042 | C21: CURSUS | D21: K1 | E21: U2026-01/3 | F21: uittreksel U2026-01/3 | G21: 440000 | H21: =INDEX('MAR 2e graad'!$B$2:$B$58,MATCH(G21,'MAR 2e graad'!$A$2:$A$58,0)) | I21: =INDEX('MAR 2e graad'!$C$2:$C$58,MATCH(G21,'MAR 2e graad'!$A$2:$A$58,0)) | J21: =IF(OR(I21="A",I21="K"),IF(K21>0,"+","-"),IF(L21>0,"+","-")) | K21: 1815 | M21: de schuld aan de leverancier daalt | N21: nee
A22: 21 | B22: 46042 | C22: CURSUS | D22: K1 | E22: U2026-01/3 | F22: uittreksel U2026-01/3 | G22: 550000 | H22: =INDEX('MAR 2e graad'!$B$2:$B$58,MATCH(G22,'MAR 2e graad'!$A$2:$A$58,0)) | I22: =INDEX('MAR 2e graad'!$C$2:$C$58,MATCH(G22,'MAR 2e graad'!$A$2:$A$58,0)) | J22: =IF(OR(I22="A",I22="K"),IF(K22>0,"+","-"),IF(L22>0,"+","-")) | L22: 1815 | M22: de bank daalt | N22: nee
A23: 22 | B23: 46043 | C23: CURSUS | D23: K1 | E23: C06 | F23: CN-2026-001 | G23: 400000 | H23: =INDEX('MAR 2e graad'!$B$2:$B$58,MATCH(G23,'MAR 2e graad'!$A$2:$A$58,0)) | I23: =INDEX('MAR 2e graad'!$C$2:$C$58,MATCH(G23,'MAR 2e graad'!$A$2:$A$58,0)) | J23: =IF(OR(I23="A",I23="K"),IF(K23>0,"+","-"),IF(L23>0,"+","-")) | L23: 726 | M23: de vordering op de klant daalt | N23: nee
A24: 23 | B24: 46043 | C24: CURSUS | D24: K1 | E24: C06 | F24: CN-2026-001 | G24: 704010 | H24: =INDEX('MAR 2e graad'!$B$2:$B$58,MATCH(G24,'MAR 2e graad'!$A$2:$A$58,0)) | I24: =INDEX('MAR 2e graad'!$C$2:$C$58,MATCH(G24,'MAR 2e graad'!$A$2:$A$58,0)) | J24: =IF(OR(I24="A",I24="K"),IF(K24>0,"+","-"),IF(L24>0,"+","-")) | K24: 600 | M24: de omzet daalt (retour) | N24: nee
A25: 24 | B25: 46043 | C25: CURSUS | D25: K1 | E25: C06 | F25: CN-2026-001 | G25: 411200 | H25: =INDEX('MAR 2e graad'!$B$2:$B$58,MATCH(G25,'MAR 2e graad'!$A$2:$A$58,0)) | I25: =INDEX('MAR 2e graad'!$C$2:$C$58,MATCH(G25,'MAR 2e graad'!$A$2:$A$58,0)) | J25: =IF(OR(I25="A",I25="K"),IF(K25>0,"+","-"),IF(L25>0,"+","-")) | K25: 126 | M25: de vordering op de overheid stijgt (btw op uitgaande creditnota) | N25: nee
A26: 25 | B26: 46044 | C26: CURSUS | D26: K1 | E26: C07 | F26: CN-2026-007 | G26: 604010 | H26: =INDEX('MAR 2e graad'!$B$2:$B$58,MATCH(G26,'MAR 2e graad'!$A$2:$A$58,0)) | I26: =INDEX('MAR 2e graad'!$C$2:$C$58,MATCH(G26,'MAR 2e graad'!$A$2:$A$58,0)) | J26: =IF(OR(I26="A",I26="K"),IF(K26>0,"+","-"),IF(L26>0,"+","-")) | L26: 400 | M26: de kosten voor handelsgoederen dalen (retour) | N26: nee
A27: 26 | B27: 46044 | C27: CURSUS | D27: K1 | E27: C07 | F27: CN-2026-007 | G27: 451200 | H27: =INDEX('MAR 2e graad'!$B$2:$B$58,MATCH(G27,'MAR 2e graad'!$A$2:$A$58,0)) | I27: =INDEX('MAR 2e graad'!$C$2:$C$58,MATCH(G27,'MAR 2e graad'!$A$2:$A$58,0)) | J27: =IF(OR(I27="A",I27="K"),IF(K27>0,"+","-"),IF(L27>0,"+","-")) | L27: 84 | M27: de schuld aan de overheid stijgt (btw op inkomende creditnota) | N27: nee
A28: 27 | B28: 46044 | C28: CURSUS | D28: K1 | E28: C07 | F28: CN-2026-007 | G28: 440000 | H28: =INDEX('MAR 2e graad'!$B$2:$B$58,MATCH(G28,'MAR 2e graad'!$A$2:$A$58,0)) | I28: =INDEX('MAR 2e graad'!$C$2:$C$58,MATCH(G28,'MAR 2e graad'!$A$2:$A$58,0)) | J28: =IF(OR(I28="A",I28="K"),IF(K28>0,"+","-"),IF(L28>0,"+","-")) | K28: 484 | M28: de schuld aan de leverancier daalt | N28: nee
A29: 28 | B29: 46046 | C29: CURSUS | D29: K1 | E29: C08 | F29: DO-2026-01 | G29: 400000 | H29: =INDEX('MAR 2e graad'!$B$2:$B$58,MATCH(G29,'MAR 2e graad'!$A$2:$A$58,0)) | I29: =INDEX('MAR 2e graad'!$C$2:$C$58,MATCH(G29,'MAR 2e graad'!$A$2:$A$58,0)) | J29: =IF(OR(I29="A",I29="K"),IF(K29>0,"+","-"),IF(L29>0,"+","-")) | K29: 1422 | M29: de vordering op de klanten (dagontvangsten) stijgt | N29: nee
A30: 29 | B30: 46046 | C30: CURSUS | D30: K1 | E30: C08 | F30: DO-2026-01 | G30: 704000 | H30: =INDEX('MAR 2e graad'!$B$2:$B$58,MATCH(G30,'MAR 2e graad'!$A$2:$A$58,0)) | I30: =INDEX('MAR 2e graad'!$C$2:$C$58,MATCH(G30,'MAR 2e graad'!$A$2:$A$58,0)) | J30: =IF(OR(I30="A",I30="K"),IF(K30>0,"+","-"),IF(L30>0,"+","-")) | L30: 600 | M30: de omzet stijgt | N30: nee
A31: 30 | B31: 46046 | C31: CURSUS | D31: K1 | E31: C08 | F31: DO-2026-01 | G31: 704000 | H31: =INDEX('MAR 2e graad'!$B$2:$B$58,MATCH(G31,'MAR 2e graad'!$A$2:$A$58,0)) | I31: =INDEX('MAR 2e graad'!$C$2:$C$58,MATCH(G31,'MAR 2e graad'!$A$2:$A$58,0)) | J31: =IF(OR(I31="A",I31="K"),IF(K31>0,"+","-"),IF(L31>0,"+","-")) | L31: 300 | M31: de omzet stijgt | N31: nee
A32: 31 | B32: 46046 | C32: CURSUS | D32: K1 | E32: C08 | F32: DO-2026-01 | G32: 704000 | H32: =INDEX('MAR 2e graad'!$B$2:$B$58,MATCH(G32,'MAR 2e graad'!$A$2:$A$58,0)) | I32: =INDEX('MAR 2e graad'!$C$2:$C$58,MATCH(G32,'MAR 2e graad'!$A$2:$A$58,0)) | J32: =IF(OR(I32="A",I32="K"),IF(K32>0,"+","-"),IF(L32>0,"+","-")) | L32: 100 | M32: de omzet stijgt | N32: nee
A33: 32 | B33: 46046 | C33: CURSUS | D33: K1 | E33: C08 | F33: DO-2026-01 | G33: 700000 | H33: =INDEX('MAR 2e graad'!$B$2:$B$58,MATCH(G33,'MAR 2e graad'!$A$2:$A$58,0)) | I33: =INDEX('MAR 2e graad'!$C$2:$C$58,MATCH(G33,'MAR 2e graad'!$A$2:$A$58,0)) | J33: =IF(OR(I33="A",I33="K"),IF(K33>0,"+","-"),IF(L33>0,"+","-")) | L33: 200 | M33: de omzet (diensten) stijgt | N33: nee
A34: 33 | B34: 46046 | C34: CURSUS | D34: K1 | E34: C08 | F34: DO-2026-01 | G34: 451100 | H34: =INDEX('MAR 2e graad'!$B$2:$B$58,MATCH(G34,'MAR 2e graad'!$A$2:$A$58,0)) | I34: =INDEX('MAR 2e graad'!$C$2:$C$58,MATCH(G34,'MAR 2e graad'!$A$2:$A$58,0)) | J34: =IF(OR(I34="A",I34="K"),IF(K34>0,"+","-"),IF(L34>0,"+","-")) | L34: 222 | M34: de schuld aan de overheid (verschuldigde btw) stijgt | N34: nee
A35: 34 | B35: 46046 | C35: CURSUS | D35: K1 | E35: C08K | F35: Kasboek DO-2026-01 | G35: 570000 | H35: =INDEX('MAR 2e graad'!$B$2:$B$58,MATCH(G35,'MAR 2e graad'!$A$2:$A$58,0)) | I35: =INDEX('MAR 2e graad'!$C$2:$C$58,MATCH(G35,'MAR 2e graad'!$A$2:$A$58,0)) | J35: =IF(OR(I35="A",I35="K"),IF(K35>0,"+","-"),IF(L35>0,"+","-")) | K35: 422 | M35: de kas stijgt | N35: nee
A36: 35 | B36: 46046 | C36: CURSUS | D36: K1 | E36: C08K | F36: Kasboek DO-2026-01 | G36: 400000 | H36: =INDEX('MAR 2e graad'!$B$2:$B$58,MATCH(G36,'MAR 2e graad'!$A$2:$A$58,0)) | I36: =INDEX('MAR 2e graad'!$C$2:$C$58,MATCH(G36,'MAR 2e graad'!$A$2:$A$58,0)) | J36: =IF(OR(I36="A",I36="K"),IF(K36>0,"+","-"),IF(L36>0,"+","-")) | L36: 422 | M36: de vordering op de klanten (contant betaald) daalt | N36: nee
A37: 36 | B37: 46050 | C37: CURSUS | D37: K1 | E37: U2026-02/1 | F37: uittreksel U2026-02/1 | G37: 550000 | H37: =INDEX('MAR 2e graad'!$B$2:$B$58,MATCH(G37,'MAR 2e graad'!$A$2:$A$58,0)) | I37: =INDEX('MAR 2e graad'!$C$2:$C$58,MATCH(G37,'MAR 2e graad'!$A$2:$A$58,0)) | J37: =IF(OR(I37="A",I37="K"),IF(K37>0,"+","-"),IF(L37>0,"+","-")) | K37: 7260 | M37: de bank stijgt | N37: nee
A38: 37 | B38: 46050 | C38: CURSUS | D38: K1 | E38: U2026-02/1 | F38: uittreksel U2026-02/1 | G38: 400000 | H38: =INDEX('MAR 2e graad'!$B$2:$B$58,MATCH(G38,'MAR 2e graad'!$A$2:$A$58,0)) | I38: =INDEX('MAR 2e graad'!$C$2:$C$58,MATCH(G38,'MAR 2e graad'!$A$2:$A$58,0)) | J38: =IF(OR(I38="A",I38="K"),IF(K38>0,"+","-"),IF(L38>0,"+","-")) | L38: 7260 | M38: de vordering op de klant daalt | N38: nee
A39: 38 | B39: 46052 | C39: CURSUS | D39: K1 | E39: U2026-03/1 | F39: uittreksel U2026-03/1 | G39: 550000 | H39: =INDEX('MAR 2e graad'!$B$2:$B$58,MATCH(G39,'MAR 2e graad'!$A$2:$A$58,0)) | I39: =INDEX('MAR 2e graad'!$C$2:$C$58,MATCH(G39,'MAR 2e graad'!$A$2:$A$58,0)) | J39: =IF(OR(I39="A",I39="K"),IF(K39>0,"+","-"),IF(L39>0,"+","-")) | K39: 2178 | M39: de bank stijgt | N39: nee
A40: 39 | B40: 46052 | C40: CURSUS | D40: K1 | E40: U2026-03/1 | F40: uittreksel U2026-03/1 | G40: 400000 | H40: =INDEX('MAR 2e graad'!$B$2:$B$58,MATCH(G40,'MAR 2e graad'!$A$2:$A$58,0)) | I40: =INDEX('MAR 2e graad'!$C$2:$C$58,MATCH(G40,'MAR 2e graad'!$A$2:$A$58,0)) | J40: =IF(OR(I40="A",I40="K"),IF(K40>0,"+","-"),IF(L40>0,"+","-")) | L40: 2178 | M40: de vordering op de klant daalt | N40: nee
A41: 40 | B41: 46052 | C41: CURSUS | D41: K1 | E41: U2026-03/2 | F41: uittreksel U2026-03/2 | G41: 550000 | H41: =INDEX('MAR 2e graad'!$B$2:$B$58,MATCH(G41,'MAR 2e graad'!$A$2:$A$58,0)) | I41: =INDEX('MAR 2e graad'!$C$2:$C$58,MATCH(G41,'MAR 2e graad'!$A$2:$A$58,0)) | J41: =IF(OR(I41="A",I41="K"),IF(K41>0,"+","-"),IF(L41>0,"+","-")) | K41: 484 | M41: de bank stijgt | N41: nee
A42: 41 | B42: 46052 | C42: CURSUS | D42: K1 | E42: U2026-03/2 | F42: uittreksel U2026-03/2 | G42: 440000 | H42: =INDEX('MAR 2e graad'!$B$2:$B$58,MATCH(G42,'MAR 2e graad'!$A$2:$A$58,0)) | I42: =INDEX('MAR 2e graad'!$C$2:$C$58,MATCH(G42,'MAR 2e graad'!$A$2:$A$58,0)) | J42: =IF(OR(I42="A",I42="K"),IF(K42>0,"+","-"),IF(L42>0,"+","-")) | L42: 484 | M42: de vordering op de leverancier (creditnota) daalt | N42: nee
A43: 42 | B43: 46052 | C43: CURSUS | D43: K1 | E43: U2026-03/3 | F43: uittreksel U2026-03/3 | G43: 550000 | H43: =INDEX('MAR 2e graad'!$B$2:$B$58,MATCH(G43,'MAR 2e graad'!$A$2:$A$58,0)) | I43: =INDEX('MAR 2e graad'!$C$2:$C$58,MATCH(G43,'MAR 2e graad'!$A$2:$A$58,0)) | J43: =IF(OR(I43="A",I43="K"),IF(K43>0,"+","-"),IF(L43>0,"+","-")) | K43: 1000 | M43: de bank stijgt | N43: nee
A44: 43 | B44: 46052 | C44: CURSUS | D44: K1 | E44: U2026-03/3 | F44: uittreksel U2026-03/3 | G44: 400000 | H44: =INDEX('MAR 2e graad'!$B$2:$B$58,MATCH(G44,'MAR 2e graad'!$A$2:$A$58,0)) | I44: =INDEX('MAR 2e graad'!$C$2:$C$58,MATCH(G44,'MAR 2e graad'!$A$2:$A$58,0)) | J44: =IF(OR(I44="A",I44="K"),IF(K44>0,"+","-"),IF(L44>0,"+","-")) | L44: 1000 | M44: de vordering (bancontact) daalt | N44: nee
A45: 44 | B45: 46055 | C45: VERPLICHT | D45: K1 | E45: A1 | F45: 2026-205 | G45: 604000 | H45: =INDEX('MAR 2e graad'!$B$2:$B$58,MATCH(G45,'MAR 2e graad'!$A$2:$A$58,0)) | I45: =INDEX('MAR 2e graad'!$C$2:$C$58,MATCH(G45,'MAR 2e graad'!$A$2:$A$58,0)) | J45: =IF(OR(I45="A",I45="K"),IF(K45>0,"+","-"),IF(L45>0,"+","-")) | K45: 4800 | M45: de kosten voor handelsgoederen stijgen | N45: nee
A46: 45 | B46: 46055 | C46: VERPLICHT | D46: K1 | E46: A1 | F46: 2026-205 | G46: 604000 | H46: =INDEX('MAR 2e graad'!$B$2:$B$58,MATCH(G46,'MAR 2e graad'!$A$2:$A$58,0)) | I46: =INDEX('MAR 2e graad'!$C$2:$C$58,MATCH(G46,'MAR 2e graad'!$A$2:$A$58,0)) | J46: =IF(OR(I46="A",I46="K"),IF(K46>0,"+","-"),IF(L46>0,"+","-")) | K46: 7000 | M46: de kosten voor handelsgoederen stijgen | N46: nee
A47: 46 | B47: 46055 | C47: VERPLICHT | D47: K1 | E47: A1 | F47: 2026-205 | G47: 604000 | H47: =INDEX('MAR 2e graad'!$B$2:$B$58,MATCH(G47,'MAR 2e graad'!$A$2:$A$58,0)) | I47: =INDEX('MAR 2e graad'!$C$2:$C$58,MATCH(G47,'MAR 2e graad'!$A$2:$A$58,0)) | J47: =IF(OR(I47="A",I47="K"),IF(K47>0,"+","-"),IF(L47>0,"+","-")) | K47: 3600 | M47: de kosten voor handelsgoederen stijgen | N47: nee
A48: 47 | B48: 46055 | C48: VERPLICHT | D48: K1 | E48: A1 | F48: 2026-205 | G48: 411100 | H48: =INDEX('MAR 2e graad'!$B$2:$B$58,MATCH(G48,'MAR 2e graad'!$A$2:$A$58,0)) | I48: =INDEX('MAR 2e graad'!$C$2:$C$58,MATCH(G48,'MAR 2e graad'!$A$2:$A$58,0)) | J48: =IF(OR(I48="A",I48="K"),IF(K48>0,"+","-"),IF(L48>0,"+","-")) | K48: 3234 | M48: de vordering op de overheid (aftrekbare btw) stijgt | N48: nee
A49: 48 | B49: 46055 | C49: VERPLICHT | D49: K1 | E49: A1 | F49: 2026-205 | G49: 440000 | H49: =INDEX('MAR 2e graad'!$B$2:$B$58,MATCH(G49,'MAR 2e graad'!$A$2:$A$58,0)) | I49: =INDEX('MAR 2e graad'!$C$2:$C$58,MATCH(G49,'MAR 2e graad'!$A$2:$A$58,0)) | J49: =IF(OR(I49="A",I49="K"),IF(K49>0,"+","-"),IF(L49>0,"+","-")) | L49: 18634 | M49: de schuld aan de leverancier stijgt | N49: nee
A50: 49 | B50: 46056 | C50: VERPLICHT | D50: K1 | E50: V1 | F50: 2026-003 | G50: 400000 | H50: =INDEX('MAR 2e graad'!$B$2:$B$58,MATCH(G50,'MAR 2e graad'!$A$2:$A$58,0)) | I50: =INDEX('MAR 2e graad'!$C$2:$C$58,MATCH(G50,'MAR 2e graad'!$A$2:$A$58,0)) | J50: =IF(OR(I50="A",I50="K"),IF(K50>0,"+","-"),IF(L50>0,"+","-")) | K50: 5808 | M50: de vordering op de klant stijgt | N50: nee
A51: 50 | B51: 46056 | C51: VERPLICHT | D51: K1 | E51: V1 | F51: 2026-003 | G51: 704000 | H51: =INDEX('MAR 2e graad'!$B$2:$B$58,MATCH(G51,'MAR 2e graad'!$A$2:$A$58,0)) | I51: =INDEX('MAR 2e graad'!$C$2:$C$58,MATCH(G51,'MAR 2e graad'!$A$2:$A$58,0)) | J51: =IF(OR(I51="A",I51="K"),IF(K51>0,"+","-"),IF(L51>0,"+","-")) | L51: 4800 | M51: de omzet stijgt | N51: nee
A52: 51 | B52: 46056 | C52: VERPLICHT | D52: K1 | E52: V1 | F52: 2026-003 | G52: 451100 | H52: =INDEX('MAR 2e graad'!$B$2:$B$58,MATCH(G52,'MAR 2e graad'!$A$2:$A$58,0)) | I52: =INDEX('MAR 2e graad'!$C$2:$C$58,MATCH(G52,'MAR 2e graad'!$A$2:$A$58,0)) | J52: =IF(OR(I52="A",I52="K"),IF(K52>0,"+","-"),IF(L52>0,"+","-")) | L52: 1008 | M52: de schuld aan de overheid (verschuldigde btw) stijgt | N52: nee
A53: 52 | B53: 46057 | C53: VERPLICHT | D53: K1 | E53: A2 | F53: SW-1032 | G53: 604000 | H53: =INDEX('MAR 2e graad'!$B$2:$B$58,MATCH(G53,'MAR 2e graad'!$A$2:$A$58,0)) | I53: =INDEX('MAR 2e graad'!$C$2:$C$58,MATCH(G53,'MAR 2e graad'!$A$2:$A$58,0)) | J53: =IF(OR(I53="A",I53="K"),IF(K53>0,"+","-"),IF(L53>0,"+","-")) | K53: 300 | M53: de kosten voor handelsgoederen stijgen | N53: nee
A54: 53 | B54: 46057 | C54: VERPLICHT | D54: K1 | E54: A2 | F54: SW-1032 | G54: 604000 | H54: =INDEX('MAR 2e graad'!$B$2:$B$58,MATCH(G54,'MAR 2e graad'!$A$2:$A$58,0)) | I54: =INDEX('MAR 2e graad'!$C$2:$C$58,MATCH(G54,'MAR 2e graad'!$A$2:$A$58,0)) | J54: =IF(OR(I54="A",I54="K"),IF(K54>0,"+","-"),IF(L54>0,"+","-")) | K54: 100 | M54: de kosten voor handelsgoederen stijgen | N54: nee
A55: 54 | B55: 46057 | C55: VERPLICHT | D55: K1 | E55: A2 | F55: SW-1032 | G55: 411100 | H55: =INDEX('MAR 2e graad'!$B$2:$B$58,MATCH(G55,'MAR 2e graad'!$A$2:$A$58,0)) | I55: =INDEX('MAR 2e graad'!$C$2:$C$58,MATCH(G55,'MAR 2e graad'!$A$2:$A$58,0)) | J55: =IF(OR(I55="A",I55="K"),IF(K55>0,"+","-"),IF(L55>0,"+","-")) | K55: 84 | M55: de vordering op de overheid (aftrekbare btw) stijgt | N55: nee
A56: 55 | B56: 46057 | C56: VERPLICHT | D56: K1 | E56: A2 | F56: SW-1032 | G56: 440000 | H56: =INDEX('MAR 2e graad'!$B$2:$B$58,MATCH(G56,'MAR 2e graad'!$A$2:$A$58,0)) | I56: =INDEX('MAR 2e graad'!$C$2:$C$58,MATCH(G56,'MAR 2e graad'!$A$2:$A$58,0)) | J56: =IF(OR(I56="A",I56="K"),IF(K56>0,"+","-"),IF(L56>0,"+","-")) | L56: 484 | M56: de schuld aan de leverancier stijgt | N56: nee
A57: 56 | B57: 46059 | C57: VERPLICHT | D57: K1 | E57: A3 | F57: HH-26-077 | G57: 604000 | H57: =INDEX('MAR 2e graad'!$B$2:$B$58,MATCH(G57,'MAR 2e graad'!$A$2:$A$58,0)) | I57: =INDEX('MAR 2e graad'!$C$2:$C$58,MATCH(G57,'MAR 2e graad'!$A$2:$A$58,0)) | J57: =IF(OR(I57="A",I57="K"),IF(K57>0,"+","-"),IF(L57>0,"+","-")) | K57: 600 | M57: de kosten voor handelsgoederen stijgen | N57: nee
A58: 57 | B58: 46059 | C58: VERPLICHT | D58: K1 | E58: A3 | F58: HH-26-077 | G58: 604000 | H58: =INDEX('MAR 2e graad'!$B$2:$B$58,MATCH(G58,'MAR 2e graad'!$A$2:$A$58,0)) | I58: =INDEX('MAR 2e graad'!$C$2:$C$58,MATCH(G58,'MAR 2e graad'!$A$2:$A$58,0)) | J58: =IF(OR(I58="A",I58="K"),IF(K58>0,"+","-"),IF(L58>0,"+","-")) | K58: 400 | M58: de kosten voor handelsgoederen stijgen | N58: nee
A59: 58 | B59: 46059 | C59: VERPLICHT | D59: K1 | E59: A3 | F59: HH-26-077 | G59: 411100 | H59: =INDEX('MAR 2e graad'!$B$2:$B$58,MATCH(G59,'MAR 2e graad'!$A$2:$A$58,0)) | I59: =INDEX('MAR 2e graad'!$C$2:$C$58,MATCH(G59,'MAR 2e graad'!$A$2:$A$58,0)) | J59: =IF(OR(I59="A",I59="K"),IF(K59>0,"+","-"),IF(L59>0,"+","-")) | K59: 210 | M59: de vordering op de overheid (aftrekbare btw) stijgt | N59: nee
A60: 59 | B60: 46059 | C60: VERPLICHT | D60: K1 | E60: A3 | F60: HH-26-077 | G60: 440000 | H60: =INDEX('MAR 2e graad'!$B$2:$B$58,MATCH(G60,'MAR 2e graad'!$A$2:$A$58,0)) | I60: =INDEX('MAR 2e graad'!$C$2:$C$58,MATCH(G60,'MAR 2e graad'!$A$2:$A$58,0)) | J60: =IF(OR(I60="A",I60="K"),IF(K60>0,"+","-"),IF(L60>0,"+","-")) | L60: 1210 | M60: de schuld aan de leverancier stijgt | N60: nee
A61: 60 | B61: 46060 | C61: VERPLICHT | D61: K1 | E61: D1 | F61: DO-2026-02 | G61: 400000 | H61: =INDEX('MAR 2e graad'!$B$2:$B$58,MATCH(G61,'MAR 2e graad'!$A$2:$A$58,0)) | I61: =INDEX('MAR 2e graad'!$C$2:$C$58,MATCH(G61,'MAR 2e graad'!$A$2:$A$58,0)) | J61: =IF(OR(I61="A",I61="K"),IF(K61>0,"+","-"),IF(L61>0,"+","-")) | K61: 2133 | M61: de vordering op de klanten (dagontvangsten) stijgt | N61: nee
A62: 61 | B62: 46060 | C62: VERPLICHT | D62: K1 | E62: D1 | F62: DO-2026-02 | G62: 704000 | H62: =INDEX('MAR 2e graad'!$B$2:$B$58,MATCH(G62,'MAR 2e graad'!$A$2:$A$58,0)) | I62: =INDEX('MAR 2e graad'!$C$2:$C$58,MATCH(G62,'MAR 2e graad'!$A$2:$A$58,0)) | J62: =IF(OR(I62="A",I62="K"),IF(K62>0,"+","-"),IF(L62>0,"+","-")) | L62: 1200 | M62: de omzet stijgt | N62: nee
A63: 62 | B63: 46060 | C63: VERPLICHT | D63: K1 | E63: D1 | F63: DO-2026-02 | G63: 704000 | H63: =INDEX('MAR 2e graad'!$B$2:$B$58,MATCH(G63,'MAR 2e graad'!$A$2:$A$58,0)) | I63: =INDEX('MAR 2e graad'!$C$2:$C$58,MATCH(G63,'MAR 2e graad'!$A$2:$A$58,0)) | J63: =IF(OR(I63="A",I63="K"),IF(K63>0,"+","-"),IF(L63>0,"+","-")) | L63: 300 | M63: de omzet stijgt | N63: nee
A64: 63 | B64: 46060 | C64: VERPLICHT | D64: K1 | E64: D1 | F64: DO-2026-02 | G64: 700000 | H64: =INDEX('MAR 2e graad'!$B$2:$B$58,MATCH(G64,'MAR 2e graad'!$A$2:$A$58,0)) | I64: =INDEX('MAR 2e graad'!$C$2:$C$58,MATCH(G64,'MAR 2e graad'!$A$2:$A$58,0)) | J64: =IF(OR(I64="A",I64="K"),IF(K64>0,"+","-"),IF(L64>0,"+","-")) | L64: 300 | M64: de omzet (diensten) stijgt | N64: nee
A65: 64 | B65: 46060 | C65: VERPLICHT | D65: K1 | E65: D1 | F65: DO-2026-02 | G65: 451100 | H65: =INDEX('MAR 2e graad'!$B$2:$B$58,MATCH(G65,'MAR 2e graad'!$A$2:$A$58,0)) | I65: =INDEX('MAR 2e graad'!$C$2:$C$58,MATCH(G65,'MAR 2e graad'!$A$2:$A$58,0)) | J65: =IF(OR(I65="A",I65="K"),IF(K65>0,"+","-"),IF(L65>0,"+","-")) | L65: 333 | M65: de schuld aan de overheid (verschuldigde btw) stijgt | N65: nee
A66: 65 | B66: 46060 | C66: VERPLICHT | D66: K1 | E66: D1K | F66: Kasboek DO-2026-02 | G66: 570000 | H66: =INDEX('MAR 2e graad'!$B$2:$B$58,MATCH(G66,'MAR 2e graad'!$A$2:$A$58,0)) | I66: =INDEX('MAR 2e graad'!$C$2:$C$58,MATCH(G66,'MAR 2e graad'!$A$2:$A$58,0)) | J66: =IF(OR(I66="A",I66="K"),IF(K66>0,"+","-"),IF(L66>0,"+","-")) | K66: 633 | M66: de kas stijgt | N66: nee
A67: 66 | B67: 46060 | C67: VERPLICHT | D67: K1 | E67: D1K | F67: Kasboek DO-2026-02 | G67: 400000 | H67: =INDEX('MAR 2e graad'!$B$2:$B$58,MATCH(G67,'MAR 2e graad'!$A$2:$A$58,0)) | I67: =INDEX('MAR 2e graad'!$C$2:$C$58,MATCH(G67,'MAR 2e graad'!$A$2:$A$58,0)) | J67: =IF(OR(I67="A",I67="K"),IF(K67>0,"+","-"),IF(L67>0,"+","-")) | L67: 633 | M67: de vordering op de klanten (contant betaald) daalt | N67: nee
A68: 67 | B68: 46062 | C68: VERPLICHT | D68: K1 | E68: A4 | F68: DP-2026-031 | G68: 616520 | H68: =INDEX('MAR 2e graad'!$B$2:$B$58,MATCH(G68,'MAR 2e graad'!$A$2:$A$58,0)) | I68: =INDEX('MAR 2e graad'!$C$2:$C$58,MATCH(G68,'MAR 2e graad'!$A$2:$A$58,0)) | J68: =IF(OR(I68="A",I68="K"),IF(K68>0,"+","-"),IF(L68>0,"+","-")) | K68: 500 | M68: de kosten voor diensten en diverse goederen stijgen | N68: nee
A69: 68 | B69: 46062 | C69: VERPLICHT | D69: K1 | E69: A4 | F69: DP-2026-031 | G69: 411100 | H69: =INDEX('MAR 2e graad'!$B$2:$B$58,MATCH(G69,'MAR 2e graad'!$A$2:$A$58,0)) | I69: =INDEX('MAR 2e graad'!$C$2:$C$58,MATCH(G69,'MAR 2e graad'!$A$2:$A$58,0)) | J69: =IF(OR(I69="A",I69="K"),IF(K69>0,"+","-"),IF(L69>0,"+","-")) | K69: 105 | M69: de vordering op de overheid (aftrekbare btw) stijgt | N69: nee
A70: 69 | B70: 46062 | C70: VERPLICHT | D70: K1 | E70: A4 | F70: DP-2026-031 | G70: 440000 | H70: =INDEX('MAR 2e graad'!$B$2:$B$58,MATCH(G70,'MAR 2e graad'!$A$2:$A$58,0)) | I70: =INDEX('MAR 2e graad'!$C$2:$C$58,MATCH(G70,'MAR 2e graad'!$A$2:$A$58,0)) | J70: =IF(OR(I70="A",I70="K"),IF(K70>0,"+","-"),IF(L70>0,"+","-")) | L70: 605 | M70: de schuld aan de leverancier stijgt | N70: nee
A71: 70 | B71: 46063 | C71: VERPLICHT | D71: K1 | E71: V2 | F71: 2026-004 | G71: 400000 | H71: =INDEX('MAR 2e graad'!$B$2:$B$58,MATCH(G71,'MAR 2e graad'!$A$2:$A$58,0)) | I71: =INDEX('MAR 2e graad'!$C$2:$C$58,MATCH(G71,'MAR 2e graad'!$A$2:$A$58,0)) | J71: =IF(OR(I71="A",I71="K"),IF(K71>0,"+","-"),IF(L71>0,"+","-")) | K71: 6292 | M71: de vordering op de klant stijgt | N71: nee
A72: 71 | B72: 46063 | C72: VERPLICHT | D72: K1 | E72: V2 | F72: 2026-004 | G72: 704000 | H72: =INDEX('MAR 2e graad'!$B$2:$B$58,MATCH(G72,'MAR 2e graad'!$A$2:$A$58,0)) | I72: =INDEX('MAR 2e graad'!$C$2:$C$58,MATCH(G72,'MAR 2e graad'!$A$2:$A$58,0)) | J72: =IF(OR(I72="A",I72="K"),IF(K72>0,"+","-"),IF(L72>0,"+","-")) | L72: 5200 | M72: de omzet stijgt | N72: nee
A73: 72 | B73: 46063 | C73: VERPLICHT | D73: K1 | E73: V2 | F73: 2026-004 | G73: 451100 | H73: =INDEX('MAR 2e graad'!$B$2:$B$58,MATCH(G73,'MAR 2e graad'!$A$2:$A$58,0)) | I73: =INDEX('MAR 2e graad'!$C$2:$C$58,MATCH(G73,'MAR 2e graad'!$A$2:$A$58,0)) | J73: =IF(OR(I73="A",I73="K"),IF(K73>0,"+","-"),IF(L73>0,"+","-")) | L73: 1092 | M73: de schuld aan de overheid (verschuldigde btw) stijgt | N73: nee
A74: 73 | B74: 46063 | C74: VERPLICHT | D74: K1 | E74: U2026-04/1 | F74: uittreksel U2026-04/1 | G74: 550000 | H74: =INDEX('MAR 2e graad'!$B$2:$B$58,MATCH(G74,'MAR 2e graad'!$A$2:$A$58,0)) | I74: =INDEX('MAR 2e graad'!$C$2:$C$58,MATCH(G74,'MAR 2e graad'!$A$2:$A$58,0)) | J74: =IF(OR(I74="A",I74="K"),IF(K74>0,"+","-"),IF(L74>0,"+","-")) | K74: 1500 | M74: de bank stijgt | N74: nee
A75: 74 | B75: 46063 | C75: VERPLICHT | D75: K1 | E75: U2026-04/1 | F75: uittreksel U2026-04/1 | G75: 400000 | H75: =INDEX('MAR 2e graad'!$B$2:$B$58,MATCH(G75,'MAR 2e graad'!$A$2:$A$58,0)) | I75: =INDEX('MAR 2e graad'!$C$2:$C$58,MATCH(G75,'MAR 2e graad'!$A$2:$A$58,0)) | J75: =IF(OR(I75="A",I75="K"),IF(K75>0,"+","-"),IF(L75>0,"+","-")) | L75: 1500 | M75: de vordering (bancontact) daalt | N75: nee
A76: 75 | B76: 46064 | C76: VERPLICHT | D76: K1 | E76: A5 | F76: KT-0458 | G76: 240200 | H76: =INDEX('MAR 2e graad'!$B$2:$B$58,MATCH(G76,'MAR 2e graad'!$A$2:$A$58,0)) | I76: =INDEX('MAR 2e graad'!$C$2:$C$58,MATCH(G76,'MAR 2e graad'!$A$2:$A$58,0)) | J76: =IF(OR(I76="A",I76="K"),IF(K76>0,"+","-"),IF(L76>0,"+","-")) | K76: 1200 | M76: het vast actief stijgt | N76: nee
A77: 76 | B77: 46064 | C77: VERPLICHT | D77: K1 | E77: A5 | F77: KT-0458 | G77: 411100 | H77: =INDEX('MAR 2e graad'!$B$2:$B$58,MATCH(G77,'MAR 2e graad'!$A$2:$A$58,0)) | I77: =INDEX('MAR 2e graad'!$C$2:$C$58,MATCH(G77,'MAR 2e graad'!$A$2:$A$58,0)) | J77: =IF(OR(I77="A",I77="K"),IF(K77>0,"+","-"),IF(L77>0,"+","-")) | K77: 252 | M77: de vordering op de overheid (aftrekbare btw) stijgt | N77: nee
A78: 77 | B78: 46064 | C78: VERPLICHT | D78: K1 | E78: A5 | F78: KT-0458 | G78: 440000 | H78: =INDEX('MAR 2e graad'!$B$2:$B$58,MATCH(G78,'MAR 2e graad'!$A$2:$A$58,0)) | I78: =INDEX('MAR 2e graad'!$C$2:$C$58,MATCH(G78,'MAR 2e graad'!$A$2:$A$58,0)) | J78: =IF(OR(I78="A",I78="K"),IF(K78>0,"+","-"),IF(L78>0,"+","-")) | L78: 1452 | M78: de schuld aan de leverancier stijgt | N78: nee
A79: 78 | B79: 46065 | C79: VERPLICHT | D79: K1 | E79: V3 | F79: 2026-005 | G79: 400000 | H79: =INDEX('MAR 2e graad'!$B$2:$B$58,MATCH(G79,'MAR 2e graad'!$A$2:$A$58,0)) | I79: =INDEX('MAR 2e graad'!$C$2:$C$58,MATCH(G79,'MAR 2e graad'!$A$2:$A$58,0)) | J79: =IF(OR(I79="A",I79="K"),IF(K79>0,"+","-"),IF(L79>0,"+","-")) | K79: 7260 | M79: de vordering op de klant stijgt | N79: nee
A80: 79 | B80: 46065 | C80: VERPLICHT | D80: K1 | E80: V3 | F80: 2026-005 | G80: 704000 | H80: =INDEX('MAR 2e graad'!$B$2:$B$58,MATCH(G80,'MAR 2e graad'!$A$2:$A$58,0)) | I80: =INDEX('MAR 2e graad'!$C$2:$C$58,MATCH(G80,'MAR 2e graad'!$A$2:$A$58,0)) | J80: =IF(OR(I80="A",I80="K"),IF(K80>0,"+","-"),IF(L80>0,"+","-")) | L80: 6000 | M80: de omzet stijgt | N80: nee
A81: 80 | B81: 46065 | C81: VERPLICHT | D81: K1 | E81: V3 | F81: 2026-005 | G81: 451100 | H81: =INDEX('MAR 2e graad'!$B$2:$B$58,MATCH(G81,'MAR 2e graad'!$A$2:$A$58,0)) | I81: =INDEX('MAR 2e graad'!$C$2:$C$58,MATCH(G81,'MAR 2e graad'!$A$2:$A$58,0)) | J81: =IF(OR(I81="A",I81="K"),IF(K81>0,"+","-"),IF(L81>0,"+","-")) | L81: 1260 | M81: de schuld aan de overheid (verschuldigde btw) stijgt | N81: nee
A82: 81 | B82: 46066 | C82: VERPLICHT | D82: K1 | E82: CA1 | F82: CN-2026-015 | G82: 604010 | H82: =INDEX('MAR 2e graad'!$B$2:$B$58,MATCH(G82,'MAR 2e graad'!$A$2:$A$58,0)) | I82: =INDEX('MAR 2e graad'!$C$2:$C$58,MATCH(G82,'MAR 2e graad'!$A$2:$A$58,0)) | J82: =IF(OR(I82="A",I82="K"),IF(K82>0,"+","-"),IF(L82>0,"+","-")) | L82: 1400 | M82: de kosten voor handelsgoederen dalen (retour) | N82: nee
A83: 82 | B83: 46066 | C83: VERPLICHT | D83: K1 | E83: CA1 | F83: CN-2026-015 | G83: 451200 | H83: =INDEX('MAR 2e graad'!$B$2:$B$58,MATCH(G83,'MAR 2e graad'!$A$2:$A$58,0)) | I83: =INDEX('MAR 2e graad'!$C$2:$C$58,MATCH(G83,'MAR 2e graad'!$A$2:$A$58,0)) | J83: =IF(OR(I83="A",I83="K"),IF(K83>0,"+","-"),IF(L83>0,"+","-")) | L83: 294 | M83: de schuld aan de overheid stijgt (btw op inkomende creditnota) | N83: nee
A84: 83 | B84: 46066 | C84: VERPLICHT | D84: K1 | E84: CA1 | F84: CN-2026-015 | G84: 440000 | H84: =INDEX('MAR 2e graad'!$B$2:$B$58,MATCH(G84,'MAR 2e graad'!$A$2:$A$58,0)) | I84: =INDEX('MAR 2e graad'!$C$2:$C$58,MATCH(G84,'MAR 2e graad'!$A$2:$A$58,0)) | J84: =IF(OR(I84="A",I84="K"),IF(K84>0,"+","-"),IF(L84>0,"+","-")) | K84: 1694 | M84: de schuld aan de leverancier daalt | N84: nee
A85: 84 | B85: 46067 | C85: VERPLICHT | D85: K1 | E85: D2 | F85: DO-2026-03 | G85: 400000 | H85: =INDEX('MAR 2e graad'!$B$2:$B$58,MATCH(G85,'MAR 2e graad'!$A$2:$A$58,0)) | I85: =INDEX('MAR 2e graad'!$C$2:$C$58,MATCH(G85,'MAR 2e graad'!$A$2:$A$58,0)) | J85: =IF(OR(I85="A",I85="K"),IF(K85>0,"+","-"),IF(L85>0,"+","-")) | K85: 2844 | M85: de vordering op de klanten (dagontvangsten) stijgt | N85: nee
A86: 85 | B86: 46067 | C86: VERPLICHT | D86: K1 | E86: D2 | F86: DO-2026-03 | G86: 704000 | H86: =INDEX('MAR 2e graad'!$B$2:$B$58,MATCH(G86,'MAR 2e graad'!$A$2:$A$58,0)) | I86: =INDEX('MAR 2e graad'!$C$2:$C$58,MATCH(G86,'MAR 2e graad'!$A$2:$A$58,0)) | J86: =IF(OR(I86="A",I86="K"),IF(K86>0,"+","-"),IF(L86>0,"+","-")) | L86: 2000 | M86: de omzet stijgt | N86: nee
A87: 86 | B87: 46067 | C87: VERPLICHT | D87: K1 | E87: D2 | F87: DO-2026-03 | G87: 700000 | H87: =INDEX('MAR 2e graad'!$B$2:$B$58,MATCH(G87,'MAR 2e graad'!$A$2:$A$58,0)) | I87: =INDEX('MAR 2e graad'!$C$2:$C$58,MATCH(G87,'MAR 2e graad'!$A$2:$A$58,0)) | J87: =IF(OR(I87="A",I87="K"),IF(K87>0,"+","-"),IF(L87>0,"+","-")) | L87: 400 | M87: de omzet (diensten) stijgt | N87: nee
A88: 87 | B88: 46067 | C88: VERPLICHT | D88: K1 | E88: D2 | F88: DO-2026-03 | G88: 451100 | H88: =INDEX('MAR 2e graad'!$B$2:$B$58,MATCH(G88,'MAR 2e graad'!$A$2:$A$58,0)) | I88: =INDEX('MAR 2e graad'!$C$2:$C$58,MATCH(G88,'MAR 2e graad'!$A$2:$A$58,0)) | J88: =IF(OR(I88="A",I88="K"),IF(K88>0,"+","-"),IF(L88>0,"+","-")) | L88: 444 | M88: de schuld aan de overheid (verschuldigde btw) stijgt | N88: nee
A89: 88 | B89: 46067 | C89: VERPLICHT | D89: K1 | E89: D2K | F89: Kasboek DO-2026-03 | G89: 570000 | H89: =INDEX('MAR 2e graad'!$B$2:$B$58,MATCH(G89,'MAR 2e graad'!$A$2:$A$58,0)) | I89: =INDEX('MAR 2e graad'!$C$2:$C$58,MATCH(G89,'MAR 2e graad'!$A$2:$A$58,0)) | J89: =IF(OR(I89="A",I89="K"),IF(K89>0,"+","-"),IF(L89>0,"+","-")) | K89: 344 | M89: de kas stijgt | N89: nee
A90: 89 | B90: 46067 | C90: VERPLICHT | D90: K1 | E90: D2K | F90: Kasboek DO-2026-03 | G90: 400000 | H90: =INDEX('MAR 2e graad'!$B$2:$B$58,MATCH(G90,'MAR 2e graad'!$A$2:$A$58,0)) | I90: =INDEX('MAR 2e graad'!$C$2:$C$58,MATCH(G90,'MAR 2e graad'!$A$2:$A$58,0)) | J90: =IF(OR(I90="A",I90="K"),IF(K90>0,"+","-"),IF(L90>0,"+","-")) | L90: 344 | M90: de vordering op de klanten (contant betaald) daalt | N90: nee
A91: 90 | B91: 46069 | C91: VERPLICHT | D91: K1 | E91: CA2 | F91: HH-CN-26-004 | G91: 604010 | H91: =INDEX('MAR 2e graad'!$B$2:$B$58,MATCH(G91,'MAR 2e graad'!$A$2:$A$58,0)) | I91: =INDEX('MAR 2e graad'!$C$2:$C$58,MATCH(G91,'MAR 2e graad'!$A$2:$A$58,0)) | J91: =IF(OR(I91="A",I91="K"),IF(K91>0,"+","-"),IF(L91>0,"+","-")) | L91: 200 | M91: de kosten voor handelsgoederen dalen (retour) | N91: nee
A92: 91 | B92: 46069 | C92: VERPLICHT | D92: K1 | E92: CA2 | F92: HH-CN-26-004 | G92: 451200 | H92: =INDEX('MAR 2e graad'!$B$2:$B$58,MATCH(G92,'MAR 2e graad'!$A$2:$A$58,0)) | I92: =INDEX('MAR 2e graad'!$C$2:$C$58,MATCH(G92,'MAR 2e graad'!$A$2:$A$58,0)) | J92: =IF(OR(I92="A",I92="K"),IF(K92>0,"+","-"),IF(L92>0,"+","-")) | L92: 42 | M92: de schuld aan de overheid stijgt (btw op inkomende creditnota) | N92: nee
A93: 92 | B93: 46069 | C93: VERPLICHT | D93: K1 | E93: CA2 | F93: HH-CN-26-004 | G93: 440000 | H93: =INDEX('MAR 2e graad'!$B$2:$B$58,MATCH(G93,'MAR 2e graad'!$A$2:$A$58,0)) | I93: =INDEX('MAR 2e graad'!$C$2:$C$58,MATCH(G93,'MAR 2e graad'!$A$2:$A$58,0)) | J93: =IF(OR(I93="A",I93="K"),IF(K93>0,"+","-"),IF(L93>0,"+","-")) | K93: 242 | M93: de schuld aan de leverancier daalt | N93: nee
A94: 93 | B94: 46070 | C94: VERPLICHT | D94: K1 | E94: V4 | F94: 2026-006 | G94: 400000 | H94: =INDEX('MAR 2e graad'!$B$2:$B$58,MATCH(G94,'MAR 2e graad'!$A$2:$A$58,0)) | I94: =INDEX('MAR 2e graad'!$C$2:$C$58,MATCH(G94,'MAR 2e graad'!$A$2:$A$58,0)) | J94: =IF(OR(I94="A",I94="K"),IF(K94>0,"+","-"),IF(L94>0,"+","-")) | K94: 636 | M94: de vordering op de klant stijgt | N94: nee
A95: 94 | B95: 46070 | C95: VERPLICHT | D95: K1 | E95: V4 | F95: 2026-006 | G95: 700000 | H95: =INDEX('MAR 2e graad'!$B$2:$B$58,MATCH(G95,'MAR 2e graad'!$A$2:$A$58,0)) | I95: =INDEX('MAR 2e graad'!$C$2:$C$58,MATCH(G95,'MAR 2e graad'!$A$2:$A$58,0)) | J95: =IF(OR(I95="A",I95="K"),IF(K95>0,"+","-"),IF(L95>0,"+","-")) | L95: 600 | M95: de omzet (diensten) stijgt | N95: nee
A96: 95 | B96: 46070 | C96: VERPLICHT | D96: K1 | E96: V4 | F96: 2026-006 | G96: 451100 | H96: =INDEX('MAR 2e graad'!$B$2:$B$58,MATCH(G96,'MAR 2e graad'!$A$2:$A$58,0)) | I96: =INDEX('MAR 2e graad'!$C$2:$C$58,MATCH(G96,'MAR 2e graad'!$A$2:$A$58,0)) | J96: =IF(OR(I96="A",I96="K"),IF(K96>0,"+","-"),IF(L96>0,"+","-")) | L96: 36 | M96: de schuld aan de overheid (verschuldigde btw) stijgt | N96: nee
A97: 96 | B97: 46072 | C97: VERPLICHT | D97: K1 | E97: V5 | F97: 2026-007 | G97: 400000 | H97: =INDEX('MAR 2e graad'!$B$2:$B$58,MATCH(G97,'MAR 2e graad'!$A$2:$A$58,0)) | I97: =INDEX('MAR 2e graad'!$C$2:$C$58,MATCH(G97,'MAR 2e graad'!$A$2:$A$58,0)) | J97: =IF(OR(I97="A",I97="K"),IF(K97>0,"+","-"),IF(L97>0,"+","-")) | K97: 1694 | M97: de vordering op de klant stijgt | N97: nee
A98: 97 | B98: 46072 | C98: VERPLICHT | D98: K1 | E98: V5 | F98: 2026-007 | G98: 704000 | H98: =INDEX('MAR 2e graad'!$B$2:$B$58,MATCH(G98,'MAR 2e graad'!$A$2:$A$58,0)) | I98: =INDEX('MAR 2e graad'!$C$2:$C$58,MATCH(G98,'MAR 2e graad'!$A$2:$A$58,0)) | J98: =IF(OR(I98="A",I98="K"),IF(K98>0,"+","-"),IF(L98>0,"+","-")) | L98: 1200 | M98: de omzet stijgt | N98: nee
A99: 98 | B99: 46072 | C99: VERPLICHT | D99: K1 | E99: V5 | F99: 2026-007 | G99: 704000 | H99: =INDEX('MAR 2e graad'!$B$2:$B$58,MATCH(G99,'MAR 2e graad'!$A$2:$A$58,0)) | I99: =INDEX('MAR 2e graad'!$C$2:$C$58,MATCH(G99,'MAR 2e graad'!$A$2:$A$58,0)) | J99: =IF(OR(I99="A",I99="K"),IF(K99>0,"+","-"),IF(L99>0,"+","-")) | L99: 200 | M99: de omzet stijgt | N99: nee
A100: 99 | B100: 46072 | C100: VERPLICHT | D100: K1 | E100: V5 | F100: 2026-007 | G100: 451100 | H100: =INDEX('MAR 2e graad'!$B$2:$B$58,MATCH(G100,'MAR 2e graad'!$A$2:$A$58,0)) | I100: =INDEX('MAR 2e graad'!$C$2:$C$58,MATCH(G100,'MAR 2e graad'!$A$2:$A$58,0)) | J100: =IF(OR(I100="A",I100="K"),IF(K100>0,"+","-"),IF(L100>0,"+","-")) | L100: 294 | M100: de schuld aan de overheid (verschuldigde btw) stijgt | N100: nee
...

Sheet J1 Proefbalans
A1: Rekening | B1: Naam | C1: A/P/K/O | D1: Openingsbalans | E1: Saldo einde K1 | F1: Saldo einde K2 | G1: Saldo einde K3 | H1: Saldo einde K4 vóór afsluiting | I1: Na afsluiting 31/12 | J1: Debetsaldo = positief, creditsaldo = negatief
A2: 100000 | B2: Geplaatst kapitaal | C2: P | D2: -20000 | E2: =$D2+SUMIFS('J1 Journaal'!$K:$K,'J1 Journaal'!$G:$G,$A2,'J1 Journaal'!$B:$B,"<="&DATE(2026,3,31),'J1 Journaal'!$N:$N,"nee")-SUMIFS('J1 Journaal'!$L:$L,'J1 Journaal'!$G:$G,$A2,'J1 Journaal'!$B:$B,"<="&DATE(2026,3,31),'J1 Journaal'!$N:$N,"nee") | F2: =$D2+SUMIFS('J1 Journaal'!$K:$K,'J1 Journaal'!$G:$G,$A2,'J1 Journaal'!$B:$B,"<="&DATE(2026,6,30),'J1 Journaal'!$N:$N,"nee")-SUMIFS('J1 Journaal'!$L:$L,'J1 Journaal'!$G:$G,$A2,'J1 Journaal'!$B:$B,"<="&DATE(2026,6,30),'J1 Journaal'!$N:$N,"nee") | G2: =$D2+SUMIFS('J1 Journaal'!$K:$K,'J1 Journaal'!$G:$G,$A2,'J1 Journaal'!$B:$B,"<="&DATE(2026,9,30),'J1 Journaal'!$N:$N,"nee")-SUMIFS('J1 Journaal'!$L:$L,'J1 Journaal'!$G:$G,$A2,'J1 Journaal'!$B:$B,"<="&DATE(2026,9,30),'J1 Journaal'!$N:$N,"nee") | H2: =$D2+SUMIFS('J1 Journaal'!$K:$K,'J1 Journaal'!$G:$G,$A2,'J1 Journaal'!$B:$B,"<="&DATE(2026,12,31),'J1 Journaal'!$N:$N,"nee")-SUMIFS('J1 Journaal'!$L:$L,'J1 Journaal'!$G:$G,$A2,'J1 Journaal'!$B:$B,"<="&DATE(2026,12,31),'J1 Journaal'!$N:$N,"nee") | I2: =$D2+SUMIFS('J1 Journaal'!$K:$K,'J1 Journaal'!$G:$G,$A2)-SUMIFS('J1 Journaal'!$L:$L,'J1 Journaal'!$G:$G,$A2)
A3: 140000 | B3: Overgedragen winst | C3: P | D3: 0 | E3: =$D3+SUMIFS('J1 Journaal'!$K:$K,'J1 Journaal'!$G:$G,$A3,'J1 Journaal'!$B:$B,"<="&DATE(2026,3,31),'J1 Journaal'!$N:$N,"nee")-SUMIFS('J1 Journaal'!$L:$L,'J1 Journaal'!$G:$G,$A3,'J1 Journaal'!$B:$B,"<="&DATE(2026,3,31),'J1 Journaal'!$N:$N,"nee") | F3: =$D3+SUMIFS('J1 Journaal'!$K:$K,'J1 Journaal'!$G:$G,$A3,'J1 Journaal'!$B:$B,"<="&DATE(2026,6,30),'J1 Journaal'!$N:$N,"nee")-SUMIFS('J1 Journaal'!$L:$L,'J1 Journaal'!$G:$G,$A3,'J1 Journaal'!$B:$B,"<="&DATE(2026,6,30),'J1 Journaal'!$N:$N,"nee") | G3: =$D3+SUMIFS('J1 Journaal'!$K:$K,'J1 Journaal'!$G:$G,$A3,'J1 Journaal'!$B:$B,"<="&DATE(2026,9,30),'J1 Journaal'!$N:$N,"nee")-SUMIFS('J1 Journaal'!$L:$L,'J1 Journaal'!$G:$G,$A3,'J1 Journaal'!$B:$B,"<="&DATE(2026,9,30),'J1 Journaal'!$N:$N,"nee") | H3: =$D3+SUMIFS('J1 Journaal'!$K:$K,'J1 Journaal'!$G:$G,$A3,'J1 Journaal'!$B:$B,"<="&DATE(2026,12,31),'J1 Journaal'!$N:$N,"nee")-SUMIFS('J1 Journaal'!$L:$L,'J1 Journaal'!$G:$G,$A3,'J1 Journaal'!$B:$B,"<="&DATE(2026,12,31),'J1 Journaal'!$N:$N,"nee") | I3: =$D3+SUMIFS('J1 Journaal'!$K:$K,'J1 Journaal'!$G:$G,$A3)-SUMIFS('J1 Journaal'!$L:$L,'J1 Journaal'!$G:$G,$A3)
A4: 141000 | B4: Overgedragen verlies (-) | C4: P | D4: 0 | E4: =$D4+SUMIFS('J1 Journaal'!$K:$K,'J1 Journaal'!$G:$G,$A4,'J1 Journaal'!$B:$B,"<="&DATE(2026,3,31),'J1 Journaal'!$N:$N,"nee")-SUMIFS('J1 Journaal'!$L:$L,'J1 Journaal'!$G:$G,$A4,'J1 Journaal'!$B:$B,"<="&DATE(2026,3,31),'J1 Journaal'!$N:$N,"nee") | F4: =$D4+SUMIFS('J1 Journaal'!$K:$K,'J1 Journaal'!$G:$G,$A4,'J1 Journaal'!$B:$B,"<="&DATE(2026,6,30),'J1 Journaal'!$N:$N,"nee")-SUMIFS('J1 Journaal'!$L:$L,'J1 Journaal'!$G:$G,$A4,'J1 Journaal'!$B:$B,"<="&DATE(2026,6,30),'J1 Journaal'!$N:$N,"nee") | G4: =$D4+SUMIFS('J1 Journaal'!$K:$K,'J1 Journaal'!$G:$G,$A4,'J1 Journaal'!$B:$B,"<="&DATE(2026,9,30),'J1 Journaal'!$N:$N,"nee")-SUMIFS('J1 Journaal'!$L:$L,'J1 Journaal'!$G:$G,$A4,'J1 Journaal'!$B:$B,"<="&DATE(2026,9,30),'J1 Journaal'!$N:$N,"nee") | H4: =$D4+SUMIFS('J1 Journaal'!$K:$K,'J1 Journaal'!$G:$G,$A4,'J1 Journaal'!$B:$B,"<="&DATE(2026,12,31),'J1 Journaal'!$N:$N,"nee")-SUMIFS('J1 Journaal'!$L:$L,'J1 Journaal'!$G:$G,$A4,'J1 Journaal'!$B:$B,"<="&DATE(2026,12,31),'J1 Journaal'!$N:$N,"nee") | I4: =$D4+SUMIFS('J1 Journaal'!$K:$K,'J1 Journaal'!$G:$G,$A4)-SUMIFS('J1 Journaal'!$L:$L,'J1 Journaal'!$G:$G,$A4)
A5: 173000 | B5: Schulden aan kredietinstellingen | C5: P | D5: 0 | E5: =$D5+SUMIFS('J1 Journaal'!$K:$K,'J1 Journaal'!$G:$G,$A5,'J1 Journaal'!$B:$B,"<="&DATE(2026,3,31),'J1 Journaal'!$N:$N,"nee")-SUMIFS('J1 Journaal'!$L:$L,'J1 Journaal'!$G:$G,$A5,'J1 Journaal'!$B:$B,"<="&DATE(2026,3,31),'J1 Journaal'!$N:$N,"nee") | F5: =$D5+SUMIFS('J1 Journaal'!$K:$K,'J1 Journaal'!$G:$G,$A5,'J1 Journaal'!$B:$B,"<="&DATE(2026,6,30),'J1 Journaal'!$N:$N,"nee")-SUMIFS('J1 Journaal'!$L:$L,'J1 Journaal'!$G:$G,$A5,'J1 Journaal'!$B:$B,"<="&DATE(2026,6,30),'J1 Journaal'!$N:$N,"nee") | G5: =$D5+SUMIFS('J1 Journaal'!$K:$K,'J1 Journaal'!$G:$G,$A5,'J1 Journaal'!$B:$B,"<="&DATE(2026,9,30),'J1 Journaal'!$N:$N,"nee")-SUMIFS('J1 Journaal'!$L:$L,'J1 Journaal'!$G:$G,$A5,'J1 Journaal'!$B:$B,"<="&DATE(2026,9,30),'J1 Journaal'!$N:$N,"nee") | H5: =$D5+SUMIFS('J1 Journaal'!$K:$K,'J1 Journaal'!$G:$G,$A5,'J1 Journaal'!$B:$B,"<="&DATE(2026,12,31),'J1 Journaal'!$N:$N,"nee")-SUMIFS('J1 Journaal'!$L:$L,'J1 Journaal'!$G:$G,$A5,'J1 Journaal'!$B:$B,"<="&DATE(2026,12,31),'J1 Journaal'!$N:$N,"nee") | I5: =$D5+SUMIFS('J1 Journaal'!$K:$K,'J1 Journaal'!$G:$G,$A5)-SUMIFS('J1 Journaal'!$L:$L,'J1 Journaal'!$G:$G,$A5)
A6: 221000 | B6: Gebouwen | C6: A | D6: 0 | E6: =$D6+SUMIFS('J1 Journaal'!$K:$K,'J1 Journaal'!$G:$G,$A6,'J1 Journaal'!$B:$B,"<="&DATE(2026,3,31),'J1 Journaal'!$N:$N,"nee")-SUMIFS('J1 Journaal'!$L:$L,'J1 Journaal'!$G:$G,$A6,'J1 Journaal'!$B:$B,"<="&DATE(2026,3,31),'J1 Journaal'!$N:$N,"nee") | F6: =$D6+SUMIFS('J1 Journaal'!$K:$K,'J1 Journaal'!$G:$G,$A6,'J1 Journaal'!$B:$B,"<="&DATE(2026,6,30),'J1 Journaal'!$N:$N,"nee")-SUMIFS('J1 Journaal'!$L:$L,'J1 Journaal'!$G:$G,$A6,'J1 Journaal'!$B:$B,"<="&DATE(2026,6,30),'J1 Journaal'!$N:$N,"nee") | G6: =$D6+SUMIFS('J1 Journaal'!$K:$K,'J1 Journaal'!$G:$G,$A6,'J1 Journaal'!$B:$B,"<="&DATE(2026,9,30),'J1 Journaal'!$N:$N,"nee")-SUMIFS('J1 Journaal'!$L:$L,'J1 Journaal'!$G:$G,$A6,'J1 Journaal'!$B:$B,"<="&DATE(2026,9,30),'J1 Journaal'!$N:$N,"nee") | H6: =$D6+SUMIFS('J1 Journaal'!$K:$K,'J1 Journaal'!$G:$G,$A6,'J1 Journaal'!$B:$B,"<="&DATE(2026,12,31),'J1 Journaal'!$N:$N,"nee")-SUMIFS('J1 Journaal'!$L:$L,'J1 Journaal'!$G:$G,$A6,'J1 Journaal'!$B:$B,"<="&DATE(2026,12,31),'J1 Journaal'!$N:$N,"nee") | I6: =$D6+SUMIFS('J1 Journaal'!$K:$K,'J1 Journaal'!$G:$G,$A6)-SUMIFS('J1 Journaal'!$L:$L,'J1 Journaal'!$G:$G,$A6)
A7: 221009 | B7: Afschrijvingen op gebouwen (-) | C7: A | D7: 0 | E7: =$D7+SUMIFS('J1 Journaal'!$K:$K,'J1 Journaal'!$G:$G,$A7,'J1 Journaal'!$B:$B,"<="&DATE(2026,3,31),'J1 Journaal'!$N:$N,"nee")-SUMIFS('J1 Journaal'!$L:$L,'J1 Journaal'!$G:$G,$A7,'J1 Journaal'!$B:$B,"<="&DATE(2026,3,31),'J1 Journaal'!$N:$N,"nee") | F7: =$D7+SUMIFS('J1 Journaal'!$K:$K,'J1 Journaal'!$G:$G,$A7,'J1 Journaal'!$B:$B,"<="&DATE(2026,6,30),'J1 Journaal'!$N:$N,"nee")-SUMIFS('J1 Journaal'!$L:$L,'J1 Journaal'!$G:$G,$A7,'J1 Journaal'!$B:$B,"<="&DATE(2026,6,30),'J1 Journaal'!$N:$N,"nee") | G7: =$D7+SUMIFS('J1 Journaal'!$K:$K,'J1 Journaal'!$G:$G,$A7,'J1 Journaal'!$B:$B,"<="&DATE(2026,9,30),'J1 Journaal'!$N:$N,"nee")-SUMIFS('J1 Journaal'!$L:$L,'J1 Journaal'!$G:$G,$A7,'J1 Journaal'!$B:$B,"<="&DATE(2026,9,30),'J1 Journaal'!$N:$N,"nee") | H7: =$D7+SUMIFS('J1 Journaal'!$K:$K,'J1 Journaal'!$G:$G,$A7,'J1 Journaal'!$B:$B,"<="&DATE(2026,12,31),'J1 Journaal'!$N:$N,"nee")-SUMIFS('J1 Journaal'!$L:$L,'J1 Journaal'!$G:$G,$A7,'J1 Journaal'!$B:$B,"<="&DATE(2026,12,31),'J1 Journaal'!$N:$N,"nee") | I7: =$D7+SUMIFS('J1 Journaal'!$K:$K,'J1 Journaal'!$G:$G,$A7)-SUMIFS('J1 Journaal'!$L:$L,'J1 Journaal'!$G:$G,$A7)
A8: 230000 | B8: Installaties | C8: A | D8: 0 | E8: =$D8+SUMIFS('J1 Journaal'!$K:$K,'J1 Journaal'!$G:$G,$A8,'J1 Journaal'!$B:$B,"<="&DATE(2026,3,31),'J1 Journaal'!$N:$N,"nee")-SUMIFS('J1 Journaal'!$L:$L,'J1 Journaal'!$G:$G,$A8,'J1 Journaal'!$B:$B,"<="&DATE(2026,3,31),'J1 Journaal'!$N:$N,"nee") | F8: =$D8+SUMIFS('J1 Journaal'!$K:$K,'J1 Journaal'!$G:$G,$A8,'J1 Journaal'!$B:$B,"<="&DATE(2026,6,30),'J1 Journaal'!$N:$N,"nee")-SUMIFS('J1 Journaal'!$L:$L,'J1 Journaal'!$G:$G,$A8,'J1 Journaal'!$B:$B,"<="&DATE(2026,6,30),'J1 Journaal'!$N:$N,"nee") | G8: =$D8+SUMIFS('J1 Journaal'!$K:$K,'J1 Journaal'!$G:$G,$A8,'J1 Journaal'!$B:$B,"<="&DATE(2026,9,30),'J1 Journaal'!$N:$N,"nee")-SUMIFS('J1 Journaal'!$L:$L,'J1 Journaal'!$G:$G,$A8,'J1 Journaal'!$B:$B,"<="&DATE(2026,9,30),'J1 Journaal'!$N:$N,"nee") | H8: =$D8+SUMIFS('J1 Journaal'!$K:$K,'J1 Journaal'!$G:$G,$A8,'J1 Journaal'!$B:$B,"<="&DATE(2026,12,31),'J1 Journaal'!$N:$N,"nee")-SUMIFS('J1 Journaal'!$L:$L,'J1 Journaal'!$G:$G,$A8,'J1 Journaal'!$B:$B,"<="&DATE(2026,12,31),'J1 Journaal'!$N:$N,"nee") | I8: =$D8+SUMIFS('J1 Journaal'!$K:$K,'J1 Journaal'!$G:$G,$A8)-SUMIFS('J1 Journaal'!$L:$L,'J1 Journaal'!$G:$G,$A8)
A9: 230009 | B9: Afschrijvingen op installaties (-) | C9: A | D9: 0 | E9: =$D9+SUMIFS('J1 Journaal'!$K:$K,'J1 Journaal'!$G:$G,$A9,'J1 Journaal'!$B:$B,"<="&DATE(2026,3,31),'J1 Journaal'!$N:$N,"nee")-SUMIFS('J1 Journaal'!$L:$L,'J1 Journaal'!$G:$G,$A9,'J1 Journaal'!$B:$B,"<="&DATE(2026,3,31),'J1 Journaal'!$N:$N,"nee") | F9: =$D9+SUMIFS('J1 Journaal'!$K:$K,'J1 Journaal'!$G:$G,$A9,'J1 Journaal'!$B:$B,"<="&DATE(2026,6,30),'J1 Journaal'!$N:$N,"nee")-SUMIFS('J1 Journaal'!$L:$L,'J1 Journaal'!$G:$G,$A9,'J1 Journaal'!$B:$B,"<="&DATE(2026,6,30),'J1 Journaal'!$N:$N,"nee") | G9: =$D9+SUMIFS('J1 Journaal'!$K:$K,'J1 Journaal'!$G:$G,$A9,'J1 Journaal'!$B:$B,"<="&DATE(2026,9,30),'J1 Journaal'!$N:$N,"nee")-SUMIFS('J1 Journaal'!$L:$L,'J1 Journaal'!$G:$G,$A9,'J1 Journaal'!$B:$B,"<="&DATE(2026,9,30),'J1 Journaal'!$N:$N,"nee") | H9: =$D9+SUMIFS('J1 Journaal'!$K:$K,'J1 Journaal'!$G:$G,$A9,'J1 Journaal'!$B:$B,"<="&DATE(2026,12,31),'J1 Journaal'!$N:$N,"nee")-SUMIFS('J1 Journaal'!$L:$L,'J1 Journaal'!$G:$G,$A9,'J1 Journaal'!$B:$B,"<="&DATE(2026,12,31),'J1 Journaal'!$N:$N,"nee") | I9: =$D9+SUMIFS('J1 Journaal'!$K:$K,'J1 Journaal'!$G:$G,$A9)-SUMIFS('J1 Journaal'!$L:$L,'J1 Journaal'!$G:$G,$A9)
A10: 232000 | B10: Uitrusting | C10: A | D10: 0 | E10: =$D10+SUMIFS('J1 Journaal'!$K:$K,'J1 Journaal'!$G:$G,$A10,'J1 Journaal'!$B:$B,"<="&DATE(2026,3,31),'J1 Journaal'!$N:$N,"nee")-SUMIFS('J1 Journaal'!$L:$L,'J1 Journaal'!$G:$G,$A10,'J1 Journaal'!$B:$B,"<="&DATE(2026,3,31),'J1 Journaal'!$N:$N,"nee") | F10: =$D10+SUMIFS('J1 Journaal'!$K:$K,'J1 Journaal'!$G:$G,$A10,'J1 Journaal'!$B:$B,"<="&DATE(2026,6,30),'J1 Journaal'!$N:$N,"nee")-SUMIFS('J1 Journaal'!$L:$L,'J1 Journaal'!$G:$G,$A10,'J1 Journaal'!$B:$B,"<="&DATE(2026,6,30),'J1 Journaal'!$N:$N,"nee") | G10: =$D10+SUMIFS('J1 Journaal'!$K:$K,'J1 Journaal'!$G:$G,$A10,'J1 Journaal'!$B:$B,"<="&DATE(2026,9,30),'J1 Journaal'!$N:$N,"nee")-SUMIFS('J1 Journaal'!$L:$L,'J1 Journaal'!$G:$G,$A10,'J1 Journaal'!$B:$B,"<="&DATE(2026,9,30),'J1 Journaal'!$N:$N,"nee") | H10: =$D10+SUMIFS('J1 Journaal'!$K:$K,'J1 Journaal'!$G:$G,$A10,'J1 Journaal'!$B:$B,"<="&DATE(2026,12,31),'J1 Journaal'!$N:$N,"nee")-SUMIFS('J1 Journaal'!$L:$L,'J1 Journaal'!$G:$G,$A10,'J1 Journaal'!$B:$B,"<="&DATE(2026,12,31),'J1 Journaal'!$N:$N,"nee") | I10: =$D10+SUMIFS('J1 Journaal'!$K:$K,'J1 Journaal'!$G:$G,$A10)-SUMIFS('J1 Journaal'!$L:$L,'J1 Journaal'!$G:$G,$A10)
A11: 232009 | B11: Afschrijvingen op uitrusting (-) | C11: A | D11: 0 | E11: =$D11+SUMIFS('J1 Journaal'!$K:$K,'J1 Journaal'!$G:$G,$A11,'J1 Journaal'!$B:$B,"<="&DATE(2026,3,31),'J1 Journaal'!$N:$N,"nee")-SUMIFS('J1 Journaal'!$L:$L,'J1 Journaal'!$G:$G,$A11,'J1 Journaal'!$B:$B,"<="&DATE(2026,3,31),'J1 Journaal'!$N:$N,"nee") | F11: =$D11+SUMIFS('J1 Journaal'!$K:$K,'J1 Journaal'!$G:$G,$A11,'J1 Journaal'!$B:$B,"<="&DATE(2026,6,30),'J1 Journaal'!$N:$N,"nee")-SUMIFS('J1 Journaal'!$L:$L,'J1 Journaal'!$G:$G,$A11,'J1 Journaal'!$B:$B,"<="&DATE(2026,6,30),'J1 Journaal'!$N:$N,"nee") | G11: =$D11+SUMIFS('J1 Journaal'!$K:$K,'J1 Journaal'!$G:$G,$A11,'J1 Journaal'!$B:$B,"<="&DATE(2026,9,30),'J1 Journaal'!$N:$N,"nee")-SUMIFS('J1 Journaal'!$L:$L,'J1 Journaal'!$G:$G,$A11,'J1 Journaal'!$B:$B,"<="&DATE(2026,9,30),'J1 Journaal'!$N:$N,"nee") | H11: =$D11+SUMIFS('J1 Journaal'!$K:$K,'J1 Journaal'!$G:$G,$A11,'J1 Journaal'!$B:$B,"<="&DATE(2026,12,31),'J1 Journaal'!$N:$N,"nee")-SUMIFS('J1 Journaal'!$L:$L,'J1 Journaal'!$G:$G,$A11,'J1 Journaal'!$B:$B,"<="&DATE(2026,12,31),'J1 Journaal'!$N:$N,"nee") | I11: =$D11+SUMIFS('J1 Journaal'!$K:$K,'J1 Journaal'!$G:$G,$A11)-SUMIFS('J1 Journaal'!$L:$L,'J1 Journaal'!$G:$G,$A11)
A12: 240000 | B12: Meubilair | C12: A | D12: 0 | E12: =$D12+SUMIFS('J1 Journaal'!$K:$K,'J1 Journaal'!$G:$G,$A12,'J1 Journaal'!$B:$B,"<="&DATE(2026,3,31),'J1 Journaal'!$N:$N,"nee")-SUMIFS('J1 Journaal'!$L:$L,'J1 Journaal'!$G:$G,$A12,'J1 Journaal'!$B:$B,"<="&DATE(2026,3,31),'J1 Journaal'!$N:$N,"nee") | F12: =$D12+SUMIFS('J1 Journaal'!$K:$K,'J1 Journaal'!$G:$G,$A12,'J1 Journaal'!$B:$B,"<="&DATE(2026,6,30),'J1 Journaal'!$N:$N,"nee")-SUMIFS('J1 Journaal'!$L:$L,'J1 Journaal'!$G:$G,$A12,'J1 Journaal'!$B:$B,"<="&DATE(2026,6,30),'J1 Journaal'!$N:$N,"nee") | G12: =$D12+SUMIFS('J1 Journaal'!$K:$K,'J1 Journaal'!$G:$G,$A12,'J1 Journaal'!$B:$B,"<="&DATE(2026,9,30),'J1 Journaal'!$N:$N,"nee")-SUMIFS('J1 Journaal'!$L:$L,'J1 Journaal'!$G:$G,$A12,'J1 Journaal'!$B:$B,"<="&DATE(2026,9,30),'J1 Journaal'!$N:$N,"nee") | H12: =$D12+SUMIFS('J1 Journaal'!$K:$K,'J1 Journaal'!$G:$G,$A12,'J1 Journaal'!$B:$B,"<="&DATE(2026,12,31),'J1 Journaal'!$N:$N,"nee")-SUMIFS('J1 Journaal'!$L:$L,'J1 Journaal'!$G:$G,$A12,'J1 Journaal'!$B:$B,"<="&DATE(2026,12,31),'J1 Journaal'!$N:$N,"nee") | I12: =$D12+SUMIFS('J1 Journaal'!$K:$K,'J1 Journaal'!$G:$G,$A12)-SUMIFS('J1 Journaal'!$L:$L,'J1 Journaal'!$G:$G,$A12)
A13: 240009 | B13: Afschrijvingen op meubilair (-) | C13: A | D13: 0 | E13: =$D13+SUMIFS('J1 Journaal'!$K:$K,'J1 Journaal'!$G:$G,$A13,'J1 Journaal'!$B:$B,"<="&DATE(2026,3,31),'J1 Journaal'!$N:$N,"nee")-SUMIFS('J1 Journaal'!$L:$L,'J1 Journaal'!$G:$G,$A13,'J1 Journaal'!$B:$B,"<="&DATE(2026,3,31),'J1 Journaal'!$N:$N,"nee") | F13: =$D13+SUMIFS('J1 Journaal'!$K:$K,'J1 Journaal'!$G:$G,$A13,'J1 Journaal'!$B:$B,"<="&DATE(2026,6,30),'J1 Journaal'!$N:$N,"nee")-SUMIFS('J1 Journaal'!$L:$L,'J1 Journaal'!$G:$G,$A13,'J1 Journaal'!$B:$B,"<="&DATE(2026,6,30),'J1 Journaal'!$N:$N,"nee") | G13: =$D13+SUMIFS('J1 Journaal'!$K:$K,'J1 Journaal'!$G:$G,$A13,'J1 Journaal'!$B:$B,"<="&DATE(2026,9,30),'J1 Journaal'!$N:$N,"nee")-SUMIFS('J1 Journaal'!$L:$L,'J1 Journaal'!$G:$G,$A13,'J1 Journaal'!$B:$B,"<="&DATE(2026,9,30),'J1 Journaal'!$N:$N,"nee") | H13: =$D13+SUMIFS('J1 Journaal'!$K:$K,'J1 Journaal'!$G:$G,$A13,'J1 Journaal'!$B:$B,"<="&DATE(2026,12,31),'J1 Journaal'!$N:$N,"nee")-SUMIFS('J1 Journaal'!$L:$L,'J1 Journaal'!$G:$G,$A13,'J1 Journaal'!$B:$B,"<="&DATE(2026,12,31),'J1 Journaal'!$N:$N,"nee") | I13: =$D13+SUMIFS('J1 Journaal'!$K:$K,'J1 Journaal'!$G:$G,$A13)-SUMIFS('J1 Journaal'!$L:$L,'J1 Journaal'!$G:$G,$A13)
... A58: 793000 | B58: Over te dragen verlies | C58: O | D58: 0 | E58: =$D58+SUMIFS('J1 Journaal'!$K:$K,'J1 Journaal'!$G:$G,$A58,'J1 Journaal'!$B:$B,"<="&DATE(2026,3,31),'J1 Journaal'!$N:$N,"nee")-SUMIFS('J1 Journaal'!$L:$L,'J1 Journaal'!$G:$G,$A58,'J1 Journaal'!$B:$B,"<="&DATE(2026,3,31),'J1 Journaal'!$N:$N,"nee") | F58: =$D58+SUMIFS('J1 Journaal'!$K:$K,'J1 Journaal'!$G:$G,$A58,'J1 Journaal'!$B:$B,"<="&DATE(2026,6,30),'J1 Journaal'!$N:$N,"nee")-SUMIFS('J1 Journaal'!$L:$L,'J1 Journaal'!$G:$G,$A58,'J1 Journaal'!$B:$B,"<="&DATE(2026,6,30),'J1 Journaal'!$N:$N,"nee") | G58: =$D58+SUMIFS('J1 Journaal'!$K:$K,'J1 Journaal'!$G:$G,$A58,'J1 Journaal'!$B:$B,"<="&DATE(2026,9,30),'J1 Journaal'!$N:$N,"nee")-SUMIFS('J1 Journaal'!$L:$L,'J1 Journaal'!$G:$G,$A58,'J1 Journaal'!$B:$B,"<="&DATE(2026,9,30),'J1 Journaal'!$N:$N,"nee") | H58: =$D58+SUMIFS('J1 Journaal'!$K:$K,'J1 Journaal'!$G:$G,$A58,'J1 Journaal'!$B:$B,"<="&DATE(2026,12,31),'J1 Journaal'!$N:$N,"nee")-SUMIFS('J1 Journaal'!$L:$L,'J1 Journaal'!$G:$G,$A58,'J1 Journaal'!$B:$B,"<="&DATE(2026,12,31),'J1 Journaal'!$N:$N,"nee") | I58: =$D58+SUMIFS('J1 Journaal'!$K:$K,'J1 Journaal'!$G:$G,$A58)-SUMIFS('J1 Journaal'!$L:$L,'J1 Journaal'!$G:$G,$A58)
B59: TOTAAL (moet 0 zijn) | D59: =ROUND(SUM(D2:D58),2) | E59: =ROUND(SUM(E2:E58),2) | F59: =ROUND(SUM(F2:F58),2) | G59: =ROUND(SUM(G2:G58),2) | H59: =ROUND(SUM(H2:H58),2) | I59: =ROUND(SUM(I2:I58),2)
B61: Resultaat (opbrengsten - kosten) vóór afsluiting | H61: =-SUMIFS(H2:H58,C2:C58,"K")-SUMIFS(H2:H58,C2:C58,"O")

Sheet J1 Voorraad
A1: Artikel | B1: Omschrijving | C1: Begin | D1: + aankopen | E1: - retours aankoop | F1: - verkopen (factuur) | G1: + retours verkoop | H1: - dagontvangsten | I1: Inventaris 31/12 | J1: Aankoopprijs | K1: Waarde inventaris
A2: STAD | B2: Stadsfiets City, 7 versnellingen | C2: 5 | D2: =SUMIFS('J1 Lijnen'!$H:$H,'J1 Lijnen'!$F:$F,$A2,'J1 Lijnen'!$C:$C,"AK") | E2: =SUMIFS('J1 Lijnen'!$H:$H,'J1 Lijnen'!$F:$F,$A2,'J1 Lijnen'!$C:$C,"CN-AK") | F2: =SUMIFS('J1 Lijnen'!$H:$H,'J1 Lijnen'!$F:$F,$A2,'J1 Lijnen'!$C:$C,"VK") | G2: =SUMIFS('J1 Lijnen'!$H:$H,'J1 Lijnen'!$F:$F,$A2,'J1 Lijnen'!$C:$C,"CN-VK") | H2: =SUMIFS('J1 Lijnen'!$H:$H,'J1 Lijnen'!$F:$F,$A2,'J1 Lijnen'!$C:$C,"DO") | I2: =C2+D2-E2-F2+G2-H2 | J2: =INDEX(Artikelen!$D$2:$D$10,MATCH(A2,Artikelen!$A$2:$A$10,0)) | K2: =I2*J2
A3: EBIKE | B3: E-bike Comfort, 500 Wh | C3: 0 | D3: =SUMIFS('J1 Lijnen'!$H:$H,'J1 Lijnen'!$F:$F,$A3,'J1 Lijnen'!$C:$C,"AK") | E3: =SUMIFS('J1 Lijnen'!$H:$H,'J1 Lijnen'!$F:$F,$A3,'J1 Lijnen'!$C:$C,"CN-AK") | F3: =SUMIFS('J1 Lijnen'!$H:$H,'J1 Lijnen'!$F:$F,$A3,'J1 Lijnen'!$C:$C,"VK") | G3: =SUMIFS('J1 Lijnen'!$H:$H,'J1 Lijnen'!$F:$F,$A3,'J1 Lijnen'!$C:$C,"CN-VK") | H3: =SUMIFS('J1 Lijnen'!$H:$H,'J1 Lijnen'!$F:$F,$A3,'J1 Lijnen'!$C:$C,"DO") | I3: =C3+D3-E3-F3+G3-H3 | J3: =INDEX(Artikelen!$D$2:$D$10,MATCH(A3,Artikelen!$A$2:$A$10,0)) | K3: =I3*J3
A4: BAK | B4: Bakfiets Cargo, 2 wielen | C4: 0 | D4: =SUMIFS('J1 Lijnen'!$H:$H,'J1 Lijnen'!$F:$F,$A4,'J1 Lijnen'!$C:$C,"AK") | E4: =SUMIFS('J1 Lijnen'!$H:$H,'J1 Lijnen'!$F:$F,$A4,'J1 Lijnen'!$C:$C,"CN-AK") | F4: =SUMIFS('J1 Lijnen'!$H:$H,'J1 Lijnen'!$F:$F,$A4,'J1 Lijnen'!$C:$C,"VK") | G4: =SUMIFS('J1 Lijnen'!$H:$H,'J1 Lijnen'!$F:$F,$A4,'J1 Lijnen'!$C:$C,"CN-VK") | H4: =SUMIFS('J1 Lijnen'!$H:$H,'J1 Lijnen'!$F:$F,$A4,'J1 Lijnen'!$C:$C,"DO") | I4: =C4+D4-E4-F4+G4-H4 | J4: =INDEX(Artikelen!$D$2:$D$10,MATCH(A4,Artikelen!$A$2:$A$10,0)) | K4: =I4*J4
A5: KIND | B5: Kinderfiets 20 inch | C5: 0 | D5: =SUMIFS('J1 Lijnen'!$H:$H,'J1 Lijnen'!$F:$F,$A5,'J1 Lijnen'!$C:$C,"AK") | E5: =SUMIFS('J1 Lijnen'!$H:$H,'J1 Lijnen'!$F:$F,$A5,'J1 Lijnen'!$C:$C,"CN-AK") | F5: =SUMIFS('J1 Lijnen'!$H:$H,'J1 Lijnen'!$F:$F,$A5,'J1 Lijnen'!$C:$C,"VK") | G5: =SUMIFS('J1 Lijnen'!$H:$H,'J1 Lijnen'!$F:$F,$A5,'J1 Lijnen'!$C:$C,"CN-VK") | H5: =SUMIFS('J1 Lijnen'!$H:$H,'J1 Lijnen'!$F:$F,$A5,'J1 Lijnen'!$C:$C,"DO") | I5: =C5+D5-E5-F5+G5-H5 | J5: =INDEX(Artikelen!$D$2:$D$10,MATCH(A5,Artikelen!$A$2:$A$10,0)) | K5: =I5*J5
A6: HELM | B6: Fietshelm Urban | C6: 10 | D6: =SUMIFS('J1 Lijnen'!$H:$H,'J1 Lijnen'!$F:$F,$A6,'J1 Lijnen'!$C:$C,"AK") | E6: =SUMIFS('J1 Lijnen'!$H:$H,'J1 Lijnen'!$F:$F,$A6,'J1 Lijnen'!$C:$C,"CN-AK") | F6: =SUMIFS('J1 Lijnen'!$H:$H,'J1 Lijnen'!$F:$F,$A6,'J1 Lijnen'!$C:$C,"VK") | G6: =SUMIFS('J1 Lijnen'!$H:$H,'J1 Lijnen'!$F:$F,$A6,'J1 Lijnen'!$C:$C,"CN-VK") | H6: =SUMIFS('J1 Lijnen'!$H:$H,'J1 Lijnen'!$F:$F,$A6,'J1 Lijnen'!$C:$C,"DO") | I6: =C6+D6-E6-F6+G6-H6 | J6: =INDEX(Artikelen!$D$2:$D$10,MATCH(A6,Artikelen!$A$2:$A$10,0)) | K6: =I6*J6
A7: SLOT | B7: Plooislot | C7: 20 | D7: =SUMIFS('J1 Lijnen'!$H:$H,'J1 Lijnen'!$F:$F,$A7,'J1 Lijnen'!$C:$C,"AK") | E7: =SUMIFS('J1 Lijnen'!$H:$H,'J1 Lijnen'!$F:$F,$A7,'J1 Lijnen'!$C:$C,"CN-AK") | F7: =SUMIFS('J1 Lijnen'!$H:$H,'J1 Lijnen'!$F:$F,$A7,'J1 Lijnen'!$C:$C,"VK") | G7: =SUMIFS('J1 Lijnen'!$H:$H,'J1 Lijnen'!$F:$F,$A7,'J1 Lijnen'!$C:$C,"CN-VK") | H7: =SUMIFS('J1 Lijnen'!$H:$H,'J1 Lijnen'!$F:$F,$A7,'J1 Lijnen'!$C:$C,"DO") | I7: =C7+D7-E7-F7+G7-H7 | J7: =INDEX(Artikelen!$D$2:$D$10,MATCH(A7,Artikelen!$A$2:$A$10,0)) | K7: =I7*J7
A8: BAND | B8: Buitenband 28 inch | C8: 20 | D8: =SUMIFS('J1 Lijnen'!$H:$H,'J1 Lijnen'!$F:$F,$A8,'J1 Lijnen'!$C:$C,"AK") | E8: =SUMIFS('J1 Lijnen'!$H:$H,'J1 Lijnen'!$F:$F,$A8,'J1 Lijnen'!$C:$C,"CN-AK") | F8: =SUMIFS('J1 Lijnen'!$H:$H,'J1 Lijnen'!$F:$F,$A8,'J1 Lijnen'!$C:$C,"VK") | G8: =SUMIFS('J1 Lijnen'!$H:$H,'J1 Lijnen'!$F:$F,$A8,'J1 Lijnen'!$C:$C,"CN-VK") | H8: =SUMIFS('J1 Lijnen'!$H:$H,'J1 Lijnen'!$F:$F,$A8,'J1 Lijnen'!$C:$C,"DO") | I8: =C8+D8-E8-F8+G8-H8 | J8: =INDEX(Artikelen!$D$2:$D$10,MATCH(A8,Artikelen!$A$2:$A$10,0)) | K8: =I8*J8
A9: KET | B9: Fietsketting 8 speed | C9: 0 | D9: =SUMIFS('J1 Lijnen'!$H:$H,'J1 Lijnen'!$F:$F,$A9,'J1 Lijnen'!$C:$C,"AK") | E9: =SUMIFS('J1 Lijnen'!$H:$H,'J1 Lijnen'!$F:$F,$A9,'J1 Lijnen'!$C:$C,"CN-AK") | F9: =SUMIFS('J1 Lijnen'!$H:$H,'J1 Lijnen'!$F:$F,$A9,'J1 Lijnen'!$C:$C,"VK") | G9: =SUMIFS('J1 Lijnen'!$H:$H,'J1 Lijnen'!$F:$F,$A9,'J1 Lijnen'!$C:$C,"CN-VK") | H9: =SUMIFS('J1 Lijnen'!$H:$H,'J1 Lijnen'!$F:$F,$A9,'J1 Lijnen'!$C:$C,"DO") | I9: =C9+D9-E9-F9+G9-H9 | J9: =INDEX(Artikelen!$D$2:$D$10,MATCH(A9,Artikelen!$A$2:$A$10,0)) | K9: =I9*J9
A10: LAMP | B10: Verlichtingsset LED | C10: 0 | D10: =SUMIFS('J1 Lijnen'!$H:$H,'J1 Lijnen'!$F:$F,$A10,'J1 Lijnen'!$C:$C,"AK") | E10: =SUMIFS('J1 Lijnen'!$H:$H,'J1 Lijnen'!$F:$F,$A10,'J1 Lijnen'!$C:$C,"CN-AK") | F10: =SUMIFS('J1 Lijnen'!$H:$H,'J1 Lijnen'!$F:$F,$A10,'J1 Lijnen'!$C:$C,"VK") | G10: =SUMIFS('J1 Lijnen'!$H:$H,'J1 Lijnen'!$F:$F,$A10,'J1 Lijnen'!$C:$C,"CN-VK") | H10: =SUMIFS('J1 Lijnen'!$H:$H,'J1 Lijnen'!$F:$F,$A10,'J1 Lijnen'!$C:$C,"DO") | I10: =C10+D10-E10-F10+G10-H10 | J10: =INDEX(Artikelen!$D$2:$D$10,MATCH(A10,Artikelen!$A$2:$A$10,0)) | K10: =I10*J10
B11: Totaal | K11: =SUM(K2:K10)
B12: Saldo 340000 na afsluiting (proefbalans) | K12: =INDEX('J1 Proefbalans'!I:I,MATCH(340000,'J1 Proefbalans'!A:A,0))
B13: Controle (moet 0 zijn) | K13: =K11-K12

Sheet J2 Lijnen
A1: ID | B1: Documentnr | C1: Soort doc | D1: Lijn | E1: Soort lijn | F1: Artikel | G1: Omschrijving | H1: Aantal | I1: Eenheidsprijs | J1: Bedrag excl. btw | K1: Btw % | L1: Btw
A2: J2A1 | B2: NL-27-01-0311 | C2: AK | D2: 1 | E2: dienst | G2: Internet en telefonie januari-maart 2027 | H2: 1 | I2: 300 | J2: =H2*I2 | K2: 0.21 | L2: =J2*K2
A3: J2A3 | B3: 2027-014 | C3: AK | D3: 1 | E3: artikel | F3: STAD | G3: Stadsfiets City, 7 versnellingen | H3: 10 | I3: 400 | J3: =H3*I3 | K3: 0.21 | L3: =J3*K3
A4: J2A3 | B4: 2027-014 | C4: AK | D4: 2 | E4: artikel | F4: EBIKE | G4: E-bike Comfort, 500 Wh | H4: 5 | I4: 1400 | J4: =H4*I4 | K4: 0.21 | L4: =J4*K4
A5: J2A3 | B5: 2027-014 | C5: AK | D5: 3 | E5: handelskorting | G5: Handelskorting 10% op de goederen | H5: 0.1 | I5: =-SUMIFS(J$3:J4,E$3:E4,"artikel") | J5: =H5*I5 | K5: 0.21 | L5: =J5*K5
A6: J2A5 | B6: HH-27-004 | C6: AK | D6: 1 | E6: artikel | F6: HELM | G6: Fietshelm Urban | H6: 20 | I6: 30 | J6: =H6*I6 | K6: 0.21 | L6: =J6*K6
A7: J2A5 | B7: HH-27-004 | C7: AK | D7: 2 | E7: artikel | F7: SLOT | G7: Plooislot | H7: 10 | I7: 20 | J7: =H7*I7 | K7: 0.21 | L7: =J7*K7
A8: J2A5 | B8: HH-27-004 | C8: AK | D8: 3 | E8: kosten | G8: Transportkosten | H8: 1 | I8: 100 | J8: =H8*I8 | K8: 0.21 | L8: =J8*K8
A9: J2A7 | B9: 2027-031 | C9: AK | D9: 1 | E9: artikel | F9: BAK | G9: Bakfiets Cargo, 2 wielen | H9: 2 | I9: 1800 | J9: =H9*I9 | K9: 0.21 | L9: =J9*K9
A10: J2A7 | B10: 2027-031 | C10: AK | D10: 2 | E10: verpakking | G10: Herbruikbaar fietsrek (waarborg) | H10: 2 | I10: 50 | J10: =H10*I10 | K10: 0 | L10: =J10*K10
A11: J2A9 | B11: 2027-052 | C11: AK | D11: 1 | E11: artikel | F11: STAD | G11: Stadsfiets City, 7 versnellingen | H11: 5 | I11: 400 | J11: =H11*I11 | K11: 0.21 | L11: =J11*K11
A12: J2A9 | B12: 2027-052 | C12: AK | D12: 2 | E12: artikel | F12: BAK | G12: Bakfiets Cargo, 2 wielen | H12: 1 | I12: 1800 | J12: =H12*I12 | K12: 0.21 | L12: =J12*K12
A13: J2A9 | B13: 2027-052 | C13: AK | D13: 3 | E13: artikel | F13: KIND | G13: Kinderfiets 20 inch | H13: 8 | I13: 150 | J13: =H13*I13 | K13: 0.21 | L13: =J13*K13
A14: J2A9 | B14: 2027-052 | C14: AK | D14: 4 | E14: financiële korting | G14: Financiële korting 2% bij betaling binnen 10 dagen (btw berekend na korting) | H14: 0.02 | I14: =-SUMIFS(J$11:J13,E$11:E13,"<>verpakking") | J14: =H14*I14 | K14: 0.21 | L14: =J14*K14
A15: J2CA2 | B15: CN-2027-002 | C15: CN-AK | D15: 1 | E15: artikel | F15: STAD | G15: Stadsfiets City, 7 versnellingen | H15: 5 | I15: 400 | J15: =H15*I15 | K15: 0.21 | L15: =J15*K15
A16: J2CA2 | B16: CN-2027-002 | C16: CN-AK | D16: 2 | E16: handelskorting | G16: Handelskorting 10% op de goederen | H16: 0.1 | I16: =-SUMIFS(J$15:J15,E$15:E15,"artikel") | J16: =H16*I16 | K16: 0.21 | L16: =J16*K16
A17: J2CA3 | B17: CN-2027-009 | C17: CN-AK | D17: 1 | E17: verpakking | G17: Herbruikbaar fietsrek (waarborg) | H17: 2 | I17: 50 | J17: =H17*I17 | K17: 0 | L17: =J17*K17
A18: J2V2 | B18: 2027-002 | C18: VK | D18: 1 | E18: dienst | G18: Onderhoudsbeurt fiets (arbeid) | H18: 10 | I18: 60 | J18: =H18*I18 | K18: 0.06 | L18: =J18*K18
A19: J2V3 | B19: 2027-003 | C19: VK | D19: 1 | E19: artikel | F19: STAD | G19: Stadsfiets City, 7 versnellingen | H19: 10 | I19: 600 | J19: =H19*I19 | K19: 0.21 | L19: =J19*K19
A20: J2V3 | B20: 2027-003 | C20: VK | D20: 2 | E20: handelskorting | G20: Handelskorting 10% op de goederen | H20: 0.1 | I20: =-SUMIFS(J$19:J19,E$19:E19,"artikel") | J20: =H20*I20 | K20: 0.21 | L20: =J20*K20
A21: J2V5 | B21: 2027-005 | C21: VK | D21: 1 | E21: artikel | F21: KIND | G21: Kinderfiets 20 inch | H21: 6 | I21: 250 | J21: =H21*I21 | K21: 0.21 | L21: =J21*K21
A22: J2V5 | B22: 2027-005 | C22: VK | D22: 2 | E22: kosten | G22: Leveringskosten | H22: 1 | I22: 100 | J22: =H22*I22 | K22: 0.21 | L22: =J22*K22
A23: J2V7 | B23: 2027-007 | C23: VK | D23: 1 | E23: artikel | F23: STAD | G23: Stadsfiets City, 7 versnellingen | H23: 6 | I23: 600 | J23: =H23*I23 | K23: 0.21 | L23: =J23*K23
A24: J2V7 | B24: 2027-007 | C24: VK | D24: 2 | E24: verpakking | G24: Herbruikbaar fietsrek (waarborg) | H24: 3 | I24: 50 | J24: =H24*I24 | K24: 0 | L24: =J24*K24
A25: J2V9 | B25: 2027-025 | C25: VK | D25: 1 | E25: artikel | F25: EBIKE | G25: E-bike Comfort, 500 Wh | H25: 1 | I25: 2000 | J25: =H25*I25 | K25: 0.21 | L25: =J25*K25
A26: J2V9 | B26: 2027-025 | C26: VK | D26: 2 | E26: artikel | F26: KIND | G26: Kinderfiets 20 inch | H26: 2 | I26: 250 | J26: =H26*I26 | K26: 0.21 | L26: =J26*K26
A27: J2V9 | B27: 2027-025 | C27: VK | D27: 3 | E27: financiële korting | G27: Financiële korting 4% bij betaling binnen 10 dagen (btw berekend na korting) | H27: 0.04 | I27: =-SUMIFS(J$25:J26,E$25:E26,"<>verpakking") | J27: =H27*I27 | K27: 0.21 | L27: =J27*K27
A28: J2CV2 | B28: CN-2027-002 | C28: CN-VK | D28: 1 | E28: artikel | F28: STAD | G28: Stadsfiets City, 7 versnellingen | H28: 5 | I28: 600 | J28: =H28*I28 | K28: 0.21 | L28: =J28*K28
A29: J2CV2 | B29: CN-2027-002 | C29: CN-VK | D29: 2 | E29: handelskorting | G29: Handelskorting 10% op de goederen | H29: 0.1 | I29: =-SUMIFS(J$28:J28,E$28:E28,"artikel") | J29: =H29*I29 | K29: 0.21 | L29: =J29*K29
A30: J2CV3 | B30: CN-2027-003 | C30: CN-VK | D30: 1 | E30: verpakking | G30: Herbruikbaar fietsrek (waarborg) | H30: 3 | I30: 50 | J30: =H30*I30 | K30: 0 | L30: =J30*K30
A31: J2D1 | B31: DO-2027-01 | C31: DO | D31: 1 | E31: artikel | F31: STAD | G31: Stadsfiets City, 7 versnellingen | H31: 2 | I31: 600 | J31: =H31*I31 | K31: 0.21 | L31: =J31*K31
A32: J2D1 | B32: DO-2027-01 | C32: DO | D32: 2 | E32: artikel | F32: BAND | G32: Buitenband 28 inch | H32: 4 | I32: 25 | J32: =H32*I32 | K32: 0.21 | L32: =J32*K32
A33: J2D1 | B33: DO-2027-01 | C33: DO | D33: 3 | E33: dienst | G33: Herstelling fiets (arbeid) | H33: 6 | I33: 50 | J33: =H33*I33 | K33: 0.06 | L33: =J33*K33
A34: J2Q2A1 | B34: 2027-198 | C34: AK | D34: 1 | E34: artikel | F34: STAD | G34: Stadsfiets City, 7 versnellingen | H34: 15 | I34: 400 | J34: =H34*I34 | K34: 0.21 | L34: =J34*K34
A35: J2Q2A1 | B35: 2027-198 | C35: AK | D35: 2 | E35: verpakking | G35: Herbruikbaar fietsrek (waarborg) | H35: 4 | I35: 50 | J35: =H35*I35 | K35: 0 | L35: =J35*K35
A36: J2Q2A1 | B36: 2027-198 | C36: AK | D36: 3 | E36: handelskorting | G36: Handelskorting 10% op de goederen | H36: 0.1 | I36: =-SUMIFS(J$34:J35,E$34:E35,"artikel") | J36: =H36*I36 | K36: 0.21 | L36: =J36*K36
A37: J2Q2A2 | B37: SK-27-1104 | C37: AK | D37: 1 | E37: dienst | G37: Elektriciteit januari-maart 2027 | H37: 1 | I37: 600 | J37: =H37*I37 | K37: 0.21 | L37: =J37*K37
A38: J2Q2CA1 | B38: CN-2027-021 | C38: CN-AK | D38: 1 | E38: artikel | F38: STAD | G38: Stadsfiets City, 7 versnellingen | H38: 5 | I38: 400 | J38: =H38*I38 | K38: 0.21 | L38: =J38*K38
A39: J2Q2CA1 | B39: CN-2027-021 | C39: CN-AK | D39: 2 | E39: handelskorting | G39: Handelskorting 10% op de goederen | H39: 0.1 | I39: =-SUMIFS(J$38:J38,E$38:E38,"artikel") | J39: =H39*I39 | K39: 0.21 | L39: =J39*K39
A40: J2Q2A4 | B40: HH-27-102 | C40: AK | D40: 1 | E40: artikel | F40: HELM | G40: Fietshelm Urban | H40: 30 | I40: 30 | J40: =H40*I40 | K40: 0.21 | L40: =J40*K40
A41: J2Q2A4 | B41: HH-27-102 | C41: AK | D41: 2 | E41: artikel | F41: SLOT | G41: Plooislot | H41: 5 | I41: 20 | J41: =H41*I41 | K41: 0.21 | L41: =J41*K41
A42: J2Q2A4 | B42: HH-27-102 | C42: AK | D42: 3 | E42: kosten | G42: Transportkosten | H42: 1 | I42: 100 | J42: =H42*I42 | K42: 0.21 | L42: =J42*K42
A43: J2Q2A7 | B43: 2027-244 | C43: AK | D43: 1 | E43: artikel | F43: STAD | G43: Stadsfiets City, 7 versnellingen | H43: 5 | I43: 400 | J43: =H43*I43 | K43: 0.21 | L43: =J43*K43
A44: J2Q2A7 | B44: 2027-244 | C44: AK | D44: 2 | E44: financiële korting | G44: Financiële korting 5% bij betaling binnen 10 dagen (btw berekend na korting) | H44: 0.05 | I44: =-SUMIFS(J$43:J43,E$43:E43,"<>verpakking") | J44: =H44*I44 | K44: 0.21 | L44: =J44*K44
A45: J2Q2A5 | B45: 2027-260 | C45: AK | D45: 1 | E45: artikel | F45: BAK | G45: Bakfiets Cargo, 2 wielen | H45: 1 | I45: 1800 | J45: =H45*I45 | K45: 0.21 | L45: =J45*K45
A46: J2Q2A5 | B46: 2027-260 | C46: AK | D46: 2 | E46: artikel | F46: KIND | G46: Kinderfiets 20 inch | H46: 8 | I46: 150 | J46: =H46*I46 | K46: 0.21 | L46: =J46*K46
A47: J2Q2A5 | B47: 2027-260 | C47: AK | D47: 3 | E47: kosten | G47: Leveringskosten | H47: 1 | I47: 100 | J47: =H47*I47 | K47: 0.21 | L47: =J47*K47
A48: J2Q2A5 | B48: 2027-260 | C48: AK | D48: 4 | E48: verpakking | G48: Herbruikbaar fietsrek (waarborg) | H48: 2 | I48: 50 | J48: =H48*I48 | K48: 0 | L48: =J48*K48
A49: J2Q2A5 | B49: 2027-260 | C49: AK | D49: 5 | E49: handelskorting | G49: Handelskorting 10% op de goederen | H49: 0.1 | I49: =-SUMIFS(J$45:J48,E$45:E48,"artikel") | J49: =H49*I49 | K49: 0.21 | L49: =J49*K49
A50: J2Q2CA2 | B50: CN-2027-030 | C50: CN-AK | D50: 1 | E50: verpakking | G50: Herbruikbaar fietsrek (waarborg) | H50: 4 | I50: 50 | J50: =H50*I50 | K50: 0 | L50: =J50*K50
A51: J2Q2V1 | B51: 2027-009 | C51: VK | D51: 1 | E51: artikel | F51: EBIKE | G51: E-bike Comfort, 500 Wh | H51: 2 | I51: 2000 | J51: =H51*I51 | K51: 0.21 | L51: =J51*K51
A52: J2Q2V1 | B52: 2027-009 | C52: VK | D52: 2 | E52: artikel | F52: HELM | G52: Fietshelm Urban | H52: 4 | I52: 50 | J52: =H52*I52 | K52: 0.21 | L52: =J52*K52
A53: J2Q2V2 | B53: 2027-010 | C53: VK | D53: 1 | E53: artikel | F53: STAD | G53: Stadsfiets City, 7 versnellingen | H53: 10 | I53: 600 | J53: =H53*I53 | K53: 0.21 | L53: =J53*K53
A54: J2Q2V2 | B54: 2027-010 | C54: VK | D54: 2 | E54: handelskorting | G54: Handelskorting 10% op de goederen | H54: 0.1 | I54: =-SUMIFS(J$53:J53,E$53:E53,"artikel") | J54: =H54*I54 | K54: 0.21 | L54: =J54*K54
A55: J2Q2V3 | B55: 2027-011 | C55: VK | D55: 1 | E55: artikel | F55: EBIKE | G55: E-bike Comfort, 500 Wh | H55: 2 | I55: 2000 | J55: =H55*I55 | K55: 0.21 | L55: =J55*K55
A56: J2Q2V3 | B56: 2027-011 | C56: VK | D56: 2 | E56: kosten | G56: Leveringskosten | H56: 1 | I56: 100 | J56: =H56*I56 | K56: 0.21 | L56: =J56*K56
A57: J2Q2V7 | B57: 2027-027 | C57: VK | D57: 1 | E57: artikel | F57: EBIKE | G57: E-bike Comfort, 500 Wh | H57: 1 | I57: 2000 | J57: =H57*I57 | K57: 0.21 | L57: =J57*K57
A58: J2Q2V7 | B58: 2027-027 | C58: VK | D58: 2 | E58: artikel | F58: KIND | G58: Kinderfiets 20 inch | H58: 2 | I58: 250 | J58: =H58*I58 | K58: 0.21 | L58: =J58*K58
A59: J2Q2V7 | B59: 2027-027 | C59: VK | D59: 3 | E59: financiële korting | G59: Financiële korting 4% bij betaling binnen 10 dagen (btw berekend na korting) | H59: 0.04 | I59: =-SUMIFS(J$57:J58,E$57:E58,"<>verpakking") | J59: =H59*I59 | K59: 0.21 | L59: =J59*K59
A60: J2Q2V5 | B60: 2027-013 | C60: VK | D60: 1 | E60: artikel | F60: BAK | G60: Bakfiets Cargo, 2 wielen | H60: 2 | I60: 2600 | J60: =H60*I60 | K60: 0.21 | L60: =J60*K60
A61: J2Q2V5 | B61: 2027-013 | C61: VK | D61: 2 | E61: artikel | F61: KIND | G61: Kinderfiets 20 inch | H61: 4 | I61: 250 | J61: =H61*I61 | K61: 0.21 | L61: =J61*K61
A62: J2Q2V5 | B62: 2027-013 | C62: VK | D62: 3 | E62: kosten | G62: Leveringskosten | H62: 1 | I62: 120 | J62: =H62*I62 | K62: 0.21 | L62: =J62*K62
A63: J2Q2V5 | B63: 2027-013 | C63: VK | D63: 4 | E63: verpakking | G63: Herbruikbaar fietsrek (waarborg) | H63: 2 | I63: 50 | J63: =H63*I63 | K63: 0 | L63: =J63*K63
A64: J2Q2V5 | B64: 2027-013 | C64: VK | D64: 5 | E64: handelskorting | G64: Handelskorting 10% op de goederen | H64: 0.1 | I64: =-SUMIFS(J$60:J63,E$60:E63,"artikel") | J64: =H64*I64 | K64: 0.21 | L64: =J64*K64
A65: J2Q2D1 | B65: DO-2027-03 | C65: DO | D65: 1 | E65: artikel | F65: STAD | G65: Stadsfiets City, 7 versnellingen | H65: 2 | I65: 600 | J65: =H65*I65 | K65: 0.21 | L65: =J65*K65
A66: J2Q2D1 | B66: DO-2027-03 | C66: DO | D66: 2 | E66: artikel | F66: HELM | G66: Fietshelm Urban | H66: 8 | I66: 50 | J66: =H66*I66 | K66: 0.21 | L66: =J66*K66
A67: J2Q2D1 | B67: DO-2027-03 | C67: DO | D67: 3 | E67: artikel | F67: SLOT | G67: Plooislot | H67: 4 | I67: 35 | J67: =H67*I67 | K67: 0.21 | L67: =J67*K67
A68: J2Q2D1 | B68: DO-2027-03 | C68: DO | D68: 4 | E68: artikel | F68: KET | G68: Fietsketting 8 speed | H68: 3 | I68: 20 | J68: =H68*I68 | K68: 0.21 | L68: =J68*K68
A69: J2Q2D1 | B69: DO-2027-03 | C69: DO | D69: 5 | E69: dienst | G69: Herstelling fiets (arbeid) | H69: 10 | I69: 50 | J69: =H69*I69 | K69: 0.06 | L69: =J69*K69
A70: J2Q2CV1 | B70: CN-2027-004 | C70: CN-VK | D70: 1 | E70: artikel | F70: KIND | G70: Kinderfiets 20 inch | H70: 4 | I70: 250 | J70: =H70*I70 | K70: 0.21 | L70: =J70*K70
A71: J2Q2CV1 | B71: CN-2027-004 | C71: CN-VK | D71: 2 | E71: handelskorting | G71: Handelskorting 10% op de goederen | H71: 0.1 | I71: =-SUMIFS(J$70:J70,E$70:E70,"artikel") | J71: =H71*I71 | K71: 0.21 | L71: =J71*K71
A72: J2Q2CV2 | B72: CN-2027-005 | C72: CN-VK | D72: 1 | E72: verpakking | G72: Herbruikbaar fietsrek (waarborg) | H72: 2 | I72: 50 | J72: =H72*I72 | K72: 0 | L72: =J72*K72
A73: J2Q3A1 | B73: 2027-401 | C73: AK | D73: 1 | E73: artikel | F73: STAD | G73: Stadsfiets City, 7 versnellingen | H73: 5 | I73: 400 | J73: =H73*I73 | K73: 0.21 | L73: =J73*K73
A74: J2Q3A1 | B74: 2027-401 | C74: AK | D74: 2 | E74: artikel | F74: BAK | G74: Bakfiets Cargo, 2 wielen | H74: 2 | I74: 1800 | J74: =H74*I74 | K74: 0.21 | L74: =J74*K74
A75: J2Q3A1 | B75: 2027-401 | C75: AK | D75: 3 | E75: artikel | F75: EBIKE | G75: E-bike Comfort, 500 Wh | H75: 1 | I75: 1400 | J75: =H75*I75 | K75: 0.21 | L75: =J75*K75
A76: J2Q3A1 | B76: 2027-401 | C76: AK | D76: 4 | E76: handelskorting | G76: Handelskorting 10% op de goederen | H76: 0.1 | I76: =-SUMIFS(J$73:J75,E$73:E75,"artikel") | J76: =H76*I76 | K76: 0.21 | L76: =J76*K76
A77: J2A2 | B77: GM-2027-119 | C77: AK | D77: 1 | E77: vast actief | G77: Bestelwagen (lichte vracht), elektrisch | H77: 1 | I77: 24000 | J77: =H77*I77 | K77: 0.21 | L77: =J77*K77
A78: J2Q3V1 | B78: 2027-015 | C78: VK | D78: 1 | E78: artikel | F78: STAD | G78: Stadsfiets City, 7 versnellingen | H78: 6 | I78: 600 | J78: =H78*I78 | K78: 0.21 | L78: =J78*K78
A79: J2Q3V1 | B79: 2027-015 | C79: VK | D79: 2 | E79: artikel | F79: HELM | G79: Fietshelm Urban | H79: 8 | I79: 50 | J79: =H79*I79 | K79: 0.21 | L79: =J79*K79
A80: J2Q3V1 | B80: 2027-015 | C80: VK | D80: 3 | E80: handelskorting | G80: Handelskorting 5% op de goederen | H80: 0.05 | I80: =-SUMIFS(J$78:J79,E$78:E79,"artikel") | J80: =H80*I80 | K80: 0.21 | L80: =J80*K80
A81: J2Q3CA1 | B81: CN-2027-044 | C81: CN-AK | D81: 1 | E81: artikel | F81: BAK | G81: Bakfiets Cargo, 2 wielen | H81: 1 | I81: 1800 | J81: =H81*I81 | K81: 0.21 | L81: =J81*K81
A82: J2Q3CA1 | B82: CN-2027-044 | C82: CN-AK | D82: 2 | E82: artikel | F82: STAD | G82: Stadsfiets City, 7 versnellingen | H82: 3 | I82: 400 | J82: =H82*I82 | K82: 0.21 | L82: =J82*K82
A83: J2Q3CA1 | B83: CN-2027-044 | C83: CN-AK | D83: 3 | E83: handelskorting | G83: Handelskorting 10% op de goederen | H83: 0.1 | I83: =-SUMIFS(J$81:J82,E$81:E82,"artikel") | J83: =H83*I83 | K83: 0.21 | L83: =J83*K83
A84: J2Q3CV1 | B84: CN-2027-006 | C84: CN-VK | D84: 1 | E84: artikel | F84: STAD | G84: Stadsfiets City, 7 versnellingen | H84: 3 | I84: 600 | J84: =H84*I84 | K84: 0.21 | L84: =J84*K84
A85: J2Q3CV1 | B85: CN-2027-006 | C85: CN-VK | D85: 2 | E85: artikel | F85: HELM | G85: Fietshelm Urban | H85: 4 | I85: 50 | J85: =H85*I85 | K85: 0.21 | L85: =J85*K85
A86: J2Q3CV1 | B86: CN-2027-006 | C86: CN-VK | D86: 3 | E86: handelskorting | G86: Handelskorting 5% op de goederen | H86: 0.05 | I86: =-SUMIFS(J$84:J85,E$84:E85,"artikel") | J86: =H86*I86 | K86: 0.21 | L86: =J86*K86
A87: J2Q3V2 | B87: 2027-016 | C87: VK | D87: 1 | E87: artikel | F87: STAD | G87: Stadsfiets City, 7 versnellingen | H87: 6 | I87: 600 | J87: =H87*I87 | K87: 0.21 | L87: =J87*K87
A88: J2Q3V2 | B88: 2027-016 | C88: VK | D88: 2 | E88: kosten | G88: Leveringskosten | H88: 1 | I88: 100 | J88: =H88*I88 | K88: 0.21 | L88: =J88*K88
A89: J2Q3V2 | B89: 2027-016 | C89: VK | D89: 3 | E89: verpakking | G89: Herbruikbaar fietsrek (waarborg) | H89: 3 | I89: 50 | J89: =H89*I89 | K89: 0 | L89: =J89*K89
A90: J2Q3A4 | B90: SW-2027-301 | C90: AK | D90: 1 | E90: artikel | F90: BAND | G90: Buitenband 28 inch | H90: 10 | I90: 15 | J90: =H90*I90 | K90: 0.21 | L90: =J90*K90
A91: J2Q3A4 | B91: SW-2027-301 | C91: AK | D91: 2 | E91: artikel | F91: LAMP | G91: Verlichtingsset LED | H91: 10 | I91: 25 | J91: =H91*I91 | K91: 0.21 | L91: =J91*K91
A92: J2Q3A4 | B92: SW-2027-301 | C92: AK | D92: 3 | E92: artikel | F92: KET | G92: Fietsketting 8 speed | H92: 10 | I92: 10 | J92: =H92*I92 | K92: 0.21 | L92: =J92*K92
A93: J2Q3A4 | B93: SW-2027-301 | C93: AK | D93: 4 | E93: verpakking | G93: Transportkrat (waarborg) | H93: 2 | I93: 25 | J93: =H93*I93 | K93: 0 | L93: =J93*K93
A94: J2Q3A6 | B94: 2027-455 | C94: AK | D94: 1 | E94: artikel | F94: STAD | G94: Stadsfiets City, 7 versnellingen | H94: 5 | I94: 400 | J94: =H94*I94 | K94: 0.21 | L94: =J94*K94
A95: J2Q3A6 | B95: 2027-455 | C95: AK | D95: 2 | E95: financiële korting | G95: Financiële korting 5% bij betaling binnen 10 dagen (btw berekend na korting) | H95: 0.05 | I95: =-SUMIFS(J$94:J94,E$94:E94,"<>verpakking") | J95: =H95*I95 | K95: 0.21 | L95: =J95*K95
A96: J2Q3V6 | B96: 2027-028 | C96: VK | D96: 1 | E96: artikel | F96: STAD | G96: Stadsfiets City, 7 versnellingen | H96: 2 | I96: 600 | J96: =H96*I96 | K96: 0.21 | L96: =J96*K96
A97: J2Q3V6 | B97: 2027-028 | C97: VK | D97: 2 | E97: artikel | F97: KIND | G97: Kinderfiets 20 inch | H97: 2 | I97: 250 | J97: =H97*I97 | K97: 0.21 | L97: =J97*K97
A98: J2Q3V6 | B98: 2027-028 | C98: VK | D98: 3 | E98: artikel | F98: HELM | G98: Fietshelm Urban | H98: 6 | I98: 50 | J98: =H98*I98 | K98: 0.21 | L98: =J98*K98
A99: J2Q3V6 | B99: 2027-028 | C99: VK | D99: 4 | E99: financiële korting | G99: Financiële korting 5% bij betaling binnen 10 dagen (btw berekend na korting) | H99: 0.05 | I99: =-SUMIFS(J$96:J98,E$96:E98,"<>verpakking") | J99: =H99*I99 | K99: 0.21 | L99: =J99*K99
A100: J2Q3CA2 | B100: SW-CN-2027-019 | C100: CN-AK | D100: 1 | E100: artikel | F100: LAMP | G100: Verlichtingsset LED | H100: 4 | I100: 25 | J100: =H100*I100 | K100: 0.21 | L100: =J100*K100
...

Sheet J2 Documenten
A1: Volgorde in set | B1: ID | C1: Set | D1: Kwartaal | E1: Soort | F1: Subsoort | G1: Datum | H1: Vervaldag | I1: Documentnr | J1: Van | K1: Aan | L1: Verwijst naar | M1: Reden / omschrijving | N1: MvH 21% | O1: Btw 21% | P1: MvH 6% | Q1: Btw 6% | R1: Waarborg | S1: Fin. korting (niet afgetrokken) | T1: Totaal (te betalen) | U1: Te betalen binnen kortingstermijn | V1: Contant (kas) | W1: Bancontact | X1: Betaald via uittreksel | Y1: Controle D-C | Z1: Opmerking
A2: 1 | B2: J2A1 | C2: K1 | D2: K1 | E2: AK | F2: eenvoudig | G2: 46392 | H2: =G2+30 | I2: NL-27-01-0311 | J2: Netlink bv | K2: Fietsatelier Noor bv | N2: =SUMIFS('J2 Lijnen'!$J:$J,'J2 Lijnen'!$A:$A,$B2,'J2 Lijnen'!$K:$K,0.21,'J2 Lijnen'!$E:$E,"<>verpakking") | O2: =SUMIFS('J2 Lijnen'!$L:$L,'J2 Lijnen'!$A:$A,$B2,'J2 Lijnen'!$K:$K,0.21) | P2: =SUMIFS('J2 Lijnen'!$J:$J,'J2 Lijnen'!$A:$A,$B2,'J2 Lijnen'!$K:$K,0.06) | Q2: =SUMIFS('J2 Lijnen'!$L:$L,'J2 Lijnen'!$A:$A,$B2,'J2 Lijnen'!$K:$K,0.06) | R2: =SUMIFS('J2 Lijnen'!$J:$J,'J2 Lijnen'!$A:$A,$B2,'J2 Lijnen'!$E:$E,"verpakking") | S2: =-SUMIFS('J2 Lijnen'!$J:$J,'J2 Lijnen'!$A:$A,$B2,'J2 Lijnen'!$E:$E,"financiële korting") | T2: =SUM(N2:S2) | X2: U2027-02 | Y2: =SUMIFS('J2 Journaal'!$K:$K,'J2 Journaal'!$E:$E,$B2)-SUMIFS('J2 Journaal'!$L:$L,'J2 Journaal'!$E:$E,$B2)
A3: 2 | B3: J2A3 | C3: K1 | D3: K1 | E3: AK | F3: handelskorting | G3: 46395 | H3: =G3+30 | I3: 2027-014 | J3: Velomax bv | K3: Fietsatelier Noor bv | N3: =SUMIFS('J2 Lijnen'!$J:$J,'J2 Lijnen'!$A:$A,$B3,'J2 Lijnen'!$K:$K,0.21,'J2 Lijnen'!$E:$E,"<>verpakking") | O3: =SUMIFS('J2 Lijnen'!$L:$L,'J2 Lijnen'!$A:$A,$B3,'J2 Lijnen'!$K:$K,0.21) | P3: =SUMIFS('J2 Lijnen'!$J:$J,'J2 Lijnen'!$A:$A,$B3,'J2 Lijnen'!$K:$K,0.06) | Q3: =SUMIFS('J2 Lijnen'!$L:$L,'J2 Lijnen'!$A:$A,$B3,'J2 Lijnen'!$K:$K,0.06) | R3: =SUMIFS('J2 Lijnen'!$J:$J,'J2 Lijnen'!$A:$A,$B3,'J2 Lijnen'!$E:$E,"verpakking") | S3: =-SUMIFS('J2 Lijnen'!$J:$J,'J2 Lijnen'!$A:$A,$B3,'J2 Lijnen'!$E:$E,"financiële korting") | T3: =SUM(N3:S3) | X3: U2027-03 | Y3: =SUMIFS('J2 Journaal'!$K:$K,'J2 Journaal'!$E:$E,$B3)-SUMIFS('J2 Journaal'!$L:$L,'J2 Journaal'!$E:$E,$B3)
A4: 3 | B4: J2A5 | C4: K1 | D4: K1 | E4: AK | F4: kosten | G4: 46399 | H4: =G4+30 | I4: HH-27-004 | J4: HelmHuis bv | K4: Fietsatelier Noor bv | N4: =SUMIFS('J2 Lijnen'!$J:$J,'J2 Lijnen'!$A:$A,$B4,'J2 Lijnen'!$K:$K,0.21,'J2 Lijnen'!$E:$E,"<>verpakking") | O4: =SUMIFS('J2 Lijnen'!$L:$L,'J2 Lijnen'!$A:$A,$B4,'J2 Lijnen'!$K:$K,0.21) | P4: =SUMIFS('J2 Lijnen'!$J:$J,'J2 Lijnen'!$A:$A,$B4,'J2 Lijnen'!$K:$K,0.06) | Q4: =SUMIFS('J2 Lijnen'!$L:$L,'J2 Lijnen'!$A:$A,$B4,'J2 Lijnen'!$K:$K,0.06) | R4: =SUMIFS('J2 Lijnen'!$J:$J,'J2 Lijnen'!$A:$A,$B4,'J2 Lijnen'!$E:$E,"verpakking") | S4: =-SUMIFS('J2 Lijnen'!$J:$J,'J2 Lijnen'!$A:$A,$B4,'J2 Lijnen'!$E:$E,"financiële korting") | T4: =SUM(N4:S4) | X4: U2027-03 | Y4: =SUMIFS('J2 Journaal'!$K:$K,'J2 Journaal'!$E:$E,$B4)-SUMIFS('J2 Journaal'!$L:$L,'J2 Journaal'!$E:$E,$B4)
A5: 4 | B5: J2A7 | C5: K1 | D5: K1 | E5: AK | F5: verpakking | G5: 46402 | H5: =G5+30 | I5: 2027-031 | J5: Velomax bv | K5: Fietsatelier Noor bv | N5: =SUMIFS('J2 Lijnen'!$J:$J,'J2 Lijnen'!$A:$A,$B5,'J2 Lijnen'!$K:$K,0.21,'J2 Lijnen'!$E:$E,"<>verpakking") | O5: =SUMIFS('J2 Lijnen'!$L:$L,'J2 Lijnen'!$A:$A,$B5,'J2 Lijnen'!$K:$K,0.21) | P5: =SUMIFS('J2 Lijnen'!$J:$J,'J2 Lijnen'!$A:$A,$B5,'J2 Lijnen'!$K:$K,0.06) | Q5: =SUMIFS('J2 Lijnen'!$L:$L,'J2 Lijnen'!$A:$A,$B5,'J2 Lijnen'!$K:$K,0.06) | R5: =SUMIFS('J2 Lijnen'!$J:$J,'J2 Lijnen'!$A:$A,$B5,'J2 Lijnen'!$E:$E,"verpakking") | S5: =-SUMIFS('J2 Lijnen'!$J:$J,'J2 Lijnen'!$A:$A,$B5,'J2 Lijnen'!$E:$E,"financiële korting") | T5: =SUM(N5:S5) | X5: U2027-06 | Y5: =SUMIFS('J2 Journaal'!$K:$K,'J2 Journaal'!$E:$E,$B5)-SUMIFS('J2 Journaal'!$L:$L,'J2 Journaal'!$E:$E,$B5)
A6: 5 | B6: J2A9 | C6: K1 | D6: K1 | E6: AK | F6: financiële korting | G6: 46409 | H6: =G6+30 | I6: 2027-052 | J6: Velomax bv | K6: Fietsatelier Noor bv | N6: =SUMIFS('J2 Lijnen'!$J:$J,'J2 Lijnen'!$A:$A,$B6,'J2 Lijnen'!$K:$K,0.21,'J2 Lijnen'!$E:$E,"<>verpakking") | O6: =SUMIFS('J2 Lijnen'!$L:$L,'J2 Lijnen'!$A:$A,$B6,'J2 Lijnen'!$K:$K,0.21) | P6: =SUMIFS('J2 Lijnen'!$J:$J,'J2 Lijnen'!$A:$A,$B6,'J2 Lijnen'!$K:$K,0.06) | Q6: =SUMIFS('J2 Lijnen'!$L:$L,'J2 Lijnen'!$A:$A,$B6,'J2 Lijnen'!$K:$K,0.06) | R6: =SUMIFS('J2 Lijnen'!$J:$J,'J2 Lijnen'!$A:$A,$B6,'J2 Lijnen'!$E:$E,"verpakking") | S6: =-SUMIFS('J2 Lijnen'!$J:$J,'J2 Lijnen'!$A:$A,$B6,'J2 Lijnen'!$E:$E,"financiële korting") | T6: =SUM(N6:S6) | U6: =T6-S6 | X6: U2027-03 | Y6: =SUMIFS('J2 Journaal'!$K:$K,'J2 Journaal'!$E:$E,$B6)-SUMIFS('J2 Journaal'!$L:$L,'J2 Journaal'!$E:$E,$B6) | Z6: 2% korting bij betaling binnen 10 dagen: binnen de termijn betaald
A7: 6 | B7: J2CA2 | C7: K1 | D7: K1 | E7: CN-AK | F7: met handelskorting | G7: 46401 | I7: CN-2027-002 | J7: Velomax bv | K7: Fietsatelier Noor bv | L7: 2027-014 | M7: 5 fietsen met herenframe i.p.v. damesframe, teruggestuurd | N7: =SUMIFS('J2 Lijnen'!$J:$J,'J2 Lijnen'!$A:$A,$B7,'J2 Lijnen'!$K:$K,0.21,'J2 Lijnen'!$E:$E,"<>verpakking") | O7: =SUMIFS('J2 Lijnen'!$L:$L,'J2 Lijnen'!$A:$A,$B7,'J2 Lijnen'!$K:$K,0.21) | P7: =SUMIFS('J2 Lijnen'!$J:$J,'J2 Lijnen'!$A:$A,$B7,'J2 Lijnen'!$K:$K,0.06) | Q7: =SUMIFS('J2 Lijnen'!$L:$L,'J2 Lijnen'!$A:$A,$B7,'J2 Lijnen'!$K:$K,0.06) | R7: =SUMIFS('J2 Lijnen'!$J:$J,'J2 Lijnen'!$A:$A,$B7,'J2 Lijnen'!$E:$E,"verpakking") | S7: =-SUMIFS('J2 Lijnen'!$J:$J,'J2 Lijnen'!$A:$A,$B7,'J2 Lijnen'!$E:$E,"financiële korting") | T7: =SUM(N7:S7) | X7: U2027-03 | Y7: =SUMIFS('J2 Journaal'!$K:$K,'J2 Journaal'!$E:$E,$B7)-SUMIFS('J2 Journaal'!$L:$L,'J2 Journaal'!$E:$E,$B7)
A8: 7 | B8: J2CA3 | C8: K1 | D8: K1 | E8: CN-AK | F8: verpakking terug | G8: 46443 | I8: CN-2027-009 | J8: Velomax bv | K8: Fietsatelier Noor bv | L8: 2027-031 | M8: 2 fietsrekken teruggestuurd | N8: =SUMIFS('J2 Lijnen'!$J:$J,'J2 Lijnen'!$A:$A,$B8,'J2 Lijnen'!$K:$K,0.21,'J2 Lijnen'!$E:$E,"<>verpakking") | O8: =SUMIFS('J2 Lijnen'!$L:$L,'J2 Lijnen'!$A:$A,$B8,'J2 Lijnen'!$K:$K,0.21) | P8: =SUMIFS('J2 Lijnen'!$J:$J,'J2 Lijnen'!$A:$A,$B8,'J2 Lijnen'!$K:$K,0.06) | Q8: =SUMIFS('J2 Lijnen'!$L:$L,'J2 Lijnen'!$A:$A,$B8,'J2 Lijnen'!$K:$K,0.06) | R8: =SUMIFS('J2 Lijnen'!$J:$J,'J2 Lijnen'!$A:$A,$B8,'J2 Lijnen'!$E:$E,"verpakking") | S8: =-SUMIFS('J2 Lijnen'!$J:$J,'J2 Lijnen'!$A:$A,$B8,'J2 Lijnen'!$E:$E,"financiële korting") | T8: =SUM(N8:S8) | X8: U2027-06 | Y8: =SUMIFS('J2 Journaal'!$K:$K,'J2 Journaal'!$E:$E,$B8)-SUMIFS('J2 Journaal'!$L:$L,'J2 Journaal'!$E:$E,$B8)
A9: 8 | B9: J2V2 | C9: K1 | D9: K1 | E9: VK | F9: eenvoudig | G9: 46400 | H9: =G9+30 | I9: 2027-002 | J9: Fietsatelier Noor bv | K9: Snelpost bv | N9: =SUMIFS('J2 Lijnen'!$J:$J,'J2 Lijnen'!$A:$A,$B9,'J2 Lijnen'!$K:$K,0.21,'J2 Lijnen'!$E:$E,"<>verpakking") | O9: =SUMIFS('J2 Lijnen'!$L:$L,'J2 Lijnen'!$A:$A,$B9,'J2 Lijnen'!$K:$K,0.21) | P9: =SUMIFS('J2 Lijnen'!$J:$J,'J2 Lijnen'!$A:$A,$B9,'J2 Lijnen'!$K:$K,0.06) | Q9: =SUMIFS('J2 Lijnen'!$L:$L,'J2 Lijnen'!$A:$A,$B9,'J2 Lijnen'!$K:$K,0.06) | R9: =SUMIFS('J2 Lijnen'!$J:$J,'J2 Lijnen'!$A:$A,$B9,'J2 Lijnen'!$E:$E,"verpakking") | S9: =-SUMIFS('J2 Lijnen'!$J:$J,'J2 Lijnen'!$A:$A,$B9,'J2 Lijnen'!$E:$E,"financiële korting") | T9: =SUM(N9:S9) | X9: U2027-03 | Y9: =SUMIFS('J2 Journaal'!$K:$K,'J2 Journaal'!$E:$E,$B9)-SUMIFS('J2 Journaal'!$L:$L,'J2 Journaal'!$E:$E,$B9)
A10: 9 | B10: J2V3 | C10: K1 | D10: K1 | E10: VK | F10: handelskorting | G10: 46406 | H10: =G10+30 | I10: 2027-003 | J10: Fietsatelier Noor bv | K10: Velocity Deelfietsen bv | N10: =SUMIFS('J2 Lijnen'!$J:$J,'J2 Lijnen'!$A:$A,$B10,'J2 Lijnen'!$K:$K,0.21,'J2 Lijnen'!$E:$E,"<>verpakking") | O10: =SUMIFS('J2 Lijnen'!$L:$L,'J2 Lijnen'!$A:$A,$B10,'J2 Lijnen'!$K:$K,0.21) | P10: =SUMIFS('J2 Lijnen'!$J:$J,'J2 Lijnen'!$A:$A,$B10,'J2 Lijnen'!$K:$K,0.06) | Q10: =SUMIFS('J2 Lijnen'!$L:$L,'J2 Lijnen'!$A:$A,$B10,'J2 Lijnen'!$K:$K,0.06) | R10: =SUMIFS('J2 Lijnen'!$J:$J,'J2 Lijnen'!$A:$A,$B10,'J2 Lijnen'!$E:$E,"verpakking") | S10: =-SUMIFS('J2 Lijnen'!$J:$J,'J2 Lijnen'!$A:$A,$B10,'J2 Lijnen'!$E:$E,"financiële korting") | T10: =SUM(N10:S10) | X10: U2027-05 | Y10: =SUMIFS('J2 Journaal'!$K:$K,'J2 Journaal'!$E:$E,$B10)-SUMIFS('J2 Journaal'!$L:$L,'J2 Journaal'!$E:$E,$B10)
A11: 10 | B11: J2V5 | C11: K1 | D11: K1 | E11: VK | F11: kosten | G11: 46434 | H11: =G11+30 | I11: 2027-005 | J11: Fietsatelier Noor bv | K11: Camping De Vlinder bv | N11: =SUMIFS('J2 Lijnen'!$J:$J,'J2 Lijnen'!$A:$A,$B11,'J2 Lijnen'!$K:$K,0.21,'J2 Lijnen'!$E:$E,"<>verpakking") | O11: =SUMIFS('J2 Lijnen'!$L:$L,'J2 Lijnen'!$A:$A,$B11,'J2 Lijnen'!$K:$K,0.21) | P11: =SUMIFS('J2 Lijnen'!$J:$J,'J2 Lijnen'!$A:$A,$B11,'J2 Lijnen'!$K:$K,0.06) | Q11: =SUMIFS('J2 Lijnen'!$L:$L,'J2 Lijnen'!$A:$A,$B11,'J2 Lijnen'!$K:$K,0.06) | R11: =SUMIFS('J2 Lijnen'!$J:$J,'J2 Lijnen'!$A:$A,$B11,'J2 Lijnen'!$E:$E,"verpakking") | S11: =-SUMIFS('J2 Lijnen'!$J:$J,'J2 Lijnen'!$A:$A,$B11,'J2 Lijnen'!$E:$E,"financiële korting") | T11: =SUM(N11:S11) | X11: U2027-08 | Y11: =SUMIFS('J2 Journaal'!$K:$K,'J2 Journaal'!$E:$E,$B11)-SUMIFS('J2 Journaal'!$L:$L,'J2 Journaal'!$E:$E,$B11)
A12: 11 | B12: J2V7 | C12: K1 | D12: K1 | E12: VK | F12: verpakking | G12: 46442 | H12: =G12+30 | I12: 2027-007 | J12: Fietsatelier Noor bv | K12: Snelpost bv | N12: =SUMIFS('J2 Lijnen'!$J:$J,'J2 Lijnen'!$A:$A,$B12,'J2 Lijnen'!$K:$K,0.21,'J2 Lijnen'!$E:$E,"<>verpakking") | O12: =SUMIFS('J2 Lijnen'!$L:$L,'J2 Lijnen'!$A:$A,$B12,'J2 Lijnen'!$K:$K,0.21) | P12: =SUMIFS('J2 Lijnen'!$J:$J,'J2 Lijnen'!$A:$A,$B12,'J2 Lijnen'!$K:$K,0.06) | Q12: =SUMIFS('J2 Lijnen'!$L:$L,'J2 Lijnen'!$A:$A,$B12,'J2 Lijnen'!$K:$K,0.06) | R12: =SUMIFS('J2 Lijnen'!$J:$J,'J2 Lijnen'!$A:$A,$B12,'J2 Lijnen'!$E:$E,"verpakking") | S12: =-SUMIFS('J2 Lijnen'!$J:$J,'J2 Lijnen'!$A:$A,$B12,'J2 Lijnen'!$E:$E,"financiële korting") | T12: =SUM(N12:S12) | X12: U2027-08 | Y12: =SUMIFS('J2 Journaal'!$K:$K,'J2 Journaal'!$E:$E,$B12)-SUMIFS('J2 Journaal'!$L:$L,'J2 Journaal'!$E:$E,$B12)
A13: 12 | B13: J2V9 | C13: K1 | D13: K1 | E13: VK | F13: financiële korting | G13: 46412 | H13: =G13+30 | I13: 2027-025 | J13: Fietsatelier Noor bv | K13: Studio Kowalski bv | N13: =SUMIFS('J2 Lijnen'!$J:$J,'J2 Lijnen'!$A:$A,$B13,'J2 Lijnen'!$K:$K,0.21,'J2 Lijnen'!$E:$E,"<>verpakking") | O13: =SUMIFS('J2 Lijnen'!$L:$L,'J2 Lijnen'!$A:$A,$B13,'J2 Lijnen'!$K:$K,0.21) | P13: =SUMIFS('J2 Lijnen'!$J:$J,'J2 Lijnen'!$A:$A,$B13,'J2 Lijnen'!$K:$K,0.06) | Q13: =SUMIFS('J2 Lijnen'!$L:$L,'J2 Lijnen'!$A:$A,$B13,'J2 Lijnen'!$K:$K,0.06) | R13: =SUMIFS('J2 Lijnen'!$J:$J,'J2 Lijnen'!$A:$A,$B13,'J2 Lijnen'!$E:$E,"verpakking") | S13: =-SUMIFS('J2 Lijnen'!$J:$J,'J2 Lijnen'!$A:$A,$B13,'J2 Lijnen'!$E:$E,"financiële korting") | T13: =SUM(N13:S13) | U13: =T13-S13 | X13: U2027-04 | Y13: =SUMIFS('J2 Journaal'!$K:$K,'J2 Journaal'!$E:$E,$B13)-SUMIFS('J2 Journaal'!$L:$L,'J2 Journaal'!$E:$E,$B13) | Z13: 4% korting bij betaling binnen 10 dagen: binnen de termijn betaald
A14: 13 | B14: J2CV2 | C14: K1 | D14: K1 | E14: CN-VK | F14: met handelskorting | G14: 46413 | I14: CN-2027-002 | J14: Fietsatelier Noor bv | K14: Velocity Deelfietsen bv | L14: 2027-003 | M14: 5 fietsen teruggenomen: te veel besteld | N14: =SUMIFS('J2 Lijnen'!$J:$J,'J2 Lijnen'!$A:$A,$B14,'J2 Lijnen'!$K:$K,0.21,'J2 Lijnen'!$E:$E,"<>verpakking") | O14: =SUMIFS('J2 Lijnen'!$L:$L,'J2 Lijnen'!$A:$A,$B14,'J2 Lijnen'!$K:$K,0.21) | P14: =SUMIFS('J2 Lijnen'!$J:$J,'J2 Lijnen'!$A:$A,$B14,'J2 Lijnen'!$K:$K,0.06) | Q14: =SUMIFS('J2 Lijnen'!$L:$L,'J2 Lijnen'!$A:$A,$B14,'J2 Lijnen'!$K:$K,0.06) | R14: =SUMIFS('J2 Lijnen'!$J:$J,'J2 Lijnen'!$A:$A,$B14,'J2 Lijnen'!$E:$E,"verpakking") | S14: =-SUMIFS('J2 Lijnen'!$J:$J,'J2 Lijnen'!$A:$A,$B14,'J2 Lijnen'!$E:$E,"financiële korting") | T14: =SUM(N14:S14) | X14: U2027-05 | Y14: =SUMIFS('J2 Journaal'!$K:$K,'J2 Journaal'!$E:$E,$B14)-SUMIFS('J2 Journaal'!$L:$L,'J2 Journaal'!$E:$E,$B14)
A15: 14 | B15: J2CV3 | C15: K1 | D15: K1 | E15: CN-VK | F15: verpakking terug | G15: 46456 | I15: CN-2027-003 | J15: Fietsatelier Noor bv | K15: Snelpost bv | L15: 2027-007 | M15: 3 fietsrekken terugontvangen | N15: =SUMIFS('J2 Lijnen'!$J:$J,'J2 Lijnen'!$A:$A,$B15,'J2 Lijnen'!$K:$K,0.21,'J2 Lijnen'!$E:$E,"<>verpakking") | O15: =SUMIFS('J2 Lijnen'!$L:$L,'J2 Lijnen'!$A:$A,$B15,'J2 Lijnen'!$K:$K,0.21) | P15: =SUMIFS('J2 Lijnen'!$J:$J,'J2 Lijnen'!$A:$A,$B15,'J2 Lijnen'!$K:$K,0.06) | Q15: =SUMIFS('J2 Lijnen'!$L:$L,'J2 Lijnen'!$A:$A,$B15,'J2 Lijnen'!$K:$K,0.06) | R15: =SUMIFS('J2 Lijnen'!$J:$J,'J2 Lijnen'!$A:$A,$B15,'J2 Lijnen'!$E:$E,"verpakking") | S15: =-SUMIFS('J2 Lijnen'!$J:$J,'J2 Lijnen'!$A:$A,$B15,'J2 Lijnen'!$E:$E,"financiële korting") | T15: =SUM(N15:S15) | X15: U2027-08 | Y15: =SUMIFS('J2 Journaal'!$K:$K,'J2 Journaal'!$E:$E,$B15)-SUMIFS('J2 Journaal'!$L:$L,'J2 Journaal'!$E:$E,$B15)
A16: 15 | B16: J2D1 | C16: K1 | D16: K1 | E16: DO | F16: dagontvangst | G16: 46403 | I16: DO-2027-01 | J16: Fietsatelier Noor bv | K16: particulieren (kasticket) | M16: Dagontvangsten winkel (verkopen aan particulieren) | N16: =SUMIFS('J2 Lijnen'!$J:$J,'J2 Lijnen'!$A:$A,$B16,'J2 Lijnen'!$K:$K,0.21,'J2 Lijnen'!$E:$E,"<>verpakking") | O16: =SUMIFS('J2 Lijnen'!$L:$L,'J2 Lijnen'!$A:$A,$B16,'J2 Lijnen'!$K:$K,0.21) | P16: =SUMIFS('J2 Lijnen'!$J:$J,'J2 Lijnen'!$A:$A,$B16,'J2 Lijnen'!$K:$K,0.06) | Q16: =SUMIFS('J2 Lijnen'!$L:$L,'J2 Lijnen'!$A:$A,$B16,'J2 Lijnen'!$K:$K,0.06) | R16: =SUMIFS('J2 Lijnen'!$J:$J,'J2 Lijnen'!$A:$A,$B16,'J2 Lijnen'!$E:$E,"verpakking") | S16: =-SUMIFS('J2 Lijnen'!$J:$J,'J2 Lijnen'!$A:$A,$B16,'J2 Lijnen'!$E:$E,"financiële korting") | T16: =SUM(N16:S16) | V16: =T16-W16 | W16: 1000 | X16: J2D1K, U2027-03 | Y16: =SUMIFS('J2 Journaal'!$K:$K,'J2 Journaal'!$E:$E,$B16)-SUMIFS('J2 Journaal'!$L:$L,'J2 Journaal'!$E:$E,$B16)
A17: 16 | B17: J2D1K | C17: K1 | D17: K1 | E17: KAS | F17: ontvangst | G17: 46403 | I17: Kasboek DO-2027-01 | J17: Fietsatelier Noor bv | K17: Fietsatelier Noor bv | L17: DO-2027-01 | M17: Contant deel van dagontvangst DO-2027-01 (laat de vordering op de klanten dalen) | T17: 891 | V17: 891 | Y17: =SUMIFS('J2 Journaal'!$K:$K,'J2 Journaal'!$E:$E,$B17)-SUMIFS('J2 Journaal'!$L:$L,'J2 Journaal'!$E:$E,$B17)
A18: 17 | B18: J2BTW1 | C18: K1 | D18: K1 | E18: MEMO | F18: btw-verrekening | G18: 46477 | I18: J2BTW1 | M18: Btw-verrekening 1e kwartaal 2027 | Y18: =SUMIFS('J2 Journaal'!$K:$K,'J2 Journaal'!$E:$E,$B18)-SUMIFS('J2 Journaal'!$L:$L,'J2 Journaal'!$E:$E,$B18)
A19: 19 | B19: J2K1 | C19: K1 | D19: K1 | E19: KAS | F19: storting | G19: 46407 | I19: KAS-2027-01 | J19: Fietsatelier Noor bv | K19: Fietsatelier Noor bv | M19: Storting contanten van de kassa naar de bank | T19: 2000 | V19: -2000 | Y19: =SUMIFS('J2 Journaal'!$K:$K,'J2 Journaal'!$E:$E,$B19)-SUMIFS('J2 Journaal'!$L:$L,'J2 Journaal'!$E:$E,$B19)
A20: 25 | B20: J2K2 | C20: K1 | D20: K1 | E20: KAS | F20: afhaling | G20: 46447 | I20: KAS-2027-02 | J20: Fietsatelier Noor bv | K20: Fietsatelier Noor bv | M20: Afhaling wisselgeld van de bank voor de kassa | T20: 300 | V20: 300 | Y20: =SUMIFS('J2 Journaal'!$K:$K,'J2 Journaal'!$E:$E,$B20)-SUMIFS('J2 Journaal'!$L:$L,'J2 Journaal'!$E:$E,$B20)
A21: 1 | B21: J2Q2A1 | C21: K2 | D21: K2 | E21: AK | F21: handelskorting + verpakking | G21: 46478 | H21: =G21+30 | I21: 2027-198 | J21: Velomax bv | K21: Fietsatelier Noor bv | N21: =SUMIFS('J2 Lijnen'!$J:$J,'J2 Lijnen'!$A:$A,$B21,'J2 Lijnen'!$K:$K,0.21,'J2 Lijnen'!$E:$E,"<>verpakking") | O21: =SUMIFS('J2 Lijnen'!$L:$L,'J2 Lijnen'!$A:$A,$B21,'J2 Lijnen'!$K:$K,0.21) | P21: =SUMIFS('J2 Lijnen'!$J:$J,'J2 Lijnen'!$A:$A,$B21,'J2 Lijnen'!$K:$K,0.06) | Q21: =SUMIFS('J2 Lijnen'!$L:$L,'J2 Lijnen'!$A:$A,$B21,'J2 Lijnen'!$K:$K,0.06) | R21: =SUMIFS('J2 Lijnen'!$J:$J,'J2 Lijnen'!$A:$A,$B21,'J2 Lijnen'!$E:$E,"verpakking") | S21: =-SUMIFS('J2 Lijnen'!$J:$J,'J2 Lijnen'!$A:$A,$B21,'J2 Lijnen'!$E:$E,"financiële korting") | T21: =SUM(N21:S21) | X21: U2027-09 | Y21: =SUMIFS('J2 Journaal'!$K:$K,'J2 Journaal'!$E:$E,$B21)-SUMIFS('J2 Journaal'!$L:$L,'J2 Journaal'!$E:$E,$B21)
A22: 2 | B22: J2Q2A2 | C22: K2 | D22: K2 | E22: AK | F22: eenvoudig | G22: 46484 | H22: =G22+30 | I22: SK-27-1104 | J22: Stroomkracht nv | K22: Fietsatelier Noor bv | N22: =SUMIFS('J2 Lijnen'!$J:$J,'J2 Lijnen'!$A:$A,$B22,'J2 Lijnen'!$K:$K,0.21,'J2 Lijnen'!$E:$E,"<>verpakking") | O22: =SUMIFS('J2 Lijnen'!$L:$L,'J2 Lijnen'!$A:$A,$B22,'J2 Lijnen'!$K:$K,0.21) | P22: =SUMIFS('J2 Lijnen'!$J:$J,'J2 Lijnen'!$A:$A,$B22,'J2 Lijnen'!$K:$K,0.06) | Q22: =SUMIFS('J2 Lijnen'!$L:$L,'J2 Lijnen'!$A:$A,$B22,'J2 Lijnen'!$K:$K,0.06) | R22: =SUMIFS('J2 Lijnen'!$J:$J,'J2 Lijnen'!$A:$A,$B22,'J2 Lijnen'!$E:$E,"verpakking") | S22: =-SUMIFS('J2 Lijnen'!$J:$J,'J2 Lijnen'!$A:$A,$B22,'J2 Lijnen'!$E:$E,"financiële korting") | T22: =SUM(N22:S22) | X22: U2027-09 | Y22: =SUMIFS('J2 Journaal'!$K:$K,'J2 Journaal'!$E:$E,$B22)-SUMIFS('J2 Journaal'!$L:$L,'J2 Journaal'!$E:$E,$B22)
A23: 3 | B23: J2Q2CA1 | C23: K2 | D23: K2 | E23: CN-AK | F23: met handelskorting | G23: 46487 | I23: CN-2027-021 | J23: Velomax bv | K23: Fietsatelier Noor bv | L23: 2027-198 | M23: 5 fietsen van het verkeerde model geleverd, teruggestuurd | N23: =SUMIFS('J2 Lijnen'!$J:$J,'J2 Lijnen'!$A:$A,$B23,'J2 Lijnen'!$K:$K,0.21,'J2 Lijnen'!$E:$E,"<>verpakking") | O23: =SUMIFS('J2 Lijnen'!$L:$L,'J2 Lijnen'!$A:$A,$B23,'J2 Lijnen'!$K:$K,0.21) | P23: =SUMIFS('J2 Lijnen'!$J:$J,'J2 Lijnen'!$A:$A,$B23,'J2 Lijnen'!$K:$K,0.06) | Q23: =SUMIFS('J2 Lijnen'!$L:$L,'J2 Lijnen'!$A:$A,$B23,'J2 Lijnen'!$K:$K,0.06) | R23: =SUMIFS('J2 Lijnen'!$J:$J,'J2 Lijnen'!$A:$A,$B23,'J2 Lijnen'!$E:$E,"verpakking") | S23: =-SUMIFS('J2 Lijnen'!$J:$J,'J2 Lijnen'!$A:$A,$B23,'J2 Lijnen'!$E:$E,"financiële korting") | T23: =SUM(N23:S23) | X23: U2027-09 | Y23: =SUMIFS('J2 Journaal'!$K:$K,'J2 Journaal'!$E:$E,$B23)-SUMIFS('J2 Journaal'!$L:$L,'J2 Journaal'!$E:$E,$B23)
A24: 4 | B24: J2Q2A4 | C24: K2 | D24: K2 | E24: AK | F24: kosten | G24: 46513 | H24: =G24+30 | I24: HH-27-102 | J24: HelmHuis bv | K24: Fietsatelier Noor bv | N24: =SUMIFS('J2 Lijnen'!$J:$J,'J2 Lijnen'!$A:$A,$B24,'J2 Lijnen'!$K:$K,0.21,'J2 Lijnen'!$E:$E,"<>verpakking") | O24: =SUMIFS('J2 Lijnen'!$L:$L,'J2 Lijnen'!$A:$A,$B24,'J2 Lijnen'!$K:$K,0.21) | P24: =SUMIFS('J2 Lijnen'!$J:$J,'J2 Lijnen'!$A:$A,$B24,'J2 Lijnen'!$K:$K,0.06) | Q24: =SUMIFS('J2 Lijnen'!$L:$L,'J2 Lijnen'!$A:$A,$B24,'J2 Lijnen'!$K:$K,0.06) | R24: =SUMIFS('J2 Lijnen'!$J:$J,'J2 Lijnen'!$A:$A,$B24,'J2 Lijnen'!$E:$E,"verpakking") | S24: =-SUMIFS('J2 Lijnen'!$J:$J,'J2 Lijnen'!$A:$A,$B24,'J2 Lijnen'!$E:$E,"financiële korting") | T24: =SUM(N24:S24) | X24: U2027-11 | Y24: =SUMIFS('J2 Journaal'!$K:$K,'J2 Journaal'!$E:$E,$B24)-SUMIFS('J2 Journaal'!$L:$L,'J2 Journaal'!$E:$E,$B24)
A25: 5 | B25: J2Q2A7 | C25: K2 | D25: K2 | E25: AK | F25: financiële korting | G25: 46519 | H25: =G25+30 | I25: 2027-244 | J25: Velomax bv | K25: Fietsatelier Noor bv | N25: =SUMIFS('J2 Lijnen'!$J:$J,'J2 Lijnen'!$A:$A,$B25,'J2 Lijnen'!$K:$K,0.21,'J2 Lijnen'!$E:$E,"<>verpakking") | O25: =SUMIFS('J2 Lijnen'!$L:$L,'J2 Lijnen'!$A:$A,$B25,'J2 Lijnen'!$K:$K,0.21) | P25: =SUMIFS('J2 Lijnen'!$J:$J,'J2 Lijnen'!$A:$A,$B25,'J2 Lijnen'!$K:$K,0.06) | Q25: =SUMIFS('J2 Lijnen'!$L:$L,'J2 Lijnen'!$A:$A,$B25,'J2 Lijnen'!$K:$K,0.06) | R25: =SUMIFS('J2 Lijnen'!$J:$J,'J2 Lijnen'!$A:$A,$B25,'J2 Lijnen'!$E:$E,"verpakking") | S25: =-SUMIFS('J2 Lijnen'!$J:$J,'J2 Lijnen'!$A:$A,$B25,'J2 Lijnen'!$E:$E,"financiële korting") | T25: =SUM(N25:S25) | U25: =T25-S25 | X25: U2027-11 | Y25: =SUMIFS('J2 Journaal'!$K:$K,'J2 Journaal'!$E:$E,$B25)-SUMIFS('J2 Journaal'!$L:$L,'J2 Journaal'!$E:$E,$B25) | Z25: 5% korting binnen 10 dagen: binnen de termijn betaald
A26: 6 | B26: J2Q2A5 | C26: K2 | D26: K2 | E26: AK | F26: handelskorting + kosten + verpakking | G26: 46527 | H26: =G26+30 | I26: 2027-260 | J26: Velomax bv | K26: Fietsatelier Noor bv | N26: =SUMIFS('J2 Lijnen'!$J:$J,'J2 Lijnen'!$A:$A,$B26,'J2 Lijnen'!$K:$K,0.21,'J2 Lijnen'!$E:$E,"<>verpakking") | O26: =SUMIFS('J2 Lijnen'!$L:$L,'J2 Lijnen'!$A:$A,$B26,'J2 Lijnen'!$K:$K,0.21) | P26: =SUMIFS('J2 Lijnen'!$J:$J,'J2 Lijnen'!$A:$A,$B26,'J2 Lijnen'!$K:$K,0.06) | Q26: =SUMIFS('J2 Lijnen'!$L:$L,'J2 Lijnen'!$A:$A,$B26,'J2 Lijnen'!$K:$K,0.06) | R26: =SUMIFS('J2 Lijnen'!$J:$J,'J2 Lijnen'!$A:$A,$B26,'J2 Lijnen'!$E:$E,"verpakking") | S26: =-SUMIFS('J2 Lijnen'!$J:$J,'J2 Lijnen'!$A:$A,$B26,'J2 Lijnen'!$E:$E,"financiële korting") | T26: =SUM(N26:S26) | X26: U2027-12 | Y26: =SUMIFS('J2 Journaal'!$K:$K,'J2 Journaal'!$E:$E,$B26)-SUMIFS('J2 Journaal'!$L:$L,'J2 Journaal'!$E:$E,$B26)
A27: 7 | B27: J2Q2CA2 | C27: K2 | D27: K2 | E27: CN-AK | F27: verpakking terug | G27: 46532 | I27: CN-2027-030 | J27: Velomax bv | K27: Fietsatelier Noor bv | L27: 2027-198 | M27: 4 fietsrekken teruggestuurd | N27: =SUMIFS('J2 Lijnen'!$J:$J,'J2 Lijnen'!$A:$A,$B27,'J2 Lijnen'!$K:$K,0.21,'J2 Lijnen'!$E:$E,"<>verpakking") | O27: =SUMIFS('J2 Lijnen'!$L:$L,'J2 Lijnen'!$A:$A,$B27,'J2 Lijnen'!$K:$K,0.21) | P27: =SUMIFS('J2 Lijnen'!$J:$J,'J2 Lijnen'!$A:$A,$B27,'J2 Lijnen'!$K:$K,0.06) | Q27: =SUMIFS('J2 Lijnen'!$L:$L,'J2 Lijnen'!$A:$A,$B27,'J2 Lijnen'!$K:$K,0.06) | R27: =SUMIFS('J2 Lijnen'!$J:$J,'J2 Lijnen'!$A:$A,$B27,'J2 Lijnen'!$E:$E,"verpakking") | S27: =-SUMIFS('J2 Lijnen'!$J:$J,'J2 Lijnen'!$A:$A,$B27,'J2 Lijnen'!$E:$E,"financiële korting") | T27: =SUM(N27:S27) | X27: U2027-12 | Y27: =SUMIFS('J2 Journaal'!$K:$K,'J2 Journaal'!$E:$E,$B27)-SUMIFS('J2 Journaal'!$L:$L,'J2 Journaal'!$E:$E,$B27)
A28: 8 | B28: J2Q2V1 | C28: K2 | D28: K2 | E28: VK | F28: eenvoudig | G28: 46485 | H28: =G28+30 | I28: 2027-009 | J28: Fietsatelier Noor bv | K28: Woonzorgcentrum Zonnehof vzw | N28: =SUMIFS('J2 Lijnen'!$J:$J,'J2 Lijnen'!$A:$A,$B28,'J2 Lijnen'!$K:$K,0.21,'J2 Lijnen'!$E:$E,"<>verpakking") | O28: =SUMIFS('J2 Lijnen'!$L:$L,'J2 Lijnen'!$A:$A,$B28,'J2 Lijnen'!$K:$K,0.21) | P28: =SUMIFS('J2 Lijnen'!$J:$J,'J2 Lijnen'!$A:$A,$B28,'J2 Lijnen'!$K:$K,0.06) | Q28: =SUMIFS('J2 Lijnen'!$L:$L,'J2 Lijnen'!$A:$A,$B28,'J2 Lijnen'!$K:$K,0.06) | R28: =SUMIFS('J2 Lijnen'!$J:$J,'J2 Lijnen'!$A:$A,$B28,'J2 Lijnen'!$E:$E,"verpakking") | S28: =-SUMIFS('J2 Lijnen'!$J:$J,'J2 Lijnen'!$A:$A,$B28,'J2 Lijnen'!$E:$E,"financiële korting") | T28: =SUM(N28:S28) | X28: U2027-11 | Y28: =SUMIFS('J2 Journaal'!$K:$K,'J2 Journaal'!$E:$E,$B28)-SUMIFS('J2 Journaal'!$L:$L,'J2 Journaal'!$E:$E,$B28)
